Workbook
Name Cash_minimum: 'CF Realisasi new'!$B$7
Name Cash_minimum: 'CF Realisasi'!$B$7

Sheet Graph
A1: JUMAT | B1: SABTU | C1: MINGGU | D1: SENIN | E1: SELASA | F1: RABU | G1: KAMIS | H1: JUMAT | I1: SABTU | J1: MINGGU | K1: SENIN | L1: SELASA | M1: RABU | N1: KAMIS | O1: JUMAT | P1: SABTU
A2: 45947 | B2: 45948 | C2: 45949 | D2: 45950 | E2: 45951 | F2: 45952 | G2: 45953 | H2: 45954 | I2: 45955 | J2: 45956 | K2: 45957 | L2: 45958 | M2: 45959 | N2: 45960 | O2: 45961 | P2: 45962
A3: ='CF Realisasi new'!C10 -> -1.4106224e+08 | B3: ='CF Realisasi new'!D10 -> -1.4106224e+08 | C3: ='CF Realisasi new'!E10 -> -1.4106224e+08 | D3: ='CF Realisasi new'!F10 -> 6.7873954e+08 | E3: ='CF Realisasi new'!G10 -> -6.2786446e+08 | F3: ='CF Realisasi new'!H10 -> -4.1149744e+08 | G3: ='CF Realisasi new'!I10 -> -1.111319e+09 | H3: ='CF Realisasi new'!J10 -> -2.2747996e+08 | ... P3: ='CF Realisasi new'!R10 -> 3.5587354e+09
D30: Blm minus tp perlu waspada | G30: Blm minus tp perlu waspada

Sheet CF Realisasi
A1: Cash Flow Realization
A2: PT. Werkudara Nirwana Sakti
A6: Period | B6: 45778
A7: Cash balance alert minimum | B7: 200000000
A8: Updated on | B8: 45823 | C8: Minggu | D8: Senin | E8: Selasa | F8: Rabu | G8: Kamis | H8: Jumat | I8: Sabtu | J8: Minggu | K8: Senin | L8: Selasa | M8: Rabu | N8: Kamis | O8: Jumat | P8: Sabtu | Q8: Minggu | R8: Senin | S8: Selasa | T8: Rabu | U8: Kamis | V8: Jumat | W8: Sabtu | X8: Minggu | Y8: Senin | Z8: Selasa | AA8: Rabu | AB8: Kamis | AC8: Jumat | AD8: Sabtu | AE8: Minggu | AF8: Senin | AG8: Selasa | AH8: Rabu | AI8: Kamis | AJ8: Jumat | AK8: Sabtu | AL8: Minggu | AM8: Senin | AN8: Selasa | AO8: Rabu | AP8: Kamis | AQ8: Jumat | AR8: Sabtu | AS8: Minggu | AT8: Senin | AU8: Selasa | AV8: Rabu | AW8: Kamis | AX8: Jumat
B9: Beginning | C9: 45823 | D9: 45824 | E9: 45825 | F9: 45826 | G9: 45827 | H9: 45828 | I9: 45829 | J9: 45830 | K9: 45831 | L9: 45832 | M9: 45833 | N9: 45834 | O9: 45835 | P9: 45836 | Q9: 45837 | R9: 45838 | S9: 45839 | T9: 45840 | U9: 45841 | V9: 45842 | W9: 45843 | X9: 45844 | Y9: 45845 | Z9: 45846 | AA9: 45847 | AB9: 45848 | AC9: 45849 | AD9: 45850 | AE9: 45851 | AF9: 45852 | AG9: 45853 | AH9: 45854 | AI9: 45855 | AJ9: 45856 | AK9: 45857 | AL9: 45858 | AM9: 45859 | AN9: 45860 | AO9: 45861 | AP9: 45862 | AQ9: 45863 | AR9: 45864 | AS9: 45865 | AT9: 45866 | AU9: 45867 | AV9: 45868 | AW9: 45869 | AX9: 45870 | AY9: TOTAL
A10: Cash on hand (beginning of month) CF.9 | B10: =#REF! -> #REF! | C10: =B10 -> #REF! | D10: =(C10+D16)-D32 -> #REF! | E10: =(D10+E16)-E32 -> #REF! | F10: =(E10+F16)-F32 -> #REF! | G10: =(F10+G16)-G32 -> #REF! | H10: =(G10+H16)-H32 -> #REF! | I10: =(H10+I16)-I32 -> #REF! | J10: =(I10+J16)-J32 -> #REF! | K10: =(J10+K16)-K32 -> #REF! | ... AX10: =(AW10+AX16)-AX32 -> #REF! | AY10: =SUM(B10:B10:AY10) -> #REF!
A12: PENERIMAAN CASH | AY12: =SUM(B12:B12:AY12) -> 0
A13: Piutang & Revenue | B13: CF.1 | C13: ='IN-ACC-Piutang & Revenue'!#REF! -> #REF! | D13: ='IN-ACC-Piutang & Revenue'!#REF! -> #REF! | E13: ='IN-ACC-Piutang & Revenue'!#REF! -> #REF! | F13: ='IN-ACC-Piutang & Revenue'!#REF! -> #REF! | G13: ='IN-ACC-Piutang & Revenue'!#REF! -> #REF! | H13: ='IN-ACC-Piutang & Revenue'!#REF! -> #REF! | I13: ='IN-ACC-Piutang & Revenue'!#REF! -> #REF! | J13: ='IN-ACC-Piutang & Revenue'!#REF! -> #REF! | ... AX13: ='IN-ACC-Piutang & Revenue'!#REF! -> #REF! | AY13: =SUM(C13:AX13) -> #REF!
A14: Penerimaan Pengembalian Pinjaman | B14: CF.11 | C14: ='IN-CFC-Penerimaan PengemPinj'!#REF! -> #REF! | D14: ='IN-CFC-Penerimaan PengemPinj'!#REF! -> #REF! | E14: ='IN-CFC-Penerimaan PengemPinj'!#REF! -> #REF! | F14: ='IN-CFC-Penerimaan PengemPinj'!#REF! -> #REF! | G14: ='IN-CFC-Penerimaan PengemPinj'!#REF! -> #REF! | H14: ='IN-CFC-Penerimaan PengemPinj'!#REF! -> #REF! | I14: ='IN-CFC-Penerimaan PengemPinj'!#REF! -> #REF! | J14: ='IN-CFC-Penerimaan PengemPinj'!#REF! -> #REF! | ... AX14: ='IN-CFC-Penerimaan PengemPinj'!#REF! -> #REF! | AY14: =SUM(C14:AX14) -> #REF!
A15: Suntikan Modal | C15: ='IN-CFC-Suntikan Modal'!#REF! -> #REF! | D15: ='IN-CFC-Suntikan Modal'!#REF! -> #REF! | E15: ='IN-CFC-Suntikan Modal'!#REF! -> #REF! | F15: ='IN-CFC-Suntikan Modal'!#REF! -> #REF! | G15: ='IN-CFC-Suntikan Modal'!#REF! -> #REF! | H15: ='IN-CFC-Suntikan Modal'!#REF! -> #REF! | I15: ='IN-CFC-Suntikan Modal'!#REF! -> #REF! | J15: ='IN-CFC-Suntikan Modal'!#REF! -> #REF! | ... AX15: ='IN-CFC-Suntikan Modal'!#REF! -> #REF! | AY15: =SUM(C15:AX15) -> #REF!
A16: TOTAL CASH RECEIPTS | D16: =SUM(D13:D15) -> #REF! | E16: =SUM(E13:E15) -> #REF! | F16: =SUM(F13:F15) -> #REF! | G16: =SUM(G13:G15) -> #REF! | H16: =SUM(H13:H15) -> #REF! | I16: =SUM(I13:I15) -> #REF! | J16: =SUM(J13:J15) -> #REF! | K16: =SUM(K13:K15) -> #REF! | ... AX16: =SUM(AX13:AX15) -> #REF! | AY16: =SUM(D16:AX16) -> #REF!
A18: CASH PAID OUT | AY18: =SUM(B18:B18:AY18) -> 0
A19: Pajak | B19: CF.10 | C19: ='OUT-ACC-PAJAK'!#REF! -> #REF! | D19: ='OUT-ACC-PAJAK'!#REF! -> #REF! | E19: ='OUT-ACC-PAJAK'!#REF! -> #REF! | F19: ='OUT-ACC-PAJAK'!#REF! -> #REF! | G19: ='OUT-ACC-PAJAK'!#REF! -> #REF! | H19: ='OUT-ACC-PAJAK'!#REF! -> #REF! | I19: ='OUT-ACC-PAJAK'!#REF! -> #REF! | J19: ='OUT-ACC-PAJAK'!#REF! -> #REF! | ... AX19: ='OUT-ACC-PAJAK'!#REF! -> #REF! | AY19: =SUM(C19:AX19) -> #REF!
A20: Gaji & Benefid Karyawan | B20: CF.3 | C20: ='OUT - HR - Gaji & Benefit'!#REF! -> #REF! | D20: ='OUT - HR - Gaji & Benefit'!#REF! -> #REF! | E20: ='OUT - HR - Gaji & Benefit'!#REF! -> #REF! | F20: ='OUT - HR - Gaji & Benefit'!#REF! -> #REF! | G20: ='OUT - HR - Gaji & Benefit'!#REF! -> #REF! | H20: ='OUT - HR - Gaji & Benefit'!#REF! -> #REF! | I20: ='OUT - HR - Gaji & Benefit'!#REF! -> #REF! | J20: ='OUT - HR - Gaji & Benefit'!#REF! -> #REF! | ... AX20: ='OUT - HR - Gaji & Benefit'!#REF! -> #REF! | AY20: =SUM(C20:AX20) -> #REF!
A21: Corporate Expenses | B21: CF.6 | C21: ='OUT - CFC - Corporate Expenses'!#REF! -> #REF! | D21: ='OUT - CFC - Corporate Expenses'!#REF! -> #REF! | E21: ='OUT - CFC - Corporate Expenses'!#REF! -> #REF! | F21: ='OUT - CFC - Corporate Expenses'!#REF! -> #REF! | G21: ='OUT - CFC - Corporate Expenses'!#REF! -> #REF! | H21: ='OUT - CFC - Corporate Expenses'!#REF! -> #REF! | I21: ='OUT - CFC - Corporate Expenses'!#REF! -> #REF! | J21: ='OUT - CFC - Corporate Expenses'!#REF! -> #REF! | ... AX21: ='OUT - CFC - Corporate Expenses'!#REF! -> #REF! | AY21: =SUM(C21:AX21) -> #REF!
A22: Operational Kantor (GA) | B22: CF.7 | C22: ='OUT - ACC - Ops Kantor'!#REF! -> #REF! | D22: ='OUT - ACC - Ops Kantor'!#REF! -> #REF! | E22: ='OUT - ACC - Ops Kantor'!#REF! -> #REF! | F22: ='OUT - ACC - Ops Kantor'!#REF! -> #REF! | G22: ='OUT - ACC - Ops Kantor'!#REF! -> #REF! | H22: ='OUT - ACC - Ops Kantor'!#REF! -> #REF! | I22: ='OUT - ACC - Ops Kantor'!#REF! -> #REF! | J22: ='OUT - ACC - Ops Kantor'!#REF! -> #REF! | ... AX22: ='OUT - ACC - Ops Kantor'!#REF! -> #REF! | AY22: =SUM(C22:AX22) -> #REF!
A23: Operational All Departemen | B23: CF.12 | C23: ='OUT - CF.12 Ops All Dept'!DT80 -> 0 | D23: ='OUT - CF.12 Ops All Dept'!DU80 -> 0 | E23: ='OUT - CF.12 Ops All Dept'!DV80 -> 0 | F23: ='OUT - CF.12 Ops All Dept'!DW80 -> 0 | G23: ='OUT - CF.12 Ops All Dept'!DX80 -> 0 | H23: ='OUT - CF.12 Ops All Dept'!DY80 -> 0 | I23: ='OUT - CF.12 Ops All Dept'!DZ80 -> 0 | J23: ='OUT - CF.12 Ops All Dept'!EA80 -> 0 | ... AX23: ='OUT - CF.12 Ops All Dept'!FO80 -> 2500000 | AY23: =SUM(C23:AX23) -> 196649062
A24: Bunga & Angsuran | B24: CF.5 | C24: ='OUT - CFC - Bunga & Angsuran'!DX15 -> 0 | D24: ='OUT - CFC - Bunga & Angsuran'!DY15 -> 0 | E24: ='OUT - CFC - Bunga & Angsuran'!DZ15 -> 0 | F24: ='OUT - CFC - Bunga & Angsuran'!EA15 -> 0 | G24: ='OUT - CFC - Bunga & Angsuran'!EB15 -> 0 | H24: ='OUT - CFC - Bunga & Angsuran'!EC15 -> 0 | I24: ='OUT - CFC - Bunga & Angsuran'!ED15 -> 0 | J24: ='OUT - CFC - Bunga & Angsuran'!EE15 -> 0 | ... AX24: ='OUT - CFC - Bunga & Angsuran'!FS15 -> 0 | AY24: =SUM(C24:AX24) -> 0
A25: Cost Of Revenue | B25: CF.2 | C25: ='OUT - TEP - Cost Of Revenue'!#REF! -> #REF! | D25: ='OUT - TEP - Cost Of Revenue'!#REF! -> #REF! | E25: ='OUT - TEP - Cost Of Revenue'!#REF! -> #REF! | F25: ='OUT - TEP - Cost Of Revenue'!#REF! -> #REF! | G25: ='OUT - TEP - Cost Of Revenue'!#REF! -> #REF! | H25: ='OUT - TEP - Cost Of Revenue'!#REF! -> #REF! | I25: ='OUT - TEP - Cost Of Revenue'!#REF! -> #REF! | J25: ='OUT - TEP - Cost Of Revenue'!#REF! -> #REF! | ... AX25: ='OUT - TEP - Cost Of Revenue'!#REF! -> #REF! | AY25: =SUM(C25:AX25) -> #REF!
A26: Hutang Usaha | B26: CF.4 | C26: ='OUT - CFC - Hutang Usaha'!#REF! -> #REF! | D26: ='OUT - CFC - Hutang Usaha'!#REF! -> #REF! | E26: ='OUT - CFC - Hutang Usaha'!DX102 -> 0 | F26: ='OUT - CFC - Hutang Usaha'!DY102 -> 0 | G26: ='OUT - CFC - Hutang Usaha'!DZ102 -> 0 | H26: ='OUT - CFC - Hutang Usaha'!EA102 -> 0 | I26: ='OUT - CFC - Hutang Usaha'!EB102 -> 0 | J26: ='OUT - CFC - Hutang Usaha'!EC102 -> 0 | K26: ='OUT - CFC - Hutang Usaha'!ED102 -> 0 | L26: ='OUT - CFC - Hutang Usaha'!EE102 -> 0 | ... AX26: ='OUT - CFC - Hutang Usaha'!FQ102 -> 0 | AY26: =SUM(C26:AX26) -> #REF!
A27: Pemberian Pinjaman | B27: CF.8 | AY27: =SUM(C27:AX27) -> 0
A28: Sales Call | B28: CF.9 | AY28: =SUM(C28:AX28) -> 0
A29: Pengembalian Suntikan Modal dari Owner | B29: CF.11 | AY29: =SUM(C29:AX29) -> 0
AY30: =SUM(C30:AX30) -> 0
AY31: =SUM(C31:AX31) -> 0
A32: SUBTOTAL CASH PAID OUT | D32: =SUM(D19:D31) -> #REF! | E32: =SUM(E19:E31) -> #REF! | F32: =SUM(F19:F31) -> #REF! | G32: =SUM(G19:G31) -> #REF! | H32: =SUM(H19:H31) -> #REF! | I32: =SUM(I19:I31) -> #REF! | J32: =SUM(J19:J31) -> #REF! | K32: =SUM(K19:K31) -> #REF! | ... AY32: =SUM(AY19:AY31) -> #REF!
AY33: =SUM(C33:AX33) -> 0
A34: Pengembalian Pinjaman Pokok Modal | AY34: =SUM(C34:AX34) -> 0
A35: Pembelanjaan Modal (Capital Expenditures) | AY35: =SUM(C35:AX35) -> 0
A36: Investasi Usaha Lain (Other startup costs) | AY36: =SUM(C36:AX36) -> 0
A37: Pemberian Pinjaman (Capital Loan) | AY37: =SUM(C37:AX37) -> 0
A38: Prive Penarikan Modal (Owners' withdrawal) | AY38: =SUM(C38:AX38) -> 0
A39: Pembayaran Hutang Usaha (EVENT & TOUR) | AY39: =SUM(C39:AX39) -> 0
A40: Pengembalian Suntikan Modal dari Owner | AY40: =SUM(C40:AX40) -> 0
A41: TOTAL CASH PAID OUT | AY41: =SUM(B41:B41:AY41) -> 0
A43: OTHER OPERATING DATA | AY43: =SUM(B43:B43:AY43) -> 0
A44: Sales Revenue | AY44: =SUM(C44:AX44) -> 0
A45: Accounts receivable balance | AY45: =SUM(C45:AX45) -> 0
A46: Bad debt balance | AY46: =SUM(C46:AX46) -> 0
A47: Inventory on hand | AY47: =SUM(C47:AX47) -> 0
A48: Accounts payable balance | AY48: =SUM(C48:AX48) -> 0
A49: Depreciation | AY49: =SUM(C49:AX49) -> 0
AY50: =SUM(C50:AX50) -> 0
A51: BALANCE | AY51: =SUM(B51:B51:AY51) -> 0
A52: Saldo Mutasi Bank di LKBH | AY52: =SUM(C52:AX52) -> 0
A53: Selisih | AY53: =SUM(C53:AX53) -> 0
A57: BALANCE

Sheet CF Realisasi new
A1: Cash Flow Realization
A2: PT. Werkudara Nirwana Sakti
A6: Period | B6: 45931
A7: Cash balance alert minimum | B7: 200000000
A8: Updated on | B8: 45947 | C8: JUMAT | D8: SABTU | E8: MINGGU | F8: SENIN | G8: SELASA | H8: RABU | I8: KAMIS | J8: JUMAT | K8: SABTU | L8: MINGGU | M8: SENIN | N8: SELASA | O8: RABU | P8: KAMIS | Q8: JUMAT | R8: SABTU
B9: Beginning | C9: 45947 | D9: 45948 | E9: 45949 | F9: 45950 | G9: 45951 | H9: 45952 | I9: 45953 | J9: 45954 | K9: 45955 | L9: 45956 | M9: 45957 | N9: 45958 | O9: 45959 | P9: 45960 | Q9: 45961 | R9: 45962 | S9: TOTAL
A10: Cash on hand (beginning of month) CF.9 | B10: 750000000 | C10: =B10+C16-C42 -> -1.4106224e+08 | D10: =C10+D16-D42 -> -1.4106224e+08 | E10: =D10+E16-E42 -> -1.4106224e+08 | F10: =E10+F16-F42 -> 6.7873954e+08 | G10: =F10+G16-G42 -> -6.2786446e+08 | H10: =G10+H16-H42 -> -4.1149744e+08 | I10: =H10+I16-I42 -> -1.111319e+09 | J10: =I10+J16-J42 -> -2.2747996e+08 | ... R10: =Q10+R16-R42 -> 3.5587354e+09
A12: TOTAL PENERIMAAN KAS | S12: =SUM(B12:B12:S12) -> 0
A13: Piutang & Revenue | B13: ACC | C13: ='IN-ACC-Piutang & Revenue'!E51 -> 0 | D13: ='IN-ACC-Piutang & Revenue'!F51 -> 0 | E13: ='IN-ACC-Piutang & Revenue'!G51 -> 0 | F13: ='IN-ACC-Piutang & Revenue'!H51 -> 838451777 | G13: ='IN-ACC-Piutang & Revenue'!I51 -> 120390000 | H13: ='IN-ACC-Piutang & Revenue'!J51 -> 291003015 | I13: ='IN-ACC-Piutang & Revenue'!K51 -> 5134305 | J13: ='IN-ACC-Piutang & Revenue'!L51 -> 885839057 | ... R13: ='IN-ACC-Piutang & Revenue'!T51 -> 3787621882 | S13: =SUM(C13:R13) -> 7133738712
A14: Penerimaan Pengembalian Pinjaman | B14: CFC | C14: ='IN-CFC-Penerimaan PengemPinj'!D19 -> 0 | D14: ='IN-CFC-Penerimaan PengemPinj'!E19 -> 0 | E14: ='IN-CFC-Penerimaan PengemPinj'!F19 -> 0 | F14: ='IN-CFC-Penerimaan PengemPinj'!G19 -> 0 | G14: ='IN-CFC-Penerimaan PengemPinj'!H19 -> 0 | H14: ='IN-CFC-Penerimaan PengemPinj'!I19 -> 0 | I14: ='IN-CFC-Penerimaan PengemPinj'!J19 -> 0 | J14: ='IN-CFC-Penerimaan PengemPinj'!K19 -> 0 | ... R14: ='IN-CFC-Penerimaan PengemPinj'!S19 -> 0 | S14: =SUM(C14:R14) -> 0
A15: Suntikan Modal | C15: ='IN-CFC-Suntikan Modal'!D12 -> 0 | D15: ='IN-CFC-Suntikan Modal'!E12 -> 0 | E15: ='IN-CFC-Suntikan Modal'!F12 -> 0 | F15: ='IN-CFC-Suntikan Modal'!G12 -> 0 | G15: ='IN-CFC-Suntikan Modal'!H12 -> 0 | H15: ='IN-CFC-Suntikan Modal'!I12 -> 0 | I15: ='IN-CFC-Suntikan Modal'!J12 -> 0 | J15: ='IN-CFC-Suntikan Modal'!K12 -> 0 | ... R15: ='IN-CFC-Suntikan Modal'!S12 -> 0 | S15: =SUM(C15:R15) -> 0
A16: TOTAL PENERIMAAN KAS | C16: =SUM(C13:C15) -> 0 | D16: =SUM(D13:D15) -> 0 | E16: =SUM(E13:E15) -> 0 | F16: =SUM(F13:F15) -> 838451777 | G16: =SUM(G13:G15) -> 120390000 | H16: =SUM(H13:H15) -> 291003015 | I16: =SUM(I13:I15) -> 5134305 | J16: =SUM(J13:J15) -> 885839057 | ... S16: =SUM(S13:S15) -> 7133738712
A18: PENGELUARAN | S18: =SUM(B18:B18:S18) -> 0
A19: Pajak | B19: ACC | C19: ='OUT-ACC-PAJAK'!D35 -> 0 | D19: ='OUT-ACC-PAJAK'!E35 -> 0 | E19: ='OUT-ACC-PAJAK'!F35 -> 0 | F19: ='OUT-ACC-PAJAK'!G35 -> 0 | G19: ='OUT-ACC-PAJAK'!H35 -> 46190827 | H19: ='OUT-ACC-PAJAK'!I35 -> 0 | I19: ='OUT-ACC-PAJAK'!J35 -> 104638748 | J19: ='OUT-ACC-PAJAK'!K35 -> 0 | ... R19: ='OUT-ACC-PAJAK'!S35 -> 0 | S19: =SUM(C19:R19) -> 3.8858056e+08
A20: Gaji & Benefit Karyawan | B20: HR | C20: ='OUT - HR - Gaji & Benefit'!D18 -> 0 | D20: ='OUT - HR - Gaji & Benefit'!E18 -> 0 | E20: ='OUT - HR - Gaji & Benefit'!F18 -> 0 | F20: ='OUT - HR - Gaji & Benefit'!G18 -> 0 | G20: ='OUT - HR - Gaji & Benefit'!H18 -> 0 | H20: ='OUT - HR - Gaji & Benefit'!I18 -> 0 | I20: ='OUT - HR - Gaji & Benefit'!J18 -> 0 | J20: ='OUT - HR - Gaji & Benefit'!K18 -> 0 | ... R20: ='OUT - HR - Gaji & Benefit'!S18 -> 250000000 | S20: =SUM(C20:R20) -> 250000000
A21: Corporate Expenses | B21: CFC | C21: ='OUT - CFC - Corporate Expenses'!H33 -> 0 | D21: ='OUT - CFC - Corporate Expenses'!I33 -> 0 | E21: ='OUT - CFC - Corporate Expenses'!J33 -> 0 | F21: ='OUT - CFC - Corporate Expenses'!K33 -> 0 | G21: ='OUT - CFC - Corporate Expenses'!L33 -> 81607500 | H21: ='OUT - CFC - Corporate Expenses'!M33 -> 74636000 | I21: ='OUT - CFC - Corporate Expenses'!N33 -> 101691071 | J21: ='OUT - CFC - Corporate Expenses'!O33 -> 0 | ... R21: ='OUT - CFC - Corporate Expenses'!W33 -> 35000000 | S21: =SUM(C21:R21) -> 300375769
A22: Operational Kantor (ACC) | B22: ACC | C22: ='OUT - ACC - Ops Kantor'!D21 -> 0 | D22: ='OUT - ACC - Ops Kantor'!E21 -> 0 | E22: ='OUT - ACC - Ops Kantor'!F21 -> 0 | F22: ='OUT - ACC - Ops Kantor'!G21 -> 0 | G22: ='OUT - ACC - Ops Kantor'!H21 -> 0 | H22: ='OUT - ACC - Ops Kantor'!I21 -> 0 | I22: ='OUT - ACC - Ops Kantor'!J21 -> 0 | J22: ='OUT - ACC - Ops Kantor'!K21 -> 0 | ... R22: ='OUT - ACC - Ops Kantor'!S21 -> 0 | S22: =SUM(C22:R22) -> 0
A23: Operational Kantor (ACS) | B23: ACS | C23: ='OUT-ACS-OPS'!D18 -> 0 | D23: ='OUT-ACS-OPS'!E18 -> 0 | E23: ='OUT-ACS-OPS'!F18 -> 0 | F23: ='OUT-ACS-OPS'!G18 -> 0 | G23: ='OUT-ACS-OPS'!H18 -> 0 | H23: ='OUT-ACS-OPS'!I18 -> 0 | I23: ='OUT-ACS-OPS'!J18 -> 0 | J23: ='OUT-ACS-OPS'!K18 -> 0 | ... R23: ='OUT-ACS-OPS'!S18 -> 0 | S23: =SUM(C23:R23) -> 0
A24: Operational Kantor (BAS) | B24: BAS | C24: ='OUT-BAS-OPS'!D18 -> 0 | D24: ='OUT-BAS-OPS'!E18 -> 0 | E24: ='OUT-BAS-OPS'!F18 -> 0 | F24: ='OUT-BAS-OPS'!G18 -> 0 | G24: ='OUT-BAS-OPS'!H18 -> 0 | H24: ='OUT-BAS-OPS'!I18 -> 0 | I24: ='OUT-BAS-OPS'!J18 -> 0 | J24: ='OUT-BAS-OPS'!K18 -> 0 | ... R24: ='OUT-BAS-OPS'!S18 -> 0 | S24: =SUM(C24:R24) -> 0
A25: Operational Kantor (BID) | B25: BID | C25: ='OUT-BID-OPS'!D12 -> 0 | D25: ='OUT-BID-OPS'!E12 -> 0 | E25: ='OUT-BID-OPS'!F12 -> 0 | F25: ='OUT-BID-OPS'!G12 -> 0 | G25: ='OUT-BID-OPS'!H12 -> 0 | H25: ='OUT-BID-OPS'!I12 -> 0 | I25: ='OUT-BID-OPS'!J12 -> 0 | J25: ='OUT-BID-OPS'!K12 -> 0 | ... R25: ='OUT-BID-OPS'!S12 -> 0 | S25: =SUM(C25:R25) -> 0
A26: Operational Kantor (CFC) | B26: CFC | C26: ='OUT-CFC-OPS'!D12 -> 0 | D26: ='OUT-CFC-OPS'!E12 -> 0 | E26: ='OUT-CFC-OPS'!F12 -> 0 | F26: ='OUT-CFC-OPS'!G12 -> 0 | G26: ='OUT-CFC-OPS'!H12 -> 0 | H26: ='OUT-CFC-OPS'!I12 -> 0 | I26: ='OUT-CFC-OPS'!J12 -> 0 | J26: ='OUT-CFC-OPS'!K12 -> 0 | ... R26: ='OUT-CFC-OPS'!S12 -> 0 | S26: =SUM(C26:R26) -> 0
A27: Operational Kantor (GA) | B27: GA | C27: ='OUT-GA-OPS'!D26 -> 0 | D27: ='OUT-GA-OPS'!E26 -> 0 | E27: ='OUT-GA-OPS'!F26 -> 0 | F27: ='OUT-GA-OPS'!G26 -> 0 | G27: ='OUT-GA-OPS'!H26 -> 7900000 | H27: ='OUT-GA-OPS'!I26 -> 0 | I27: ='OUT-GA-OPS'!J26 -> 300000 | J27: ='OUT-GA-OPS'!K26 -> 0 | ... R27: ='OUT-GA-OPS'!S26 -> 0 | S27: =SUM(C27:R27) -> 26540000
A28: Operational Kantor (HR) | B28: HR | C28: ='OUT-HR-OPS'!D15 -> 0 | D28: ='OUT-HR-OPS'!E15 -> 0 | E28: ='OUT-HR-OPS'!F15 -> 0 | F28: ='OUT-HR-OPS'!G15 -> 0 | G28: ='OUT-HR-OPS'!H15 -> 0 | H28: ='OUT-HR-OPS'!I15 -> 0 | I28: ='OUT-HR-OPS'!J15 -> 2000000 | J28: ='OUT-HR-OPS'!K15 -> 2000000 | ... R28: ='OUT-HR-OPS'!S15 -> 0 | S28: =SUM(C28:R28) -> 16500000
A29: Operational Kantor (PD) | B29: PD | C29: ='OUT-PD-OPS'!D12 -> 0 | D29: ='OUT-PD-OPS'!E12 -> 0 | E29: ='OUT-PD-OPS'!F12 -> 0 | F29: ='OUT-PD-OPS'!G12 -> 0 | G29: ='OUT-PD-OPS'!H12 -> 0 | H29: ='OUT-PD-OPS'!I12 -> 0 | I29: ='OUT-PD-OPS'!J12 -> 0 | J29: ='OUT-PD-OPS'!K12 -> 0 | ... R29: ='OUT-PD-OPS'!S12 -> 0 | S29: =SUM(C29:R29) -> 0
A30: Operational Kantor (SS) | B30: SS | C30: ='OUT-SS-OPS'!D12 -> 0 | D30: ='OUT-SS-OPS'!E12 -> 0 | E30: ='OUT-SS-OPS'!F12 -> 0 | F30: ='OUT-SS-OPS'!G12 -> 0 | G30: ='OUT-SS-OPS'!H12 -> 0 | H30: ='OUT-SS-OPS'!I12 -> 0 | I30: ='OUT-SS-OPS'!J12 -> 0 | J30: ='OUT-SS-OPS'!K12 -> 0 | ... R30: ='OUT-SS-OPS'!S12 -> 0 | S30: =SUM(C30:R30) -> 0
A31: Operational Kantor (SO) | B31: SO | C31: ='OUT-SO-OPS'!D12 -> 0 | D31: ='OUT-SO-OPS'!E12 -> 0 | E31: ='OUT-SO-OPS'!F12 -> 0 | F31: ='OUT-SO-OPS'!G12 -> 0 | G31: ='OUT-SO-OPS'!H12 -> 0 | H31: ='OUT-SO-OPS'!I12 -> 0 | I31: ='OUT-SO-OPS'!J12 -> 0 | J31: ='OUT-SO-OPS'!K12 -> 0 | ... R31: ='OUT-SO-OPS'!S12 -> 0 | S31: =SUM(C31:R31) -> 0
A32: Operational Kantor (TEP) | B32: TEP | C32: ='OUT-TEP-OPS'!D12 -> 0 | D32: ='OUT-TEP-OPS'!E12 -> 0 | E32: ='OUT-TEP-OPS'!F12 -> 0 | F32: ='OUT-TEP-OPS'!G12 -> 0 | G32: ='OUT-TEP-OPS'!H12 -> 0 | H32: ='OUT-TEP-OPS'!I12 -> 0 | I32: ='OUT-TEP-OPS'!J12 -> 0 | J32: ='OUT-TEP-OPS'!K12 -> 0 | ... R32: ='OUT-TEP-OPS'!S12 -> 0 | S32: =SUM(C32:R32) -> 0
A33: Operational Kantor (RESERVASI) | B33: RESERVASI | C33: ='OUT-RESERVASI-OPS'!D12 -> 0 | D33: ='OUT-RESERVASI-OPS'!E12 -> 0 | E33: ='OUT-RESERVASI-OPS'!F12 -> 0 | F33: ='OUT-RESERVASI-OPS'!G12 -> 0 | G33: ='OUT-RESERVASI-OPS'!H12 -> 0 | H33: ='OUT-RESERVASI-OPS'!I12 -> 0 | I33: ='OUT-RESERVASI-OPS'!J12 -> 0 | J33: ='OUT-RESERVASI-OPS'!K12 -> 0 | ... R33: ='OUT-RESERVASI-OPS'!S12 -> 0 | S33: =SUM(C33:R33) -> 0
A34: Operational Kantor (TAKSHAKA) | B34: TAKSHAKA | C34: ='OUT-TAKSHAKA-OPS'!D12 -> 0 | D34: ='OUT-TAKSHAKA-OPS'!E12 -> 0 | E34: ='OUT-TAKSHAKA-OPS'!F12 -> 0 | F34: ='OUT-TAKSHAKA-OPS'!G12 -> 0 | G34: ='OUT-TAKSHAKA-OPS'!H12 -> 0 | H34: ='OUT-TAKSHAKA-OPS'!I12 -> 0 | I34: ='OUT-TAKSHAKA-OPS'!J12 -> 0 | J34: ='OUT-TAKSHAKA-OPS'!K12 -> 0 | ... R34: ='OUT-TAKSHAKA-OPS'!S12 -> 0 | S34: =SUM(C34:R34) -> 0
A35: Bunga & Angsuran | B35: CFC | C35: ='OUT - CFC - Bunga & Angsuran'!I15 -> 0 | D35: ='OUT - CFC - Bunga & Angsuran'!J15 -> 0 | E35: ='OUT - CFC - Bunga & Angsuran'!K15 -> 0 | F35: ='OUT - CFC - Bunga & Angsuran'!L15 -> 0 | G35: ='OUT - CFC - Bunga & Angsuran'!M15 -> 0 | H35: ='OUT - CFC - Bunga & Angsuran'!N15 -> 0 | I35: ='OUT - CFC - Bunga & Angsuran'!O15 -> 0 | J35: ='OUT - CFC - Bunga & Angsuran'!P15 -> 0 | ... R35: ='OUT - CFC - Bunga & Angsuran'!X15 -> 0 | S35: =SUM(C35:R35) -> 0
A36: Cost Of Revenue | B36: TEP | C36: ='OUT - TEP - Cost Of Revenue'!H27 -> 8.9106224e+08 | D36: ='OUT - TEP - Cost Of Revenue'!I27 -> 0 | E36: ='OUT - TEP - Cost Of Revenue'!J27 -> 0 | F36: ='OUT - TEP - Cost Of Revenue'!K27 -> 0 | G36: ='OUT - TEP - Cost Of Revenue'!L27 -> 276735094 | H36: ='OUT - TEP - Cost Of Revenue'!M27 -> 0 | I36: ='OUT - TEP - Cost Of Revenue'!N27 -> 2.9284306e+08 | J36: ='OUT - TEP - Cost Of Revenue'!O27 -> 0 | ... R36: ='OUT - TEP - Cost Of Revenue'!W27 -> 0 | S36: =SUM(C36:R36) -> 1.5792729e+09
A37: Hutang Usaha | B37: CFC | C37: ='OUT - CFC - Hutang Usaha'!H103 -> 0 | D37: ='OUT - CFC - Hutang Usaha'!I103 -> 0 | E37: ='OUT - CFC - Hutang Usaha'!J103 -> 0 | F37: ='OUT - CFC - Hutang Usaha'!K103 -> 18650000 | G37: ='OUT - CFC - Hutang Usaha'!L103 -> 1014560576 | H37: ='OUT - CFC - Hutang Usaha'!M103 -> 0 | I37: ='OUT - CFC - Hutang Usaha'!N103 -> 203483000 | J37: ='OUT - CFC - Hutang Usaha'!O103 -> 0 | ... R37: ='OUT - CFC - Hutang Usaha'!W103 -> 0 | S37: =SUM(C37:R37) -> 1763734063
A38: Pemberian Pinjaman | B38: HR | C38: ='OUT - HR - Pemberian Pinjaman'!D12 -> 0 | D38: ='OUT - HR - Pemberian Pinjaman'!E12 -> 0 | E38: ='OUT - HR - Pemberian Pinjaman'!F12 -> 0 | F38: ='OUT - HR - Pemberian Pinjaman'!G12 -> 0 | G38: ='OUT - HR - Pemberian Pinjaman'!H12 -> 0 | H38: ='OUT - HR - Pemberian Pinjaman'!I12 -> 0 | I38: ='OUT - HR - Pemberian Pinjaman'!J12 -> 0 | J38: ='OUT - HR - Pemberian Pinjaman'!K12 -> 0 | ... R38: ='OUT - HR - Pemberian Pinjaman'!S12 -> 0 | S38: =SUM(C38:R38) -> 0
A39: Sales Call | B39: TEP | C39: ='OUT - TEP - Sales Call'!D12 -> 0 | D39: ='OUT - TEP - Sales Call'!E12 -> 0 | E39: ='OUT - TEP - Sales Call'!F12 -> 0 | F39: ='OUT - TEP - Sales Call'!G12 -> 0 | G39: ='OUT - TEP - Sales Call'!H12 -> 0 | H39: ='OUT - TEP - Sales Call'!I12 -> 0 | I39: ='OUT - TEP - Sales Call'!J12 -> 0 | J39: ='OUT - TEP - Sales Call'!K12 -> 0 | ... R39: ='OUT - TEP - Sales Call'!S12 -> 0 | S39: =SUM(C39:R39) -> 0
A40: Pengembalian Suntikan Modal dari Owner | B40: CFC | C40: ='OUT-CFC -Pengem Sunti Modal Own'!D12 -> 0 | D40: ='OUT-CFC -Pengem Sunti Modal Own'!E12 -> 0 | E40: ='OUT-CFC -Pengem Sunti Modal Own'!F12 -> 0 | F40: ='OUT-CFC -Pengem Sunti Modal Own'!G12 -> 0 | G40: ='OUT-CFC -Pengem Sunti Modal Own'!H12 -> 0 | H40: ='OUT-CFC -Pengem Sunti Modal Own'!I12 -> 0 | I40: ='OUT-CFC -Pengem Sunti Modal Own'!J12 -> 0 | J40: ='OUT-CFC -Pengem Sunti Modal Own'!K12 -> 0 | ... R40: ='OUT-CFC -Pengem Sunti Modal Own'!S12 -> 0 | S40: =SUM(C40:R40) -> 0
S41: =SUM(C41:R41) -> 0
A42: TOTAL PENGELUARAN KAS | C42: =SUM(C19:C40) -> 8.9106224e+08 | D42: =SUM(D19:D40) -> 0 | E42: =SUM(E19:E40) -> 0 | F42: =SUM(F19:F40) -> 18650000 | G42: =SUM(G19:G40) -> 1.426994e+09 | H42: =SUM(H19:H40) -> 74636000 | I42: =SUM(I19:I40) -> 7.0495588e+08 | J42: =SUM(J19:J40) -> 2000000 | ... R42: =SUM(R19:R40) -> 285000000 | S42: =SUM(S19:S41) -> 4.3250033e+09
S43: =SUM(C43:R43) -> 0
A44: Pengembalian Pinjaman Pokok Modal | S44: =SUM(C44:R44) -> 0
A45: Pembelanjaan Modal (Capital Expenditures) | S45: =SUM(C45:R45) -> 0
A46: Investasi Usaha Lain (Other startup costs) | S46: =SUM(C46:R46) -> 0
A47: Pemberian Pinjaman (Capital Loan) | S47: =SUM(C47:R47) -> 0
A48: Prive Penarikan Modal (Owners' withdrawal) | S48: =SUM(C48:R48) -> 0
A49: Pembayaran Hutang Usaha (EVENT & TOUR) | S49: =SUM(C49:R49) -> 0
A50: Pengembalian Suntikan Modal dari Owner | S50: =SUM(C50:R50) -> 0
A51: TOTAL CASH PAID OUT | S51: =SUM(S43:S50) -> 0
A53: OTHER OPERATING DATA | S53: =SUM(B53:B53:S53) -> 0
A54: Sales Revenue | S54: =SUM(C54:R54) -> 0
A55: Accounts receivable balance | S55: =SUM(C55:R55) -> 0
A56: Bad debt balance | S56: =SUM(C56:R56) -> 0
A57: Inventory on hand | S57: =SUM(C57:R57) -> 0
A58: Accounts payable balance | S58: =SUM(C58:R58) -> 0
A59: Depreciation | S59: =SUM(C59:R59) -> 0
S60: =SUM(C60:R60) -> 0
A61: BALANCE | S61: =SUM(B61:B61:S61) -> 0
A62: Saldo Mutasi Bank di LKBH | S62: =SUM(C62:R62) -> 0
A63: Selisih | S63: =SUM(C63:R63) -> 0
A67: BALANCE

Sheet IN-ACC-Piutang & Revenue
F1: Hari Kerja
F2: Jadwal Pembayaran (Selasa/ Jumat)
F3: Hari Libur
E4: Pengeluaran Biaya Operating Sales & Marketing | F4: 22 Okt 2021
E5: JUMAT | F5: SABTU | G5: MINGGU | H5: SENIN | I5: SELASA | J5: RABU | K5: KAMIS | L5: JUMAT | M5: SABTU | N5: MINGGU | O5: SENIN | P5: SELASA | Q5: RABU | R5: KAMIS | S5: JUMAT | T5: SABTU
B6: DESKRIPSI | C6: NOMINAL | D6: TANGGAL | E6: 45947 | F6: 45948 | G6: 45949 | H6: 45950 | I6: 45951 | J6: 45952 | K6: 45953 | L6: 45954 | M6: 45955 | N6: 45956 | O6: 45957 | P6: 45958 | Q6: 45959 | R6: 45960 | S6: 45961 | T6: 45962 | U6: TOTAL
B7: World Bank VP DFI Site Visitation tgl 22-23 Aug 2025 | C7: 115426850 | S7: 115426850 | U7: =SUM(E7:T7) -> 115426850
B8: WNS BALI - Forest Therapy Kemenpar Soulful Escape: Recharge & Rediscover 8D7N Bali Yogyakarta Famtrip New Zealand tgl 25 Aug 2025 | C8: 20000000 | H8: 20000000 | U8: =SUM(E8:T8) -> 20000000
B9: UOB INDONESIA - UOB Brand Internal Campaign Service May - September 2025 | C9: 144437585 | J9: 50000000 | T9: 144437585 | U9: =SUM(E9:T9) -> 194437585
B10: UOB INDONESIA - Transport Arrangement Mr. Hendra UOB Indonesia tgl 22-23 Aug 2025 | C10: 8325000 | T10: 8325000 | U10: =SUM(E10:T10) -> 8325000
B11: PROTELINDO GROUP - Corporate Travel Protelindo Group tgl 1-30 August 2025 | C11: 45500363 | S11: 45500363 | U11: =SUM(E11:T11) -> 45500363
B12: UOB INDONESIA - UOB BOD Board Retreat tgl 2-6 September 2025 | C12: 850267131 | T12: 850267131 | U12: =SUM(E12:T12) -> 850267131
B13: PT ROCHE INDONESIA - Booth Roche at Pertemuan Ilmiah Tahunan Perhimpunan Dokter Spesial Patologi Anatomik in Yogyakarta on September 5-7, 2025 | C13: 87198216 | L13: 87198216 | U13: =SUM(E13:T13) -> 87198216
B14: UN WOMEN INDONESIA - 25th Anniversary of UNSCR 1325 Celebration : Exhibition, Workshop, and Launch of the Indonesian CSO Network for 17-19 September 2025 | C14: 574887500 | S14: 574887500 | U14: =SUM(E14:T14) -> 574887500
B15: WORLD BANK - World Bank VP for East Asia and Pacific Region Visit to Jakarta Tour tgl 20 Sep 2025 | C15: 95825400 | S15: 95825400 | U15: =SUM(E15:T15) -> 95825400
B16: PT FINACCEL TEKNOLOGI INDONESIA - Tour Company Outing Team 2025 in Bogor on September 26-27, 2025 (Term 2) | C16: 77025563 | O16: 77025563 | U16: =SUM(E16:T16) -> 77025563
B17: RS SILOAM MRCC SEMANGGI - Backdrop Arrangement - Hardoknas tgl 1-31 Oktober 2025 (Term 1) | C17: 5134305 | K17: 5134305 | U17: =SUM(E17:T17) -> 5134305
B18: RS SILOAM MRCC SEMANGGI - Backdrop Arrangement - Hardoknas tgl 1-31 Oktober 2025 (Term 2) | C18: 5134305 | T18: 5134305 | U18: =SUM(E18:T18) -> 5134305
B19: PT DONALDSON FILTRATION INDONESIA - Halfday Tour Sightseeing in Bandung on November 11, 2025 | C19: 138845685 | T19: 138845685 | U19: =SUM(E19:T19) -> 138845685
B20: PT DONALDSON FILTRATION INDONESIA - Halfday Tour Sightseeing in Bandung on November 11, 2025 (Additional Term 1) | C20: 36324750 | T20: 36324750 | U20: =SUM(E20:T20) -> 36324750
B21: PT DONALDSON FILTRATION INDONESIA - Halfday Tour Sightseeing in Bandung on November 11, 2025 (Additional Term 2) | C21: 15567750 | T21: 15567750 | U21: =SUM(E21:T21) -> 15567750
B22: ILO INDONESIA - ILO - Official Visit of Federal Councilor of Switzerland to KPBS Pangalengan on October 2, 2025 | C22: 191003015 | J22: 191003015 | U22: =SUM(E22:T22) -> 191003015
B23: PT BADAN ESSENCE INDONESIA - IFF Festive Night 2025 (Additional) | C23: 109890000 | I23: 109890000 | U23: =SUM(E23:T23) -> 109890000
B24: TEAM INTERNATIONAL TEXTILE MANUFACTURER FEDERATION - ITMF Annual Conference & IAF World Fashion Convention in Yogyakarta on October 24-26, 2025 (Term 3) | C24: 155058600 | T24: 155058600 | U24: =SUM(E24:T24) -> 155058600
B25: ASOSIASI PERTEKSTILAN INDONESIA (API) - Booth Diamond APR - ITMF Annual Conference & IAF World Fashion Convention in Yogyakarta on October 24, 2025 | C25: 54945000 | T25: 54945000 | U25: =SUM(E25:T25) -> 54945000
B26: APDMET - Sosialisasi Hasil Munas V dan Rapat Kerja ADPMET 2025 in Cepu on October 15, 2025 (Term 2) | C26: 19658000 | P26: 19658000 | U26: =SUM(E26:T26) -> 19658000
B27: JOE - Sosialisasi Hasil Munas V dan Rapat Kerja ADPMET 2025 in Cepu on October 15, 2025 (Term 3 / Dana Sponsorship) | C27: 50000000 | J27: 50000000 | U27: =SUM(E27:T27) -> 50000000
B28: PT KROM BANK INDONESIA TBK - Tour Annual Gathering tgl 24-25 Oktober 2025 (Term 1) | C28: 411443637 | H28: 411443637 | U28: =SUM(E28:T28) -> 411443637
B29: PT KROM BANK INDONESIA TBK - Tour Annual Gathering tgl 24-25 Oktober 2025 (Term 2) | C29: 617165456 | U29: =SUM(E29:T29) -> 0
B30: RANTAI TEKSTIL LESTARI - Meeting RTL tgl 23 October 2025 (Term 2) | C30: =189560250-151648200 -> 37912050 | U30: =SUM(E30:T30) -> 0
B31: PT WNS - BI KPW Sulawesi Utara Mastering Smart Correspondence with AI | C31: 7000000 | T31: 7000000 | U31: =SUM(E31:T31) -> 7000000
B32: KEMENPAR - Workshop Kejutan tgl 1-2 Oktober 2025 (WNS) | C32: 199050000 | L32: 199050000 | U32: =SUM(E32:T32) -> 199050000
B33: KEMENPAR - Workshop Kejutan tgl 1-2 Oktober 2025 (YPN) | C33: 49950000 | L33: 49950000 | U33: =SUM(E33:T33) -> 49950000
B34: KEMENPAR - Workshop Kejutan tgl 1-2 Oktober 2025 (Kwitansi WNS) | C34: 990000 | L34: 990000 | U34: =SUM(E34:T34) -> 990000
B35: PT RINTIS SEJAHTERA - PRIMA Executive Gathering 2025 | C35: 442500000 | T35: 442500000 | U35: =SUM(E35:T35) -> 442500000
B36: PT DATA SINERGITAMA JAYA TBK - Elitery Company Gathering Team Building & Gala Dinner (Term 1) | C36: 407008140 | H36: 407008140 | U36: =SUM(E36:T36) -> 407008140
B37: PT DATA SINERGITAMA JAYA TBK - Elitery Company Gathering Team Building & Gala Dinner (Term 2) | C37: 174432060 | T37: 174432060 | U37: =SUM(E37:T37) -> 174432060
B38: GIZ INDONESIA - Green Infrastructur Initiative World Clean Up Day Event in Batu Lumbang Mangrove Bali on October 13, 2025 | C38: 276975000 | S38: 276975000 | U38: =SUM(E38:T38) -> 276975000
B39: BI KPW SULUT - Transportation Arrival (MRP) | C39: 133235178 | L39: 133235178 | U39: =SUM(E39:T39) -> 133235178
B40: BI KPW SULUT - Transportation Departure (MRP) | C40: 110562488 | L40: 110562488 | U40: =SUM(E40:T40) -> 110562488
B41: BI KPW SULUT - Event Arrangement Festival Jurnalistik Rekanan Media Sulut tgl 1-4 Oct 2025 | C41: 184859400 | L41: 184859400 | U41: =SUM(E41:T41) -> 184859400
B42: BI KPW SULUT - Accomodation (YPN) | C42: 119993775 | L42: 119993775 | U42: =SUM(E42:T42) -> 119993775
B43: PT ASIA PACIFIC RAYON - Gala Dinner ITMF Annual Conference & IAF World Fashion Convention October 24, 2025 | C43: 1216214291 | T43: 1216214291 | U43: =SUM(E43:T43) -> 1216214291
A44: Agt | B44: UOB INDONESIA - Brand Internal Campaign | C44: 110836275 | T44: 110836275 | U44: =SUM(E44:T44) -> 110836275
B45: UNDP SLPI - Bintang SLPI Live at International Indonesia Sustainability Forukm tgl 10 October 2025 | C45: 126861900 | T45: 126861900 | U45: =SUM(E45:T45) -> 126861900
B46: GIZ INDONESIA - IKI Interface Workshop tgl 21 Oct 2025 | C46: 294821550 | T46: 294821550 | U46: =SUM(E46:T46) -> 294821550
B47: BU EVI INDIVIDUAL GUEST - 3D2N Yogyakarta Tour Experience tgl 21-23 November 2025 | C47: 6050000 | T47: 6050000 | U47: =SUM(E47:T47) -> 6050000
B48: PT GOLDEN TEKSTIL INDONESIA - ITMF Annual Conference & IAF World Fashion Convention tgl 22 October 2025 | C48: 10500000 | I48: 10500000 | U48: =SUM(E48:T48) -> 10500000
U49: =SUM(E49:T49) -> 0
U50: =SUM(E50:T50) -> 0
B51: TOTAL | E51: =SUM(E7:E50) -> 0 | F51: =SUM(F7:F50) -> 0 | G51: =SUM(G7:G50) -> 0 | H51: =SUM(H7:H50) -> 838451777 | I51: =SUM(I7:I50) -> 120390000 | J51: =SUM(J7:J50) -> 291003015 | K51: =SUM(K7:K50) -> 5134305 | L51: =SUM(L7:L50) -> 885839057 | ... U51: =SUM(U7:U50) -> 7133738712

Sheet IN-CFC-Penerimaan PengemPinj
B1: Kategori : | C1: Cash Outflow (Penerimaan Kas) | E1: Hari Kerja
B2: Pos Akun : | C2: Pemberian Pinjaman | E2: Jadwal Pembayaran (Selasa/ Jumat)
B3: Periode : | E3: Hari Libur
B4: Updated on : | C4: ='CF Realisasi new'!B8 -> 45947 | D4: Pengeluaran Biaya Operating Sales & Marketing | E4: Pengeluaran Biaya Operating Sales & Marketing
D5: JUMAT | E5: SABTU | F5: MINGGU | G5: SENIN | H5: SELASA | I5: RABU | J5: KAMIS | K5: JUMAT | L5: SABTU | M5: MINGGU | N5: SENIN | O5: SELASA | P5: RABU | Q5: KAMIS | R5: JUMAT | S5: SABTU
A6: PENERIMAAN PINJAMAN | B6: NOMINAL | C6: TANGGAL | D6: 45947 | E6: 45948 | F6: 45949 | G6: 45950 | H6: 45951 | I6: 45952 | J6: 45953 | K6: 45954 | L6: 45955 | M6: 45956 | N6: 45957 | O6: 45958 | P6: 45959 | Q6: 45960 | R6: 45961 | S6: 45962 | T6: TOTAL
T7: =SUM(D7:S7) -> 0
T8: =SUM(D8:S8) -> 0
T9: =SUM(D9:S9) -> 0
T10: =SUM(D10:S10) -> 0
T11: =SUM(D11:S11) -> 0
T12: =SUM(D12:S12) -> 0
T13: =SUM(D13:S13) -> 0
T14: =SUM(D14:S14) -> 0
T15: =SUM(D15:S15) -> 0
T16: =SUM(D16:S16) -> 0
T17: =SUM(D17:S17) -> 0
T18: =SUM(D18:S18) -> 0
B19: TOTAL PEMBERIAN PINJAMAN | D19: =SUM(D7:D18) -> 0 | E19: =SUM(E7:E18) -> 0 | F19: =SUM(F7:F18) -> 0 | G19: =SUM(G7:G18) -> 0 | H19: =SUM(H7:H18) -> 0 | I19: =SUM(I7:I18) -> 0 | J19: =SUM(J7:J18) -> 0 | K19: =SUM(K7:K18) -> 0 | ... T19: =SUM(T7:T18) -> 0

Sheet IN-CFC-Suntikan Modal
B1: Kategori : | C1: Cash Outflow (Penerimaan Kas) | F1: Hari Kerja
B2: Pos Akun : | C2: IN-Suntikan Modal | F2: Jadwal Pembayaran (Selasa/ Jumat)
B3: Periode : | F3: Hari Libur
B4: Updated on : | C4: ='CF Realisasi new'!B8 -> 45947 | D4: Pengeluaran Biaya Operating Sales & Marketing
D5: JUMAT | E5: SABTU | F5: MINGGU | G5: SENIN | H5: SELASA | I5: RABU | J5: KAMIS | K5: JUMAT | L5: SABTU | M5: MINGGU | N5: SENIN | O5: SELASA | P5: RABU | Q5: KAMIS | R5: JUMAT | S5: SABTU
A6: DESKRIPSI | B6: NOMINAL | C6: TANGGAL | D6: 45947 | E6: 45948 | F6: 45949 | G6: 45950 | H6: 45951 | I6: 45952 | J6: 45953 | K6: 45954 | L6: 45955 | M6: 45956 | N6: 45957 | O6: 45958 | P6: 45959 | Q6: 45960 | R6: 45961 | S6: 45962 | T6: TOTAL
T7: =SUM(D7:S7) -> 0
B8: Menerima suntikan modal | T8: =SUM(D8:S8) -> 0
T9: =SUM(D9:S9) -> 0
T10: =SUM(D10:S10) -> 0
T11: =SUM(D11:S11) -> 0
B12: TOTAL PENERIMAAN SUNTIKAN MODAL DARI OWNER | D12: =SUM(D7:D11) -> 0 | E12: =SUM(E7:E11) -> 0 | F12: =SUM(F7:F11) -> 0 | G12: =SUM(G7:G11) -> 0 | H12: =SUM(H7:H11) -> 0 | I12: =SUM(I7:I11) -> 0 | J12: =SUM(J7:J11) -> 0 | K12: =SUM(K7:K11) -> 0 | ... T12: =SUM(T7:T11) -> 0

Sheet OUT-ACC-PAJAK
B1: Kategori : | C1: Cash Outflow (Pengeluaran Kas)
B2: Pos Akun : | C2: OUT-ACC-Pajak
B3: Periode :
B4: Updated on : | C4: ='CF Realisasi new'!B8 -> 45947 | D4: Pengeluaran Biaya Operating Sales & Marketing
D5: JUMAT | E5: SABTU | F5: MINGGU | G5: SENIN | H5: SELASA | I5: RABU | J5: KAMIS | K5: JUMAT | L5: SABTU | M5: MINGGU | N5: SENIN | O5: SELASA | P5: RABU | Q5: KAMIS | R5: JUMAT | S5: SABTU
A6: DESKRIPSI | B6: NOMINAL | C6: TANGGAL | D6: 45947 | E6: 45948 | F6: 45949 | G6: 45950 | H6: 45951 | I6: 45952 | J6: 45953 | K6: 45954 | L6: 45955 | M6: 45956 | N6: 45957 | O6: 45958 | P6: 45959 | Q6: 45960 | R6: 45961 | S6: 45962 | T6: TOTAL
A7: PPN MEI 2025 | B7: 104638748 | J7: 104638748 | T7: =SUM(D7:S7) -> 104638748
A8: PPH 23, 26, 4(2) JUNI | B8: 12025717 | O8: 12025717 | T8: =SUM(D8:S8) -> 12025717
A9: PPN IMPOR JUNI | B9: 109222 | H9: 109222 | T9: =SUM(D9:S9) -> 109222
A10: PPN JUNI 2025 | B10: 216881482 | Q10: 216881482 | T10: =SUM(D10:S10) -> 216881482
A11: PPH 23 & 26 JULI 2025 | B11: 8843790 | O11: 8843790 | T11: =SUM(D11:S11) -> 8843790
A12: PPN IMPOR JULI | B12: 93952 | H12: 93952 | T12: =SUM(D12:S12) -> 93952
A13: SKPKB PPN DES ANG 10 | B13: 6311430 | H13: 6311430 | T13: =SUM(D13:S13) -> 6311430
A14: PPN JULI 2025 | B14: 0 | T14: =SUM(D14:S14) -> 0
A15: SKPKB PPN SEPTEMBER ANG 17 | H15: 1511359.5 | T15: =SUM(D15:S15) -> 1511359.5
A16: SKPKB PPN AGUSTUS ANG 17 | H16: 4159986.9 | T16: =SUM(D16:S16) -> 4159986.9
A17: SKPKB PPN NOVEMBER ANG 17 | H17: 4326280.6 | T17: =SUM(D17:S17) -> 4326280.6
A18: SKPKB PPN OKTOBER ANG 17 | H18: 9861633.8 | T18: =SUM(D18:S18) -> 9861633.8
A19: SKPKB PPN DESEMBER ANG 17 | H19: 6311430.1 | T19: =SUM(D19:S19) -> 6311430.1
A20: SKPKB PPN JULI ANG 17 | H20: 34696.833 | T20: =SUM(D20:S20) -> 34696.833
A21: SKPKB PPH 23 MARET ANG 17 | H21: 532953.92 | T21: =SUM(D21:S21) -> 532953.92
A22: SKPKB PPH 23 APRIL ANG 17 | H22: 164520.21 | T22: =SUM(D22:S22) -> 164520.21
A23: SKPKB PPH 23 MEI ANG 17 | H23: 435969.92 | T23: =SUM(D23:S23) -> 435969.92
A24: SKPKB PPH 23 JUNI ANG 17 | H24: 306404.21 | T24: =SUM(D24:S24) -> 306404.21
A25: SKPKB PPH 23 JULI ANG 17 | H25: 306404.21 | T25: =SUM(D25:S25) -> 306404.21
A26: SKPKB PPH 23 AGUSTUS ANG 17 | H26: 301269.92 | T26: =SUM(D26:S26) -> 301269.92
... A32: SKPKB STP PPN ANG 17 | H32: 1436205.4 | T32: =SUM(D32:S32) -> 1436205.4
T34: =SUM(D34:S34) -> 0
B35: TOTAL PAJAK | D35: =SUM(D7:D34) -> 0 | E35: =SUM(E7:E34) -> 0 | F35: =SUM(F7:F34) -> 0 | G35: =SUM(G7:G34) -> 0 | H35: =SUM(H7:H34) -> 46190827 | I35: =SUM(I7:I34) -> 0 | J35: =SUM(J7:J34) -> 104638748 | K35: =SUM(K7:K34) -> 0 | ... S35: =SUM(S7:S34) -> 0 | T35: =SUM(T7:T33) -> 3.8858056e+08

Sheet OUT - HR - Gaji & Benefit
B1: Kategori : | C1: Cash Outflow (Pengeluaran Kas) | E1: Hari Kerja
B2: Pos Akun : | C2: Out-HR- Gaji & Benefit | E2: Jadwal Pembayaran (Selasa/ Jumat)
B3: Periode : | E3: Hari Libur
B4: Updated on : | C4: ='OUT-ACC-PAJAK'!C4 -> 45947 | D4: Pengeluaran Biaya Operating Sales & Marketing | E4: Pengeluaran Biaya Operating Sales & Marketing
D5: JUMAT | E5: SABTU | F5: MINGGU | G5: SENIN | H5: SELASA | I5: RABU | J5: KAMIS | K5: JUMAT | L5: SABTU | M5: MINGGU | N5: SENIN | O5: SELASA | P5: RABU | Q5: KAMIS | R5: JUMAT | S5: SABTU
A6: KETERANGAN | B6: NOMINAL | C6: TANGGAL | D6: 45947 | E6: 45948 | F6: 45949 | G6: 45950 | H6: 45951 | I6: 45952 | J6: 45953 | K6: 45954 | L6: 45955 | M6: 45956 | N6: 45957 | O6: 45958 | P6: 45959 | Q6: 45960 | R6: 45961 | S6: 45962 | T6: TOTAL
S7: 250000000 | T7: =SUM(D7:S7) -> 250000000
T8: =SUM(D8:S8) -> 0
T9: =SUM(D9:S9) -> 0
T10: =SUM(D10:S10) -> 0
T11: =SUM(D11:S11) -> 0
T12: =SUM(D12:S12) -> 0
T13: =SUM(D13:S13) -> 0
T14: =SUM(D14:S14) -> 0
T15: =SUM(D15:S15) -> 0
T16: =SUM(D16:S16) -> 0
T17: =SUM(D17:S17) -> 0
B18: TOTAL BIAYA HRD | D18: =SUM(D7:D17) -> 0 | E18: =SUM(E7:E17) -> 0 | F18: =SUM(F7:F17) -> 0 | G18: =SUM(G7:G17) -> 0 | H18: =SUM(H7:H17) -> 0 | I18: =SUM(I7:I17) -> 0 | J18: =SUM(J7:J17) -> 0 | K18: =SUM(K7:K17) -> 0 | ... T18: =SUM(T7:T17) -> 250000000

Sheet OUT - CFC - Corporate Expenses
C1: Kategori : | E1: Cash Outflow (Pengeluaran Kas) | J1: Hari Kerja
C2: Pos Akun : | E2: Out-CFC-Corporate Expenses | J2: Jadwal Pembayaran (Selasa/ Jumat)
C3: Periode : | J3: Hari Libur
C4: Updated on : | E4: 45947 | I4: Pengeluaran Biaya Operating Sales & Marketing | J4: Pengeluaran Biaya Operating Sales & Marketing
H5: JUMAT | I5: SABTU | J5: MINGGU | K5: SENIN | L5: SELASA | M5: RABU | N5: KAMIS | O5: JUMAT | P5: SABTU | Q5: MINGGU | R5: SENIN | S5: SELASA | T5: RABU | U5: KAMIS | V5: JUMAT | W5: SABTU
A6: A | B6: cicilan/bln | C6: KETERANGAN | E6: NOMINAL | F6: TGL JATUH TEMPO | G6: TANGGAL | H6: 45947 | I6: 45948 | J6: 45949 | K6: 45950 | L6: 45951 | M6: 45952 | N6: 45953 | O6: 45954 | P6: 45955 | Q6: 45956 | R6: 45957 | S6: 45958 | T6: 45959 | U6: 45960 | V6: 45961 | W6: 45962 | X6: TOTAL
A7: 1 | B7: sdh dibyr lunas mggu lalu | C7: CC BRI Easy Card 5188 2802 8215 3601 (Based on billing tagihan bulan Okt) Tagihan Okt sudah dibayar | E7: 6352050 | F7: 22 OKT 2025 | X7: =SUM(H7:W7) -> 0
A8: 2 | B8: 5634050 | C8: CC DANAMON 5522 3923 4584 5175 dicicil 12x sdh dbyr 6x, bln ini sdh dbyr | E8: =167081785-B8 -> 161447735 | F8: 21 OKT 2025 | X8: =SUM(H8:W8) -> 0
A9: 3 | B9: =832665+835057 -> 1667722 | C9: CC HSBC 4034 0900 0329 0809 dicicil 36x sdh dbyr 4x @832.665 dicicil 36x sdh dbyr 4x @835.057 | E9: 26541476 | F9: 45958 | N9: =E9 -> 26541476 | X9: =SUM(H9:W9) -> 26541476
A10: 4 | B10: =2492006+103899 -> 2595905 | C10: CC HSBC 5183 2301 0213 6604 dicicil 36x sdh dibyr 4x @2,492,006 dicicil 4x sdh dibyr 4x @103,899 | E10: =60745985.546 -> 60745986 | F10: 45958 | N10: =B10 -> 2595905 | X10: =SUM(H10:W10) -> 2595905
A11: 5 | B11: =7518739+5406875 -> 12925614 | C11: CC DANAMON AMEX 3755 312077 38007 (dicicil 6x & sdh dbyr 3x) @7.518.739 dicicil 6x, sdh dbyr 1x @ 5.406.875, bln ini sudah dibayar | E11: =62783184-B11 -> 49857570 | F11: 45951 | X11: =SUM(H11:W11) -> 0
A12: 6 | C12: CC BRI PLATINUM 5520 0202 8322 8201, rencana bayar 13.764.854 | E12: 72553690 | F12: 45957 | N12: =E12 -> 72553690 | X12: =SUM(H12:W12) -> 72553690
A13: 7 | C13: CC DBS 4374-5600-0155-3448 rencana bayar 17.801.124 | E13: 21287550 | F13: 45932 | L13: 17801124 | X13: =SUM(H13:W13) -> 17801124
A14: 8 | C14: CC MANDIRI 4149 3130 0154 8958 Sdh dibyr tgl 07 Okt 2025 = 11.796.341 Akan dibyr lg tgl 21 Okt 25 = 18.101.721 | E14: =112039827-11796341 -> 100243486 | F14: 45938 | L14: 18101721 | X14: =SUM(H14:W14) -> 18101721
A15: 9 | C15: CC OCBC 4645 8311 0202 4628 Sdh dibyr tgl 02 Okt 25 = 5.040.126 | E15: =36348680-5040125 -> 31308555 | F15: 45936 | X15: =SUM(H15:W15) -> 0
A16: 10 | C16: CC DANAMON 3755 312163 39003 AMEX Sdh dibyr tgl 02 Okt 25 = 5.301.962 Akan dibyr lg tgl 21 Okt 25 = 15.178.135 | E16: =25057506-5301962 -> 19755544 | F16: 45935 | L16: 15178135 | X16: =SUM(H16:W16) -> 15178135
A17: 11 | C17: CC DANAMON 4258570913716109 INFINIT Sdh dibyr tgl 02 Okt 25 = 4.316.821 | E17: =13517654-4316821 -> 9200833 | F17: 45935 | X17: =SUM(H17:W17) -> 0
A18: 12 | C18: CC DANAMON 3567 9600 0500 0322 Sdh dibyr tgl 02 Okt 25 = 729.297 | E18: =12116411-729297 -> 11387114 | F18: 45935 | X18: =SUM(H18:W18) -> 0
A19: 13 | C19: CC MEGA 4201 9400 5250 1935 Sdh dibyr tgl 07 Okt 25 = 4.147.313 | E19: =50251214-414731 -> 49836483 | F19: 45940 | X19: =SUM(H19:W19) -> 0
A20: 14 | C20: CC MANDIRI 4137 1803 1348 6456 (Based on billing tagihan Okt 25) Tagihan Okt 25 sudah dibayar | E20: 2732885 | F20: 45941 | X20: =SUM(H20:W20) -> 0
A21: 15 | C21: CC MANDIRI 5126 7603 0309 4806 (Based on tagihan bulan Okt 2025) Tagihan Okt sudah dibayar | E21: 1440227 | F21: 45941 | X21: =SUM(H21:W21) -> 0
A22: 16 | C22: CC OCBC 5241 6955 0205 4757 (Based on tagihan bulan Okt 25) Tagihan Okt sudah dibayar | E22: 2793758 | F22: 45938 | X22: =SUM(H22:W22) -> 0
A23: 17 | C23: CC UOB 4219 2020 7256 0866 (Based on billing tagihan bln Okt 25) Tagihan Okt 25 sudah dibayar | E23: 2358430 | F23: 45935 | X23: =SUM(H23:W23) -> 0
A24: 18 | C24: CC CIMB 5463 1800 6037 0623 Sdh dibyr tgl 02 Okt 25 = 2.722.709 | E24: =24245918.57-2722709 -> 21523210 | F24: 45936 | X24: =SUM(H24:W24) -> 0
A25: 19 | C25: CC BNI CORP 4365 8300 0015 5888 (bln Okt 25 blm ada tagihan) | D25: Dita | E25: 0 | F25: 45939 | X25: =SUM(H25:W25) -> 0
A26: 20 | C26: CC BNI CORP 4365 8300 0015 5896 (based on billing tagihan Okt 25) Bln Okt 25 sudah dibayar tgl 09 Okt 25 | E26: 3079320 | F26: 45939 | X26: =SUM(H26:W26) -> 0
A27: 21 | C27: CC BNI CORP 4365 8300 0015 5904 (Based on Billing tagihan bulan Sept 25) Sdh dibyr bln Okt 25 = 88.383.689 | D27: Dimas | E27: =88383689 -> 88383689 | F27: 45939 | X27: =SUM(H27:W27) -> 0
A28: 22 | C28: CC BNI CORP 4365 8300 0015 5912 Sdh dibyr tgl 16 Okt 25 = 14.500.000 | E28: =34855152-14500000 -> 20355152 | F28: 45939 | X28: =SUM(H28:W28) -> 0
A29: 23 | C29: CC BNI CORP 4365 8300 0015 5961 Sdh dibyr tgl 14 Okt 25 = 22.842.460 | D29: Fadli | E29: =60217678-22842460 -> 37375218 | F29: 45939 | L29: 30526520 | S29: 7441198 | X29: =SUM(H29:W29) -> 37967718
A30: 24 | C30: CC BNI CORP 4365 8300 0015 5953 Blm ada tagihan CC bln Okt 25. | D30: Adiel | E30: 0 | F30: 45939 | X30: =SUM(H30:W30) -> 0
C31: Persiapan subscription (362 jt / tahun -> per bulan = 35 jt an) | E31: 35000000 | W31: 35000000 | X31: =SUM(H31:W31) -> 35000000
C32: WTM London : - tiket pesawat sdh masuk ek CC 100 jt - sisanya 74.636.000 | E32: 174636000 | M32: 74636000 | X32: =SUM(H32:W32) -> 74636000
C33: TOTAL | E33: =SUM(E7:E31) -> 8.3555996e+08 | H33: =SUM(H7:H32) -> 0 | I33: =SUM(I7:I32) -> 0 | J33: =SUM(J7:J32) -> 0 | K33: =SUM(K7:K32) -> 0 | L33: =SUM(L7:L32) -> 81607500 | M33: =SUM(M7:M32) -> 74636000 | N33: =SUM(N7:N32) -> 101691071 | O33: =SUM(O7:O32) -> 0 | ... X33: =SUM(X7:X32) -> 300375769

Sheet OUT - ACC - Ops Kantor
B1: Kategori : | C1: Cash Outflow (Pengeluaran Kas) | E1: Hari Kerja
B2: Pos Akun : | C2: Pengeluaran Operasional Kantor | E2: Jadwal Pembayaran (Selasa/ Jumat)
B3: Periode : | E3: Hari Libur
B4: Kategori : | C4: Cash Outflow (Pengeluaran Kas) | F4: Hari Kerja
B5: Pos Akun : | C5: Out-ACC-Ops | F5: Jadwal Pembayaran (Selasa/Kamis)
B6: Periode : | F6: Hari Libur
B7: Updated on : | C7: ='OUT - CFC - Bunga & Angsuran'!H4 -> 0 | D7: Pengeluaran Biaya Operating Sales & Marketing | E7: Pengeluaran Biaya Operating Sales & Marketing
D8: JUMAT | E8: SABTU | F8: MINGGU | G8: SENIN | H8: SELASA | I8: RABU | J8: KAMIS | K8: JUMAT | L8: SABTU | M8: MINGGU | N8: SENIN | O8: SELASA | P8: RABU | Q8: KAMIS | R8: JUMAT | S8: SABTU
A9: KETERANGAN | B9: NOMINAL | C9: TANGGAL | D9: 45947 | E9: 45948 | F9: 45949 | G9: 45950 | H9: 45951 | I9: 45952 | J9: 45953 | K9: 45954 | L9: 45955 | M9: 45956 | N9: 45957 | O9: 45958 | P9: 45959 | Q9: 45960 | R9: 45961 | S9: 45962 | T9: TOTAL
T10: =SUM(D10:S10) -> 0
T11: =SUM(D11:S11) -> 0
T12: =SUM(D12:S12) -> 0
T13: =SUM(D13:S13) -> 0
T14: =SUM(D14:S14) -> 0
T15: =SUM(D15:S15) -> 0
T16: =SUM(D16:S16) -> 0
T17: =SUM(D17:S17) -> 0
T18: =SUM(D18:S18) -> 0
T19: =SUM(D19:S19) -> 0
T20: =SUM(D20:S20) -> 0
B21: TOTAL BIAYA ACC | D21: =SUM(D10:D20) -> 0 | E21: =SUM(E10:E20) -> 0 | F21: =SUM(F10:F20) -> 0 | G21: =SUM(G10:G20) -> 0 | H21: =SUM(H10:H20) -> 0 | I21: =SUM(I10:I20) -> 0 | J21: =SUM(J10:J20) -> 0 | K21: =SUM(K10:K20) -> 0 | ... T21: =SUM(T10:T20) -> 0

Sheet OUT-ACS-OPS
B1: Kategori : | C1: Cash Outflow (Pengeluaran Kas) | F1: Hari Kerja
B2: Pos Akun : | C2: Out-ACS-Ops | F2: Jadwal Pembayaran (Selasa/ Kamis)
B3: Periode : | F3: Hari Libur
B4: Updated on : | C4: 45947 | D4: Pengeluaran Biaya Operating Sales & Marketing
D5: JUMAT | E5: SABTU | F5: MINGGU | G5: SENIN | H5: SELASA | I5: RABU | J5: KAMIS | K5: JUMAT | L5: SABTU | M5: MINGGU | N5: SENIN | O5: SELASA | P5: RABU | Q5: KAMIS | R5: JUMAT | S5: SABTU
A6: KETERANGAN | B6: NOMINAL | C6: TANGGAL | D6: 45947 | E6: 45948 | F6: 45949 | G6: 45950 | H6: 45951 | I6: 45952 | J6: 45953 | K6: 45954 | L6: 45955 | M6: 45956 | N6: 45957 | O6: 45958 | P6: 45959 | Q6: 45960 | R6: 45961 | S6: 45962 | T6: TOTAL
T7: =SUM(D7:S7) -> 0
T8: =SUM(D8:S8) -> 0
T9: =SUM(D9:S9) -> 0
T10: =SUM(D10:S10) -> 0
T11: =SUM(D11:S11) -> 0
T12: =SUM(D12:S12) -> 0
T13: =SUM(D13:S13) -> 0
T14: =SUM(D14:S14) -> 0
T15: =SUM(D15:S15) -> 0
T16: =SUM(D16:S16) -> 0
T17: =SUM(D17:S17) -> 0
B18: TOTAL BIAYA ACS | D18: =SUM(D7:D17) -> 0 | E18: =SUM(E7:E17) -> 0 | F18: =SUM(F7:F17) -> 0 | G18: =SUM(G7:G17) -> 0 | H18: =SUM(H7:H17) -> 0 | I18: =SUM(I7:I17) -> 0 | J18: =SUM(J7:J17) -> 0 | K18: =SUM(K7:K17) -> 0 | ... T18: =SUM(T7:T17) -> 0

Sheet OUT-BAS-OPS
B1: Kategori : | C1: Cash Outflow (Pengeluaran Kas) | F1: Hari Kerja
B2: Pos Akun : | C2: Out-Ops-BAS | F2: Jadwal Pembayaran (Selasa/ Kamis)
B3: Periode : | F3: Hari Libur
B4: Updated on : | C4: 45947 | D4: Pengeluaran Biaya Operating Sales & Marketing
D5: JUMAT | E5: SABTU | F5: MINGGU | G5: SENIN | H5: SELASA | I5: RABU | J5: KAMIS | K5: JUMAT | L5: SABTU | M5: MINGGU | N5: SENIN | O5: SELASA | P5: RABU | Q5: KAMIS | R5: JUMAT | S5: SABTU
A6: KETERANGAN | B6: NOMINAL | C6: TANGGAL | D6: 45947 | E6: 45948 | F6: 45949 | G6: 45950 | H6: 45951 | I6: 45952 | J6: 45953 | K6: 45954 | L6: 45955 | M6: 45956 | N6: 45957 | O6: 45958 | P6: 45959 | Q6: 45960 | R6: 45961 | S6: 45962 | T6: TOTAL
T7: =SUM(D7:S7) -> 0
T8: =SUM(D8:S8) -> 0
T9: =SUM(D9:S9) -> 0
T10: =SUM(D10:S10) -> 0
T11: =SUM(D11:S11) -> 0
T12: =SUM(D12:S12) -> 0
T13: =SUM(D13:S13) -> 0
T14: =SUM(D14:S14) -> 0
T15: =SUM(D15:S15) -> 0
T16: =SUM(D16:S16) -> 0
T17: =SUM(D17:S17) -> 0
B18: TOTAL BIAYA BAS | D18: =SUM(D7:D17) -> 0 | E18: =SUM(E7:E17) -> 0 | F18: =SUM(F7:F17) -> 0 | G18: =SUM(G7:G17) -> 0 | H18: =SUM(H7:H17) -> 0 | I18: =SUM(I7:I17) -> 0 | J18: =SUM(J7:J17) -> 0 | K18: =SUM(K7:K17) -> 0 | ... T18: =SUM(T7:T17) -> 0

Sheet OUT-BID-OPS
B1: Kategori : | C1: Cash Outflow (Pengeluaran Kas) | F1: Hari Kerja
B2: Pos Akun : | C2: OUT-BID-OPS | F2: Jadwal Pembayaran (Selasa/ Kamis)
B3: Periode : | F3: Hari Libur
B4: Updated on : | C4: 45947 | D4: Pengeluaran Biaya Operating Sales & Marketing
D5: JUMAT | E5: SABTU | F5: MINGGU | G5: SENIN | H5: SELASA | I5: RABU | J5: KAMIS | K5: JUMAT | L5: SABTU | M5: MINGGU | N5: SENIN | O5: SELASA | P5: RABU | Q5: KAMIS | R5: JUMAT | S5: SABTU
A6: HTANG PAJAK | B6: NOMINAL | C6: TANGGAL | D6: 45947 | E6: 45948 | F6: 45949 | G6: 45950 | H6: 45951 | I6: 45952 | J6: 45953 | K6: 45954 | L6: 45955 | M6: 45956 | N6: 45957 | O6: 45958 | P6: 45959 | Q6: 45960 | R6: 45961 | S6: 45962 | T6: TOTAL
T8: =SUM(D8:S8) -> 0
T9: =SUM(D9:S9) -> 0
T10: =SUM(D10:S10) -> 0
T11: =SUM(D11:S11) -> 0
B12: TOTAL | D12: =SUM(D8:D11) -> 0 | E12: =SUM(E8:E11) -> 0 | F12: =SUM(F8:F11) -> 0 | G12: =SUM(G8:G11) -> 0 | H12: =SUM(H8:H11) -> 0 | I12: =SUM(I8:I11) -> 0 | J12: =SUM(J8:J11) -> 0 | K12: =SUM(K8:K11) -> 0 | ... T12: =SUM(T8:T11) -> 0

Sheet OUT-CFC-OPS
B1: Kategori : | C1: Cash Outflow (Pengeluaran Kas) | F1: Hari Kerja
B2: Pos Akun : | C2: OUT-CFC-OPS | F2: Jadwal Pembayaran (Selasa/ Kamis)
B3: Periode : | F3: Hari Libur
B4: Updated on : | C4: 45947 | D4: Pengeluaran Biaya Operating Sales & Marketing
D5: JUMAT | E5: SABTU | F5: MINGGU | G5: SENIN | H5: SELASA | I5: RABU | J5: KAMIS | K5: JUMAT | L5: SABTU | M5: MINGGU | N5: SENIN | O5: SELASA | P5: RABU | Q5: KAMIS | R5: JUMAT | S5: SABTU
A6: HTANG PAJAK | B6: NOMINAL | C6: TANGGAL | D6: 45947 | E6: 45948 | F6: 45949 | G6: 45950 | H6: 45951 | I6: 45952 | J6: 45953 | K6: 45954 | L6: 45955 | M6: 45956 | N6: 45957 | O6: 45958 | P6: 45959 | Q6: 45960 | R6: 45961 | S6: 45962 | T6: TOTAL
T8: =SUM(D8:S8) -> 0
T9: =SUM(D9:S9) -> 0
T10: =SUM(D10:S10) -> 0
T11: =SUM(D11:S11) -> 0
B12: TOTAL | D12: =SUM(D8:D11) -> 0 | E12: =SUM(E8:E11) -> 0 | F12: =SUM(F8:F11) -> 0 | G12: =SUM(G8:G11) -> 0 | H12: =SUM(H8:H11) -> 0 | I12: =SUM(I8:I11) -> 0 | J12: =SUM(J8:J11) -> 0 | K12: =SUM(K8:K11) -> 0 | ... S12: =SUM(S8:S11) -> 0 | T12: =SUM(D12:S12) -> 0

Sheet OUT-GA-OPS
B1: Kategori : | C1: Cash Outflow (Pengeluaran Kas) | F1: Hari Kerja
B2: Pos Akun : | C2: OUT-GA-OPS | F2: Jadwal Pembayaran (Selasa/ Kamis)
B3: Periode : | F3: Hari Libur
B4: Updated on : | C4: 45947 | D4: Pengeluaran Biaya Operating Sales & Marketing
D5: JUMAT | E5: SABTU | F5: MINGGU | G5: SENIN | H5: SELASA | I5: RABU | J5: KAMIS | K5: JUMAT | L5: SABTU | M5: MINGGU | N5: SENIN | O5: SELASA | P5: RABU | Q5: KAMIS | R5: JUMAT | S5: SABTU
A6: HTANG PAJAK | B6: NOMINAL | C6: TANGGAL | D6: 45947 | E6: 45948 | F6: 45949 | G6: 45950 | H6: 45951 | I6: 45952 | J6: 45953 | K6: 45954 | L6: 45955 | M6: 45956 | N6: 45957 | O6: 45958 | P6: 45959 | Q6: 45960 | R6: 45961 | S6: 45962 | T6: TOTAL
A8: LISTRIK NOVEMBER | B8: 8000000 | O8: 8000000 | T8: =SUM(D8:S8) -> 8000000
A9: SEWA LAPANGAN BADMINTON | B9: 1200000 | H9: 1200000 | T9: =SUM(D9:S9) -> 1200000
A10: CATERING MAKAN SIANG | B10: 9000000 | H10: 4500000 | O10: 4500000 | T10: =SUM(D10:S10) -> 9000000
A11: BUAH | B11: 600000 | H11: 300000 | O11: 300000 | T11: =SUM(D11:S11) -> 600000
A12: ES BATU | B12: 80000 | H12: 40000 | O12: 40000 | T12: =SUM(D12:S12) -> 80000
A13: KADO FAREWELL | B13: 600000 | O13: 600000 | T13: =SUM(D13:S13) -> 600000
A14: KARANGAN BUNGA - TENTATIVE | B14: 1000000 | O14: 1000000 | T14: =SUM(D14:S14) -> 1000000
A15: PAJAK VARIO AB 4432 QI | B15: 300000 | J15: 300000 | T15: =SUM(D15:S15) -> 300000
A16: PAJAK VARIO AB 5523 KA | B16: 300000 | Q16: 300000 | T16: =SUM(D16:S16) -> 300000
A17: SERVICE POMPA WIPER | B17: 1000000 | O17: 1000000 | T17: =SUM(D17:S17) -> 1000000
A18: ASURANSI XPANDER | B18: 300000 | H18: 300000 | T18: =SUM(D18:S18) -> 300000
A19: SELANG WASTAFEL, FLASHER, SEALANT | B19: 300000 | O19: 300000 | T19: =SUM(D19:S19) -> 300000
A20: BBM MINGGUAN ZENIX & EXPANDER | B20: 600000 | H20: 600000 | T20: =SUM(D20:S20) -> 600000
A21: BBM GENSET | B21: 300000 | H21: 300000 | T21: =SUM(D21:S21) -> 300000
A22: PAKET FILTER WATER PURIFIER | B22: 2300000 | Q22: 2300000 | T22: =SUM(D22:S22) -> 2300000
A23: SELANG DAN CORONG VAKUM | B23: 660000 | H23: 660000 | T23: =SUM(D23:S23) -> 660000
T24: =SUM(D24:S24) -> 0
T25: =SUM(D25:S25) -> 0
B26: TOTAL | D26: =SUM(D8:D25) -> 0 | E26: =SUM(E8:E25) -> 0 | F26: =SUM(F8:F25) -> 0 | G26: =SUM(G8:G25) -> 0 | H26: =SUM(H8:H25) -> 7900000 | I26: =SUM(I8:I25) -> 0 | J26: =SUM(J8:J25) -> 300000 | K26: =SUM(K8:K25) -> 0 | ... S26: =SUM(S8:S25) -> 0 | T26: =SUM(D26:S26) -> 26540000

Sheet OUT-HR-OPS
B1: Kategori : | C1: Cash Outflow (Pengeluaran Kas) | F1: Hari Kerja
B2: Pos Akun : | C2: OUT-HR-OPS | F2: Jadwal Pembayaran (Selasa/ Kamis)
B3: Periode : | F3: Hari Libur
B4: Updated on : | C4: 45947 | D4: Pengeluaran Biaya Operating Sales & Marketing
D5: JUMAT | E5: SABTU | F5: MINGGU | G5: SENIN | H5: SELASA | I5: RABU | J5: KAMIS | K5: JUMAT | L5: SABTU | M5: MINGGU | N5: SENIN | O5: SELASA | P5: RABU | Q5: KAMIS | R5: JUMAT | S5: SABTU
A6: DESKRIPSI | B6: NOMINAL | C6: TANGGAL | D6: 45947 | E6: 45948 | F6: 45949 | G6: 45950 | H6: 45951 | I6: 45952 | J6: 45953 | K6: 45954 | L6: 45955 | M6: 45956 | N6: 45957 | O6: 45958 | P6: 45959 | Q6: 45960 | R6: 45961 | S6: 45962 | T6: TOTAL
A8: Training Branch Manager | B8: 5500000 | L8: 5500000 | T8: =SUM(D8:S8) -> 5500000
A9: CSR ke Darul Ullum by Lazismu | B9: 5000000 | O9: 5000000 | T9: =SUM(D9:S9) -> 5000000
A10: Posting lowongan di Glints | B10: 2000000 | J10: 2000000 | T10: =SUM(D10:S10) -> 2000000
A11: Posting lowongan di linkedIn (by CC) | B11: 2000000 | K11: 2000000 | T11: =SUM(D11:S11) -> 2000000
A12: Training Buttler for GA | B12: 2000000 | O12: 2000000 | T12: =SUM(D12:S12) -> 2000000
T13: =SUM(D13:S13) -> 0
T14: =SUM(D14:S14) -> 0
B15: TOTAL | D15: =SUM(D8:D14) -> 0 | E15: =SUM(E8:E14) -> 0 | F15: =SUM(F8:F14) -> 0 | G15: =SUM(G8:G14) -> 0 | H15: =SUM(H8:H14) -> 0 | I15: =SUM(I8:I14) -> 0 | J15: =SUM(J8:J14) -> 2000000 | K15: =SUM(K8:K14) -> 2000000 | ... S15: =SUM(S8:S14) -> 0 | T15: =SUM(D15:S15) -> 16500000

Sheet OUT-PD-OPS
B1: Kategori : | C1: Cash Outflow (Pengeluaran Kas) | F1: Hari Kerja
B2: Pos Akun : | C2: OUT-PD-OPS | F2: Jadwal Pembayaran (Selasa/ Kamis)
B3: Periode : | F3: Hari Libur
B4: Updated on : | C4: 45947 | D4: Pengeluaran Biaya Operating Sales & Marketing
D5: JUMAT | E5: SABTU | F5: MINGGU | G5: SENIN | H5: SELASA | I5: RABU | J5: KAMIS | K5: JUMAT | L5: SABTU | M5: MINGGU | N5: SENIN | O5: SELASA | P5: RABU | Q5: KAMIS | R5: JUMAT | S5: SABTU
A6: HTANG PAJAK | B6: NOMINAL | C6: TANGGAL | D6: 45947 | E6: 45948 | F6: 45949 | G6: 45950 | H6: 45951 | I6: 45952 | J6: 45953 | K6: 45954 | L6: 45955 | M6: 45956 | N6: 45957 | O6: 45958 | P6: 45959 | Q6: 45960 | R6: 45961 | S6: 45962 | T6: TOTAL
T8: =SUM(D8:S8) -> 0
T9: =SUM(D9:S9) -> 0
T10: =SUM(D10:S10) -> 0
T11: =SUM(D11:S11) -> 0
B12: TOTAL | D12: =SUM(D8:D11) -> 0 | E12: =SUM(E8:E11) -> 0 | F12: =SUM(F8:F11) -> 0 | G12: =SUM(G8:G11) -> 0 | H12: =SUM(H8:H11) -> 0 | I12: =SUM(I8:I11) -> 0 | J12: =SUM(J8:J11) -> 0 | K12: =SUM(K8:K11) -> 0 | ... S12: =SUM(S8:S11) -> 0 | T12: =SUM(D12:S12) -> 0

Sheet OUT-SS-OPS
B1: Kategori : | C1: Cash Outflow (Pengeluaran Kas) | F1: Hari Kerja
B2: Pos Akun : | C2: OUT-SS-OPS | F2: Jadwal Pembayaran (Selasa/ Kamis)
B3: Periode : | F3: Hari Libur
B4: Updated on : | C4: 45947 | D4: Pengeluaran Biaya Operating Sales & Marketing
D5: JUMAT | E5: SABTU | F5: MINGGU | G5: SENIN | H5: SELASA | I5: RABU | J5: KAMIS | K5: JUMAT | L5: SABTU | M5: MINGGU | N5: SENIN | O5: SELASA | P5: RABU | Q5: KAMIS | R5: JUMAT | S5: SABTU
A6: HTANG PAJAK | B6: NOMINAL | C6: TANGGAL | D6: 45947 | E6: 45948 | F6: 45949 | G6: 45950 | H6: 45951 | I6: 45952 | J6: 45953 | K6: 45954 | L6: 45955 | M6: 45956 | N6: 45957 | O6: 45958 | P6: 45959 | Q6: 45960 | R6: 45961 | S6: 45962 | T6: TOTAL
T8: =SUM(D8:S8) -> 0
T9: =SUM(D9:S9) -> 0
T10: =SUM(D10:S10) -> 0
T11: =SUM(D11:S11) -> 0
B12: TOTAL | D12: =SUM(D8:D11) -> 0 | E12: =SUM(E8:E11) -> 0 | F12: =SUM(F8:F11) -> 0 | G12: =SUM(G8:G11) -> 0 | H12: =SUM(H8:H11) -> 0 | I12: =SUM(I8:I11) -> 0 | J12: =SUM(J8:J11) -> 0 | K12: =SUM(K8:K11) -> 0 | ... S12: =SUM(S8:S11) -> 0 | T12: =SUM(D12:S12) -> 0

Sheet OUT-SO-OPS
B1: Kategori : | C1: Cash Outflow (Pengeluaran Kas) | F1: Hari Kerja
B2: Pos Akun : | C2: OUT-SO-OPS | F2: Jadwal Pembayaran (Selasa/ Kamis)
B3: Periode : | F3: Hari Libur
B4: Updated on : | C4: 45947 | D4: Pengeluaran Biaya Operating Sales & Marketing
D5: JUMAT | E5: SABTU | F5: MINGGU | G5: SENIN | H5: SELASA | I5: RABU | J5: KAMIS | K5: JUMAT | L5: SABTU | M5: MINGGU | N5: SENIN | O5: SELASA | P5: RABU | Q5: KAMIS | R5: JUMAT | S5: SABTU
A6: HTANG PAJAK | B6: NOMINAL | C6: TANGGAL | D6: 45947 | E6: 45948 | F6: 45949 | G6: 45950 | H6: 45951 | I6: 45952 | J6: 45953 | K6: 45954 | L6: 45955 | M6: 45956 | N6: 45957 | O6: 45958 | P6: 45959 | Q6: 45960 | R6: 45961 | S6: 45962 | T6: TOTAL
T8: =SUM(D8:S8) -> 0
T9: =SUM(D9:S9) -> 0
T10: =SUM(D10:S10) -> 0
T11: =SUM(D11:S11) -> 0
B12: TOTAL | D12: =SUM(D8:D11) -> 0 | E12: =SUM(E8:E11) -> 0 | F12: =SUM(F8:F11) -> 0 | G12: =SUM(G8:G11) -> 0 | H12: =SUM(H8:H11) -> 0 | I12: =SUM(I8:I11) -> 0 | J12: =SUM(J8:J11) -> 0 | K12: =SUM(K8:K11) -> 0 | ... S12: =SUM(S8:S11) -> 0 | T12: =SUM(D12:S12) -> 0

Sheet OUT-TEP-OPS
B1: Kategori : | C1: Cash Outflow (Pengeluaran Kas) | F1: Hari Kerja
B2: Pos Akun : | C2: OUT-TEP-OPS | F2: Jadwal Pembayaran (Selasa/ Kamis)
B3: Periode : | F3: Hari Libur
B4: Updated on : | C4: 45947 | D4: Pengeluaran Biaya Operating Sales & Marketing
D5: JUMAT | E5: SABTU | F5: MINGGU | G5: SENIN | H5: SELASA | I5: RABU | J5: KAMIS | K5: JUMAT | L5: SABTU | M5: MINGGU | N5: SENIN | O5: SELASA | P5: RABU | Q5: KAMIS | R5: JUMAT | S5: SABTU
A6: HTANG PAJAK | B6: NOMINAL | C6: TANGGAL | D6: 45947 | E6: 45948 | F6: 45949 | G6: 45950 | H6: 45951 | I6: 45952 | J6: 45953 | K6: 45954 | L6: 45955 | M6: 45956 | N6: 45957 | O6: 45958 | P6: 45959 | Q6: 45960 | R6: 45961 | S6: 45962 | T6: TOTAL
T8: =SUM(D8:S8) -> 0
T9: =SUM(D9:S9) -> 0
T10: =SUM(D10:S10) -> 0
T11: =SUM(D11:S11) -> 0
B12: TOTAL | D12: =SUM(D8:D11) -> 0 | E12: =SUM(E8:E11) -> 0 | F12: =SUM(F8:F11) -> 0 | G12: =SUM(G8:G11) -> 0 | H12: =SUM(H8:H11) -> 0 | I12: =SUM(I8:I11) -> 0 | J12: =SUM(J8:J11) -> 0 | K12: =SUM(K8:K11) -> 0 | ... S12: =SUM(S8:S11) -> 0 | T12: =SUM(D12:S12) -> 0

Sheet OUT-RESERVASI-OPS
B1: Kategori : | C1: Cash Outflow (Pengeluaran Kas) | F1: Hari Kerja
B2: Pos Akun : | C2: OUT-RESERVASI-OPS | F2: Jadwal Pembayaran (Selasa/ Kamis)
B3: Periode : | F3: Hari Libur
B4: Updated on : | C4: 45947 | D4: Pengeluaran Biaya Operating Sales & Marketing
D5: JUMAT | E5: SABTU | F5: MINGGU | G5: SENIN | H5: SELASA | I5: RABU | J5: KAMIS | K5: JUMAT | L5: SABTU | M5: MINGGU | N5: SENIN | O5: SELASA | P5: RABU | Q5: KAMIS | R5: JUMAT | S5: SABTU
A6: HTANG PAJAK | B6: NOMINAL | C6: TANGGAL | D6: 45947 | E6: 45948 | F6: 45949 | G6: 45950 | H6: 45951 | I6: 45952 | J6: 45953 | K6: 45954 | L6: 45955 | M6: 45956 | N6: 45957 | O6: 45958 | P6: 45959 | Q6: 45960 | R6: 45961 | S6: 45962 | T6: TOTAL
T8: =SUM(D8:S8) -> 0
T9: =SUM(D9:S9) -> 0
T10: =SUM(D10:S10) -> 0
T11: =SUM(D11:S11) -> 0
B12: TOTAL | D12: =SUM(D8:D11) -> 0 | E12: =SUM(E8:E11) -> 0 | F12: =SUM(F8:F11) -> 0 | G12: =SUM(G8:G11) -> 0 | H12: =SUM(H8:H11) -> 0 | I12: =SUM(I8:I11) -> 0 | J12: =SUM(J8:J11) -> 0 | K12: =SUM(K8:K11) -> 0 | ... S12: =SUM(S8:S11) -> 0 | T12: =SUM(D12:S12) -> 0

Sheet OUT-TAKSHAKA-OPS
B1: Kategori : | C1: Cash Outflow (Pengeluaran Kas) | F1: Hari Kerja
B2: Pos Akun : | C2: OUT-TAKSHAKA-OPS | F2: Jadwal Pembayaran (Selasa/ Kamis)
B3: Periode : | F3: Hari Libur
B4: Updated on : | C4: 45947 | D4: Pengeluaran Biaya Operating Sales & Marketing
D5: JUMAT | E5: SABTU | F5: MINGGU | G5: SENIN | H5: SELASA | I5: RABU | J5: KAMIS | K5: JUMAT | L5: SABTU | M5: MINGGU | N5: SENIN | O5: SELASA | P5: RABU | Q5: KAMIS | R5: JUMAT | S5: SABTU
A6: DESKRIPSI | B6: NOMINAL | C6: TANGGAL | D6: 45947 | E6: 45948 | F6: 45949 | G6: 45950 | H6: 45951 | I6: 45952 | J6: 45953 | K6: 45954 | L6: 45955 | M6: 45956 | N6: 45957 | O6: 45958 | P6: 45959 | Q6: 45960 | R6: 45961 | S6: 45962 | T6: TOTAL
T8: =SUM(D8:S8) -> 0
T9: =SUM(D9:S9) -> 0
T10: =SUM(D10:S10) -> 0
T11: =SUM(D11:S11) -> 0
B12: TOTAL | D12: =SUM(D8:D11) -> 0 | E12: =SUM(E8:E11) -> 0 | F12: =SUM(F8:F11) -> 0 | G12: =SUM(G8:G11) -> 0 | H12: =SUM(H8:H11) -> 0 | I12: =SUM(I8:I11) -> 0 | J12: =SUM(J8:J11) -> 0 | K12: =SUM(K8:K11) -> 0 | ... S12: =SUM(S8:S11) -> 0 | T12: =SUM(D12:S12) -> 0

Sheet OUT - CFC - Bunga & Angsuran
G1: Kategori : | H1: Cash Outflow (Pengeluaran Kas) | K1: Hari Kerja
G2: Pos Akun : | H2: Out-CFC-Pengeluaran Pembayaran Bunga & Angsuran | K2: Jadwal Pembayaran (Selasa/Kamis)
G3: Periode : | K3: Hari Libur
G4: Updated on : | H4: ='OUT - HR - Pemberian Pinjaman'!C4 -> 0 | I4: Pengeluaran Biaya Operating Sales & Marketing | J4: Pengeluaran Biaya Operating Sales & Marketing
I5: JUMAT | J5: SABTU | K5: MINGGU | L5: SENIN | M5: SELASA | N5: RABU | O5: KAMIS | P5: JUMAT | Q5: SABTU | R5: MINGGU | S5: SENIN | T5: SELASA | U5: RABU | V5: KAMIS | W5: JUMAT | X5: SABTU
A6: Nama Pos | B6: Bunga | C6: Pokok | D6: Nomor Kontrak | E6: Rekening Bank | F6: PERIODE PEMBAYARAN | G6: NOMINAL PEMBAYARAN | H6: TANGGAL | I6: 45947 | J6: 45948 | K6: 45949 | L6: 45950 | M6: 45951 | N6: 45952 | O6: 45953 | P6: 45954 | Q6: 45955 | R6: 45956 | S6: 45957 | T6: 45958 | U6: 45959 | V6: 45960 | W6: 45961 | X6: 45962 | Y6: TOTAL
A7: Biaya Bunga Pinjaman Modal Individu
A8: Biaya Bunga Pinjaman Modal BRI
F15: Total Biaya Bunga Modal Individu | I15: =SUM(I8:I14) -> 0 | J15: =SUM(J8:J14) -> 0 | K15: =SUM(K8:K14) -> 0 | L15: =SUM(L8:L14) -> 0 | M15: =SUM(M8:M14) -> 0 | N15: =SUM(N8:N14) -> 0 | O15: =SUM(O8:O14) -> 0 | P15: =SUM(P8:P14) -> 0 | ... Y15: =SUM(Y8:Y14) -> 0
A21: Biaya Bunga & Angsuran Pokok Kartu Kredit (Jika ada) | B21: Tgl Cetak | C21: Tgl Jatuh Tempo | D21: Tot Tagihan | E21: Min Payment | F21: Rencana Payment | G21: Sisa Tagihan | I21: 44711 | J21: 44712
G28: TOTAL BIAYA PEMBAYARAN RUTIN BUNGA & ANGSURAN | I28: =SUM(I22:I27) -> 0 | J28: =SUM(J22:J27) -> 0

Sheet OUT - TEP - Cost Of Revenue
C1: EXPENSES | D1: Kategori : | E1: Cash Outflow (Pengeluaran Kas) | H1: Hari Kerja
C2: 80% DP | D2: Pos Akun : | E2: OUT-TEP-COST OF REVENUE | H2: Jadwal Pembayaran (Selasa/ Kamis)
C3: 20% PEL | D3: Periode : | H3: Hari Libur
D4: Updated on : | E4: ='IN-ACC-Piutang & Revenue'!D4 -> 0 | F4: Pengeluaran Biaya Operating Sales & Marketing | G4: Pengeluaran Biaya Operating Sales & Marketing
H5: JUMAT | I5: SABTU | J5: MINGGU | K5: SENIN | L5: SELASA | M5: RABU | N5: KAMIS | O5: JUMAT | P5: SABTU | Q5: MINGGU | R5: SENIN | S5: SELASA | T5: RABU | U5: KAMIS | V5: JUMAT | W5: SABTU
B6: COMPANY | C6: EVENT | D6: EST PENERIMAAN REVENUE | E6: EST NET REVENUE | F6: EST EXPENSE (80% x Tot. Rev) | G6: TANGGAL | H6: 45947 | I6: 45948 | J6: 45949 | K6: 45950 | L6: 45951 | M6: 45952 | N6: 45953 | O6: 45954 | P6: 45955 | Q6: 45956 | R6: 45957 | S6: 45958 | T6: 45959 | U6: 45960 | V6: 45961 | W6: 45962 | X6: TOTAL
X10: =SUM(H10:W10) -> 0
B11: GIZ | C11: GIZ IKI INTERFACE WORKSHOP | D11: 294821550 | E11: =D11*100/111 -> 265605000 | F11: 195035000 | G11: 21 OKTOBER 2025 | H11: 23965000 | L11: 37000000 | S11: 37750000 | X11: =SUM(H11:W11) -> 98715000
B12: PT RINTIS SEJAHTERA | C12: PRIMA EXECUTIVE GATHERING | D12: 1475000000 | E12: =D12*100/111 -> 1.3288288e+09 | F12: 1164220200 | G12: 22-23 OKTOBER 2025 | H12: 516172600 | L12: 75150000 | U12: 1750000 | X12: =SUM(H12:W12) -> 593072600
B13: ELITERY | C13: ELITERY WFA WEEK | D13: 581440000 | E13: =D13*100/111 -> 5.2381982e+08 | F13: 350839388 | G13: 22-24 OKTOBER 2025 | H13: 52134694 | L13: 46484694 | U13: 24750000 | X13: =SUM(H13:W13) -> 123369388
B14: ITMF | C14: ITMF CONFERENCE 2025 | D14: 1105522788 | E14: =D14*100/111 -> 9.9596648e+08 | F14: =E14*80% -> 7.9677318e+08 | G14: 22-26 OKTOBER 2025 | H14: =30%*E14 -> 2.9878994e+08 | X14: =SUM(H14:W14) -> 2.9878994e+08
B15: RTL | C15: RTL MEETING | D15: 189560250 | E15: =D15*100/111 -> 170775000 | F15: =E15*80% -> 136620000 | G15: 23 OKTOBER 2025 | U15: =30%*E15 -> 51232500 | X15: =SUM(H15:W15) -> 51232500
B16: ROCHE | C16: ROCHE BOOTH MEDAN | D16: 85933980 | E16: =D16*100/111 -> 77418000 | F16: =E16*85% -> 65805300 | G16: 23-24 OKTOBER 2025 | L16: =30%*E16 -> 23225400 | X16: =SUM(H16:W16) -> 23225400
B17: BALI ES | C17: BALI ES TOUR YOGYAKARTA | D17: 53000000 | E17: =D17*100/101.2 -> 52371542 | F17: 41250000 | G17: 23-25 OKTOBER 2025 | L17: 19150000 | N17: 8950000 | U17: 3150000 | X17: =SUM(H17:W17) -> 31250000
B18: API | C18: ITMF GALA DINNER | D18: 1216214291 | E18: =D18*100/111 -> 1.0956886e+09 | F18: =E18*80% -> 8.7655084e+08 | G18: 24 OKTOBER 2025 | X18: =SUM(H18:W18) -> 0
B19: KROM BANK | C19: KROM BANK ANNUAL GATHERING | D19: 876140183 | E19: =D19*100/111 -> 7.8931548e+08 | F19: =E19*80% -> 6.3145238e+08 | G19: 24-25 OKTOBER 2025 | N19: =30%*E19 -> 2.3679464e+08 | X19: =SUM(H19:W19) -> 2.3679464e+08
B20: BANK INDONESIA KPW JATENG | C20: BI KPW JATENG MATRA LAUT | D20: 101189154 | E20: =D20*100/111 -> 91161400 | F20: =E20*80% -> 72929120 | G20: 24-25 OKTOBER 2025 | N20: =30%*E20 -> 27348420 | X20: =SUM(H20:W20) -> 27348420
B21: MRCCC SILOAM | C21: MRCCC HARDOKNAS 2025 | D21: 219541905 | E21: =D21*100/111 -> 197785500 | F21: 15665000 | G21: 25 OKTOBER 2025 | L21: 75725000 | N21: 19750000 | X21: =SUM(H21:W21) -> 95475000
X22: =SUM(H22:W22) -> 0
X23: =SUM(H23:W23) -> 0
X24: =SUM(H24:W24) -> 0
X25: =SUM(H25:W25) -> 0
X26: =SUM(H26:W26) -> 0
D27: TOTAL BIAYA SALES CALL | H27: =SUM(H10:H26) -> 8.9106224e+08 | I27: =SUM(I10:I26) -> 0 | J27: =SUM(J10:J26) -> 0 | K27: =SUM(K10:K26) -> 0 | L27: =SUM(L10:L26) -> 276735094 | M27: =SUM(M10:M26) -> 0 | N27: =SUM(N10:N26) -> 2.9284306e+08 | O27: =SUM(O10:O26) -> 0 | ... X27: =SUM(X10:X26) -> 1.5792729e+09
D30: BIAYA SURVEY SALES OPERATIONS
D36: TOTAL BIAYA SURVEY SALES OPERATIONS | H36: 0 | I36: 0
D39: BIAYA SALES OPERATING SUPPLIES
D40: Biaya kirim company profile ke Bali
D48: TOTAL BIAYA SALES OPERATING SUPPLIES | H48: 0 | I48: 0
C51: NO PO | D51: Event
C52: BANK INDONESIA DSDM-TEGAL | D52: EMPLOYEE GATHERING 2023 | E52: 135720000 | F52: =80%*E52 -> 108576000 | G52: 18 November 2023 | K52: =80%*F52 -> 86860800
C53: PREMIUMPASS INTERNATIONAL (5D4N SINGAPORE-BATAM-BINTAN) | D53: 5D4N SINGAPORE-BATAM-BINTAN | E53: 326072376 | F53: =80%*E53 -> 2.608579e+08 | G53: 19-23 November 2023 | K53: =80%*F53 -> 2.0868632e+08
C54: WORLD BANK (CCDR LAUNCH ) | D54: WB CCDR LAUNCH | E54: 117450000 | F54: =80%*E54 -> 93960000 | G54: 27 November 2023 | T54: =80%*F54 -> 75168000
C55: THE ASEAN COORDINATING CENTRE FOR HUMANITARIAN ASSISTANCE ON DISASTER MANAGEMENT (AHA CENTRE) | D55: ASEAN RETREAT | E55: 692533050 | F55: =80%*E55 -> 554026440 | G55: 3 - 8 Dec 23
C56: PERTAMINA EP | D56: RAKER EKSPLORASI 2023 | E56: 1131000000 | F56: =80%*E56 -> 904800000 | G56: 5 - 8 Dec 23
C57: SURYA MADISTRINDO AO JAKARTA JAKARTA SA2-3 TDN 4D3N BALI | D57: SM AO JAKARTA SA2-3 TDN 4D3N BALI | E57: 813960000 | F57: =80%*E57 -> 651168000 | G57: 6 - 9 Dec 23
C58: SEDAYA MULTI INVESTAMA - YEAR END GATHERING 2023 | D58: YEAR END GATHERING 2023 | E58: 778219002 | F58: =80%*E58 -> 6.225752e+08 | G58: 8 - 10 Dec 23
C59: SURYA MADISTRINDO RO JAWA TIMUR - RO JATIM SA1-2 TDN 4D3N BALI | D59: SM RO JATIM SA1-2 TDN 4D3N BALI | E59: 920550000 | F59: =80%*E59 -> 736440000 | G59: 14 - 17 Dec 23
C60: HCML (HUSKY-CNOOC MADURA LIMITED) - HCML SYNERGY 2023 | D60: HCML SYNERGY 2023 | E60: 147900000 | F60: =80%*E60 -> 118320000 | G60: 17 December 2023 | R60: =F60/3 -> 39440000
D63: TOTAL PENGELUARAN COST OF REVENUE PERIODE SEBELUMNYA | H63: =SUM(H52:H62) -> 0 | I63: =SUM(I52:I62) -> 0 | J63: =SUM(J52:J62) -> 0 | K63: =SUM(K52:K62) -> 2.9554712e+08 | L63: =SUM(L52:L62) -> 0 | M63: =SUM(M52:M62) -> 0 | N63: =SUM(N52:N62) -> 0 | O63: =SUM(O52:O62) -> 0 | ... X63: =SUM(X52:X62) -> 0
G66: TANGGAL | H66: 44711 | I66: 44712

Sheet OUT - CFC - Hutang Usaha
G1: Cash Outflow (Pengeluaran Kas) | H1: Hari Kerja
G2: Pembayaran Hutang Usah | H2: Jadwal Pembayaran (Selasa/ Jumat)
H3: Hari Libur
F4: Kategori : | G4: Cash Outflow (Pengeluaran Kas) | I4: Hari Kerja
F5: Pos Akun : | G5: OUT-CFC-HUTANG USAHA | I5: Jadwal Pembayaran (Selasa/ Jumat)
F6: Periode : | I6: Hari Libur
F7: Updated on : | G7: ='OUT - HR - Gaji & Benefit'!C4 -> 45947
H8: JUMAT | I8: SABTU | J8: MINGGU | K8: SENIN | L8: SELASA | M8: RABU | N8: KAMIS | O8: JUMAT | P8: SABTU | Q8: MINGGU | R8: SENIN | S8: SELASA | T8: RABU | U8: KAMIS | V8: JUMAT | W8: SABTU
B9: VENDOR | C9: KETERANGAN OUTSTANDING HUTANG USAHA | D9: NOMINAL | E9: DP | F9: TGL JATUH TEMPO | G9: TANGGAL | H9: 45947 | I9: 45948 | J9: 45949 | K9: 45950 | L9: 45951 | M9: 45952 | N9: 45953 | O9: 45954 | P9: 45955 | Q9: 45956 | R9: 45957 | S9: 45958 | T9: 45959 | U9: 45960 | V9: 45961 | W9: 45962 | X9: TOTAL
B10: PT VITAMIN DISKUSI SOLUSI - VINDES | C10: WNS; 2025; OCTOBER 2025; 063-01-TEP5-OCT-2025; WNS - ELITERY - COMPANY OUTING BOGOR TGL 22 - 24 OCT 25; BIAYA OOMLEO BERKARAOKE ELITERY COMPANY OUTING BOGOR 24 OCT 2025 ( 1 PCKG X Rp 45.918.367 ). TOTAL Rp 45.918.367 + PPN 12% Rp 5.051.020 = Rp 50.969.387 - PPH 23 Rp 918.367 = Rp 50.051.020. INV NO : VTMND/X/2025/217 DP 50% Rp 25.025.510 TGL 16 OCT 2025 PELUNASAN Rp 25.025.510 TGL 21 OCT 2025 TRF REK BCA 0710398658 an PT VITAMIN DISKUSI SOLUSI | D10: 25025510 | F10: 45951 | L10: =D10 -> 25025510 | X10: =SUM(H10:W10) -> 25025510
B11: ANUGRAH DEWATA | C11: 2025;OCTOBER 2025;OPS KANTOR;TEE - OPS KANTOR;BIAYA PEMB TELEPHONE KANTOR PABX PANASONIC 1 PCS DENGAN TOTAL Rp. 9.500.000;BIAYA PEMB PESAWAT TELP ANLOG KX TS500 4 PCS DENGAN TOTAL Rp. 1.200.000;BIAYA PEMB TELPON WALL SAHITEL S21 1 PCS DENGAN TOTAL 295.000;BIAYA PEMB KABEL TELPON ISI 4 SEPANJANG 120 M DENGAN TOTAL Rp. 720.000;BIAYA PEMB INSTALASI KABEL SETTING UNTUK 6 TITIK DENGAN TOTAL Rp. 900.000;BIAYA PEMB MATERIAL SUPPORT KLEM KABEL DUCK PENUTUP KABEL DAN ROSLET UNTUK 1 LS DENGAN TOTAL Rp. 400.000;GRAND TOTAL Rp. 13.015.000 NO INVOICE : AD/BALI/X/ 2025 DP 1 50% : Rp. 6.507.500 TGL 16 OKT 2025 PELUNASAN : Rp. 6.507.500 AFTER INSTALASI/21 OKT 2025 PAYMENT TF BNI 3555355950 an WERKUDARA NIRWANA SAKTI | D11: 6507500 | F11: 45951 | L11: =D11 -> 6507500 | X11: =SUM(H11:W11) -> 6507500
B12: ENIGMA INTERTAMA | C12: WNS; 2025; OCTOBER 2025; 054-01-TEP3-SEP-2025; WNS - ILO INDONESIA - OFFICIAL VISIT OF FEDERAL COUNCILLOR OF SWITZERLAND TO KPBS PANGALENG TGL 2 OCT 25; BIAYA EVENT SUPPORTING PRODUCTION DAN MANPOWER FOR EVENT ILO TGL 2 OCT 2025 ( 1 PCKG X Rp 78.819.520 ). TOTAL Rp 78.819.520 - PPH 21 Rp 1.970.488 = Rp 76.849.032. INV NO : 03/ENIGMA-WG/X/25 PELUNASAN Rp 76.849.032 TGL 16 OCT 2025 TRF REK BCA 7560142034 an ALFI YANSYAH | D12: 38424516 | F12: 45951 | L12: =D12 -> 38424516 | X12: =SUM(H12:W12) -> 38424516
B13: PRIME STAR MICE SERVICE | C13: WNS; 2025; SEPTEMBER 2025; 051-01-TEP3-SEP-2025; WNS - UN WOMEN INDONESIA - 25TH ANNIVERSARY OF UNSCR 1325 CELEBRATION JAKARTA TGL 17 - 18 SEP 25; BIAYA PRODUCTION UN WOMEN TGL 17-18 SEP 2025 ( 1 PCKG X Rp 126.030.000 ). TOTAL Rp 126.030.000 - PPH 23 Rp 2.520.600 = Rp 123.509.400. INV NO : PELUNASAN Rp 123.509.400 TGL 21 OKTOBER 2025 TRF REK BCA 6975808061 an PANCA INDERA KREATIF INDONESIA | D13: 30877350 | F13: 45951 | L13: =D13 -> 30877350 | X13: =SUM(H13:W13) -> 30877350
B14: LUMICOS | C14: WNS; 2025; SEPTEMBER 2025; 051-01-TEP3-SEP-2025; WNS - UN WOMEN INDONESIA - 25TH ANNIVERSARY OF UNSCR 1325 CELEBRATION JAKARTA TGL 17 - 18 SEP 25; BIAYA DOKUMENTASI TGL 17-18 SEP 2025 ( 1 PCKG X Rp 10.500.000 ). TOTAL Rp 10.500.000 - PPH 23 Rp 210.000 = Rp 10.290.000. INV NO : #2607 PELUNASAN Rp 10.290.000 TGL 16 OCT 2025 TRF REK BCA 8610674900 an BHAGAWANTA PUTRA SAKTI | D14: 10290000 | F14: 45951 | L14: =D14 -> 10290000 | X14: =SUM(H14:W14) -> 10290000
B15: BALAWAN BATUAN ETHNIC FUSION | C15: TEE; 2025; OCTOBER 2025; 006-01-TEE-OCT-2025; TEE - RINTIS SEJAHTERA (PRIMA) - EXECUTIVE GATHERING 2025 BALI TGL 22 - 24 OCT 25; BIAYA PEMB BALAWAN TRIO (GUITAR, VOCAL, KEYBOARD) PERFOMANCE TGL 23 OKTOBER 2025 DI HOTEL MULIA BALI. TOTAL 20.000.000 NO INV : BEF014/010/2025 DP 1 50% : 10.000.000 TGL 14 OKT 2025 PELUNASAN : 10.000.000 TGL 21 OKT 2025 PAYMENT TF MANDIRI 1450007961432 A.N I WAYAN BALAWAN | D15: 10000000 | F15: 45951 | L15: =D15 -> 10000000 | X15: =SUM(H15:W15) -> 10000000
B16: GUIDE GUNG PUTRI | C16: 2025;OCTOBER 2025;TEP;KEMENPAREKRAF - MEGA FAM TRIP 14 - 17 OKT 2025; BIAYA PEMB GUIDE FEE TGL 14-17 JUMLAH 4 PAX DENGAN TOTAL Rp. 2.800.000;BIAYA PEMB MEALS TGL 14-17 JUMLAH 4 PAX DENGAN TOTAL Rp. 300.000; BIAYA PEM TIPPING TGL 14-17 JUMLAH 4 PAX DENGAN TOTAL Rp. 600.000;BIAYA PEMB PENGINAPAN TGL 16-17 DENGAN TOTAL Rp. 300.000; SUB TOTAL Rp. 4.000.000 NO INV : INV/00113 PELUNASAN : Rp. 4.000.000 TGL 16 OKT 2025 SBLM JAM 12.00 PAYMENT TF KE BCA 7680190849 an ANAK AGUNG GEK PUTRI ANTARI | D16: 2000000 | F16: 45951 | L16: =D16 -> 2000000 | X16: =SUM(H16:W16) -> 2000000
B17: MANPOWER | C17: TKS; 2025; SEPTEMBER 2025; 005-04-TKS-SEP-2025; TKS - ASURANSI BRI LIFE - BOOTH SAMANSA RUN MAKASSAR TGL 20 - 21 SEP 25; BIAYA MANPOWER SUPPORT REMOTE BRI LIFE TGL 20-21 SEP 2025 AN REFANGGA ( 1 PCKG X Rp 300.000 ). TOTAL Rp 300.000. INV NO : PELUNASAN Rp 300.000 TGL 2 OCT 2025 TRF REFANGGA | D17: 300000 | F17: 45951 | L17: =D17 -> 300000 | X17: =SUM(H17:W17) -> 300000
B18: MANPOWER | C18: TKS; 2025; SEPTEMBER 2025; 005-04-TKS-SEP-2025; TKS - ASURANSI BRI LIFE - BOOTH SAMANSA RUN MAKASSAR TGL 20 - 21 SEP 25; BIAYA MANPOWER SUPPORT REMOTE BRI LIFE TGL 20-21 SEP 2025 AN VIANA ( 1 PCKG X Rp 350.000 ). TOTAL Rp 350.000. INV NO : PELUNASAN Rp 350.000 TGL 2 OCT 2025 TRF VIANA | D18: 350000 | F18: 45951 | L18: =D18 -> 350000 | X18: =SUM(H18:W18) -> 350000
B19: PARKIR TOL BBM | C19: WNS - GA - BIAYA PEMB BBM INOVA DAN PARKIR UNTUK TABLE TOP HARRIS CIUMBULEUIT BANDUNG. TTL 105.000 REIMBURSE ANWAR | D19: 105000 | F19: 45951 | L19: =D19 -> 105000 | X19: =SUM(H19:W19) -> 105000
B20: KASBON PURWATI | C20: KASBON EVENT KROM BANK ANNUAL GATHERING 2025 | D20: 12450000 | F20: 45951 | L20: =D20 -> 12450000 | X20: =SUM(H20:W20) -> 12450000
B21: NUSAIBA SOUVENIR | C21: WNS; 2025; OCTOBER 2025; 033-01-TEP2-JUL-2025; WNS - ITMF - ANNUAL CONFERENCE & IAF WORLD FASHION CONVENTION YOGYAKRATA TGL 24 - 25 OCT 25; BIAYA TROPHY RESIN BOX BLUDRU 2 PCS ( 1 PCKG X Rp 1.150.000 ). TOTAL Rp 1.150.000. INV NO : DP 50% Rp 575.000 TGL 16 OCT 2025 PELUNASAN Rp 575.000 TGL 21 OCT 2025 TRF REK BRI 040901037462502 an ANNISA KUSUMASTUTY | D21: 575000 | F21: 45951 | L21: =D21 -> 575000 | X21: =SUM(H21:W21) -> 575000
... B48: EVENT | C48: ELITERY | D48: 45684000 | F48: 45951 | L48: =D48 -> 45684000 | X48: =SUM(H48:W48) -> 45684000
B49: EVENT | C49: KASBON ELITERY | D49: 8650000 | F49: 45951 | K49: =D49 -> 8650000 | X49: =SUM(H49:W49) -> 8650000
B50: EVENT | C50: BJS | D50: 25000000 | F50: 45951 | L50: =D50 -> 25000000 | X50: =SUM(H50:W50) -> 25000000
B51: EVENT | C51: BI JATENG | D51: 13000000 | F51: 45951 | L51: =D51 -> 13000000 | X51: =SUM(H51:W51) -> 13000000
B52: EVENT | C52: ITMF CONFERENCE | D52: 9000000 | F52: 45951 | L52: =D52 -> 9000000 | X52: =SUM(H52:W52) -> 9000000
B53: EVENT | C53: KASBON ITMF PART 2 | D53: 15000000 | F53: 45951 | L53: =D53 -> 15000000 | X53: =SUM(H53:W53) -> 15000000
B54: EVENT | C54: KASBON ITMF DINNER | D54: 11100000 | F54: 45951 | L54: =D54 -> 11100000 | X54: =SUM(H54:W54) -> 11100000
B55: EVENT | C55: GIZ JAKARTA | D55: 37000000 | F55: 45951 | L55: =D55 -> 37000000 | X55: =SUM(H55:W55) -> 37000000
B56: EVENT | C56: ITMF DINNER | D56: 48000000 | F56: 45951 | L56: =D56 -> 48000000 | X56: =SUM(H56:W56) -> 48000000
B57: EVENT | C57: KASBON BALI ESTOUR | D57: 12600000 | F57: 45951 | L57: =D57 -> 12600000 | X57: =SUM(H57:W57) -> 12600000
B58: EVENT | C58: BALI ES TOUR | D58: 6550000 | F58: 45951 | L58: =D58 -> 6550000 | X58: =SUM(H58:W58) -> 6550000
B59: EVENT | C59: SAFETY DEPOSIT GIZ | D59: 10000000 | F59: 45950 | K59: =D59 -> 10000000 | X59: =SUM(H59:W59) -> 10000000
B60: EVENT | C60: SAFETY DEPOSIT ELITERY | D60: 10000000 | F60: 45951 | L60: 10000000 | X60: =SUM(H60:W60) -> 10000000
B61: EVENT | C61: PRIMA TEE | D61: =75000000+50000000 -> 125000000 | F61: 45951 | L61: =D61 -> 125000000 | X61: =SUM(H61:W61) -> 125000000
B62: MC IKLIMA HARUM | C62: WNS; 2025; OCTOBER 2025; 059-02-TEP5-SEP-2025; WNS - KROM BANK - ANNUAL GATHERING BOGOR TGL 24 -25 OCT 25; BIAYA MC GALA DINNER KROM BANK TGL 24 OCT 2025 ( 1 PCKG X Rp 5.600.000 ). TOTAL Rp 5.600.000 - PPH 21 Rp 140.000 = Rp 5.460.000. INV NO : DP 1 Rp 2.000.000 TGL 16 OCT 2025 PELUNASAN Rp 3.460.000 TGL 23 OCT 2025 TRF REK BCA 1370138806 an IKLIMA NUR RAYHAN | D62: 3460000 | F62: 45953 | N62: =D62 -> 3460000 | X62: =SUM(H62:W62) -> 3460000
B63: KASBON SHEILIA | C63: PENGAJUAN KASBON PAJAK VARIO AB 4432 IQ | D63: 281500 | F63: 45953 | N63: =D63 -> 281500 | X63: =SUM(H63:W63) -> 281500
B64: MUSIK INDAH ENTERTAIMENT | C64: WNS; 2025; OCTOBER 2025; 063-01-TEP5-OCT-2025; WNS - ELITERY - COMPANY OUTING BOGOR TGL 22 - 24 OCT 25; BIAYA MC GALA DINNER ELITERY OUTING 24 OCT 2025 ( 1 PCKG X Rp 3.080.000 ). TOTAL Rp 3.080.000 - PPH 21 Rp 77.000 = Rp 3.003.000. INV NO : DP 50% Rp 1.500.000 TGL 16 OCT 2025 PELUNASAN Rp 1.503.000 TGL 23 OCT 2025 TRF REK BCA 3981424989 an INDAH PERMATA | D64: 1500000 | F64: 45953 | N64: =D64 -> 1500000 | X64: =SUM(H64:W64) -> 1500000
B65: EXTRAVAGONGZO | C65: WNS; 2025; OCTOBER 2025; 022-01-TEP2-MAY-2025; WNS - APR - GALA DINNER ITMF IAF 2025 YOGYAKARTA TGL 24 OCT 25; BIAYA KOSTUM JAWA 50 PCS ( 1 PCKG X Rp 5.130.000 ) COKEKAN 4 PEMUSIK TGL 24 OCT 2025 ( 1 PCKG X Rp 5.130.000 ). TOTAL Rp 10.260.000 - PPH 21 Rp 256.500 = Rp 10.003.500. INV NO : DP 50% Rp 5.000.000 TGL 16 OCT 2025 PELUNASAN Rp 5.003.500 TGL 23 OCT 2025 TRF REK BPD DIY 006221035989 an FAJAR AGUNG PAMBUDI | D65: 5000000 | F65: 45953 | N65: =D65 -> 5000000 | X65: =SUM(H65:W65) -> 5000000
B66: MC ALLYSA NATALIE | C66: WNS; 2025; OCTOBER 2025; 046-01-TEP3-AUG-2025; WNS - GIZ INDONESIA - IKI INTERFACE WORKSHOP JAKARTA TGL 21 OCT 25; BIAYA BILLINGUAL MC FULLDAY TGL 15 OCT 2025 ( 1 PCKG X Rp 12.000.000 ). TOTAL Rp 12.000.000 - PPH 21 Rp 300.000 = Rp 11.700.000. INV NO : GILANG DP 50% Rp 5.850.000 TGL 16 OCT 2025 PELUNASAN Rp 5.850.000 TGL 23 OCT 2025 TRF REK BCA 0650924045 an ALLYSA NATALIE HARTONO No NPWP : 60.649.642.0-043.000 an ALLYSA NATALIE HARTONO No KTP : 3172065612010001 an ALLYSA NATALIE HARTONO | D66: 5850000 | F66: 45953 | N66: =D66 -> 5850000 | X66: =SUM(H66:W66) -> 5850000
B67: PMJ PAKET | C67: WNW; 2025; OCTOBER 2025; 008-WNW-03-TEP6-SEP-2025; WNW - PTC - RETAIL MERCHANDISE PRODUCTION JAKARTA TGL 5 OCT 25; BIAYA KIRIM PAKET 2 KOLI ( 1 PCKG X Rp 550.000 ). TOTAL Rp 550.000. INV NO : 0676 PELUNASAN Rp 550.000 TGL 9 OCT 2025 TRF REK BCA 0600689665 an TEGUH SUNARYO | D67: 550000 | F67: 45953 | N67: =D67 -> 550000 | X67: =SUM(H67:W67) -> 550000
B68: PT TEKUN LANCAR SEJAHTERA | C68: WNS - GA - BIAYA PEMB FLOOR CHEMICAL, KARBOL CLEANER, SUNLIGHT, GAS PINK 5KG 1, GAS 3 KG 2, TTL 2.981.000 NO INV : 1166, 1154, 1158, 1160, 1161, 1162, 1163 PELUNASAN 18 SEPT 25 | D68: 2981000 | F68: 45953 | N68: =D68 -> 2981000 | X68: =SUM(H68:W68) -> 2981000
B69: PT TEKUN LANCAR SEJAHTERA | C69: WNS - GA - BIAYA PEMB PAKET HADIA JUARA 1,2,3 UNTUK KEGIATAN KEMERDEKAAN TOTAL 7 BOX, BIAYA PEMB GULA PASIR 2 PACK DAN TEH POCI UNTUK KEGIATAN KEMERDEKAAN 27 AGUST 25. TTL 889.500 NO INV : 1167 DAN 1168 PELUNASAN 25 SEPT 25 | D69: 889500 | F69: 45953 | N69: =D69 -> 889500 | X69: =SUM(H69:W69) -> 889500
B70: LUMICOS | C70: WNS; 2025; AUGUST 2025; 036-01-TEP5-JUL-2025; WNS - YASULOR INDONESIA - L'OREAL SAPMENA HR UPSTREAM OFFSITE MEETING YOGYAKARTA TGL 19 - 22 AUG 25; BIAYA DOKUMENTASI YASULOR TGL 19-22 AUG 2025 ( 1 PCKG X Rp 15.750.000 ). TOTAL Rp 15.750.000 - PPH 23 Rp 315.000 = Rp 15.435.000. INV NO : #2601 PELUNASAN Rp 15.435.000 TGL 23 SEP 2025 TRF REK BCA 8610674900 an CV BHAGAWANTA PUTRA SAKTI | D70: 15435000 | F70: 45953 | N70: =D70 -> 15435000 | X70: =SUM(H70:W70) -> 15435000
B71: ALAM SARI SEMBAKO | C71: TEE - GA - BIAYA PEMB AQUA 330 ML 2 DUZ UNTUK TAKSHAKA BALI. TTL 86.000 PAYMENT TF KE BANK BCA 8270271554 A.N NI PUTU DEWI ALAM SARI PELUNASAN 23 OKT 2025 | D71: 86000 | F71: 45953 | N71: =D71 -> 86000 | X71: =SUM(H71:W71) -> 86000
B72: EVENT | C72: MRSCC | D72: 20750000 | F72: 45953 | N72: =D72 -> 20750000 | X72: =SUM(H72:W72) -> 20750000
B73: EVENT | C73: GIZ JAKARTA | D73: 37500000 | F73: 45953 | N73: =D73 -> 37500000 | X73: =SUM(H73:W73) -> 37500000
... B77: EVENT | C77: PRIMA TEE | D77: 10750000 | F77: 45953 | N77: =D77 -> 10750000 | X77: =SUM(H77:W77) -> 10750000
B78: PRIME STAR MICE SERVICE | C78: WNS; 2025; SEPTEMBER 2025; 051-01-TEP3-SEP-2025; WNS - UN WOMEN INDONESIA - 25TH ANNIVERSARY OF UNSCR 1325 CELEBRATION JAKARTA TGL 17 - 18 SEP 25; BIAYA PRODUCTION UN WOMEN TGL 17-18 SEP 2025 ( 1 PCKG X Rp 126.030.000 ). TOTAL Rp 126.030.000 - PPH 23 Rp 2.520.600 = Rp 123.509.400. INV NO : PELUNASAN Rp 123.509.400 TGL 21 OKTOBER 2025 TRF REK BCA 6975808061 an PANCA INDERA KREATIF INDONESIA | D78: 30877350 | F78: 45958 | S78: =D78 -> 30877350 | X78: =SUM(H78:W78) -> 30877350
B79: A-PRO FREELANCE AGENT | C79: WNS; 2025; OCTOBER 2025; 038-01-TEP5-AUG-2025; WNS - IFF - GALA DINNER 2025 YOGYAKARTA TGL 10 OCT 25; BIAYA SHOW MANAGEMENT DAN LO DONNY SIBARANI TGL 10 OCT 2025 ( 1 PCKG X Rp 9.750.000 ). TOTAL Rp 9.750.000 - PPH 21 Rp 243.750 = Rp 9.506.250. INV NO : 02 PELUNASAN Rp 9.506.250 TGL 28 OCT 2025 TRF REK MANDIRI 1180014442544 an SCOLASTICA RIANDINI | D79: 9506250 | F79: 45958 | S79: =D79 -> 9506250 | X79: =SUM(H79:W79) -> 9506250
B80: PT TEKUN LANCAR SEJAHTERA | C80: WNS - GA - BIAYA PEMB GAS 3KG, MINYAK GR, SAOS SAMBAL , BIAYA PEMB PLASTIK 100X120, BIAYA PEMB REFILE DIFUSER, SUNLIGHT, SPON CUCI, NIVEA MEN, PONDS . TTL 782.500 NO INV : 1171, 1173, 1172 PELUNASAN 2 OKT 2025 | D80: 782500 | F80: 45958 | S80: =D80 -> 782500 | X80: =SUM(H80:W80) -> 782500
B81: PT TEKUN LANCAR SEJAHTERA | C81: WNS - GA - BIAYA PEMB ISI STRAPLES NO 10, BOLPIN GEL DAN KERTAS HVS A4 . TTL 1.210.000 NO INV : 1170 PELUNASAN 2 OKT 2025 | D81: 1210000 | F81: 45958 | S81: =D81 -> 1210000 | X81: =SUM(H81:W81) -> 1210000
B82: PT TEKUN LANCAR SEJAHTERA | C82: MRP - GA - BIAYA PEMB KERTAS LOCAL CHIP 450 LEMBAR @325. TTL 146.250 NO INV : 1169 PELUNASAN 2 OKT 2025 | D82: 146250 | F82: 45958 | S82: =D82 -> 146250 | X82: =SUM(H82:W82) -> 146250
B83: HT MILIK KITA | C83: WNS; 2025; OCTOBER 2025; 048-02-TEP5-SEP-2025; WNS - KREDIVO GROUP - GAJIGESA OUTING BOGOR TGL 26 - 27 SEP 25; BIAYA HT COMETECK UV82 ( 5 UNIT X 4 DAYS X Rp 13.000). TOTAL Rp 260.000. INV NO : 8951/IX/2025 PELUNASAN Rp 260.000 TGL 28 OCT 2025 TRF REK : BCA 0374338524 an SATRIYO WICAKSONO | D83: 260000 | F83: 45958 | S83: =D83 -> 260000 | X83: =SUM(H83:W83) -> 260000
B84: KASBON WG 002 | C84: PENGAJUAN KASBON TA WTM DI LONDON TGL 31 OCT - 12 NOV 2025 | D84: 26995000 | F84: 45958 | S84: =D84 -> 26995000 | X84: =SUM(H84:W84) -> 26995000
B85: KAS BON GILANG | C85: PENGAJUAN KASBON EVENT IJK 3-4 NOV 2025 | D85: 24800000 | F85: 45958 | S85: =D85 -> 24800000 | X85: =SUM(H85:W85) -> 24800000
B86: LUMICOS | C86: WNS; 2025; OCTOBER 2025; 034-01-TEP2-JUL-2025; WNS - DISPERINDAG DIY - JIBB YOGYAKARTA TGL 15 SEP - 5 OCT 25; BIAYA DOKUMENTASI TGL 16-18 & 22-26 SEP 2025 ( 1 PCKG X Rp 12.000.000 ). TOTAL Rp 12.000.000 - PPH 23 Rp 240.000 = Rp 11.760.000. INV NO : #2608 PELUNASAN Rp 11.760.000 TGL 28 OCT 2025 TRF REK BCA 8610674900 an BHAGAWANTA PUTRA SAKTI | D86: 11760000 | F86: 45958 | S86: =D86 -> 11760000 | X86: =SUM(H86:W86) -> 11760000
B87: PARAAKAR | C87: WNS; 2025; NOVEMBER 2025; 057-01-TEP4-SEP-2025; WNS - OJK DPBS - INTERNATIONAL ISLAMIC FINANCE CONFERENCE SURABAYA TGL 3 - 4 NOV 25; BIAYA PEMBUATAN CANVAS TOTE BAG CETAK DTF 500 PCS ( 500 PCS X Rp 75.000 ) CANVAS TOTE BAG BORDIR 300 PCS ( 300 PCS X Rp 175.000 ). TOTAL Rp 90.000.000. INV NO : IX/PAIWEO/07109/2025 DP 50% Rp 45.000.000 TGL 9 OCT 2025 PELUNASAN Rp 45.000.000 TGL 28 OCT 2025 TRF REK BCA 4451046467 an DONY PERMANA | D87: 45000000 | F87: 45958 | S87: =D87 -> 45000000 | X87: =SUM(H87:W87) -> 45000000
B88: EVENT | C88: KROM BANK | D88: 33000000 | F88: 45958 | S88: =D88 -> 33000000 | X88: =SUM(H88:W88) -> 33000000
B89: EVENT | C89: OJK | D89: 85000000 | F89: 45958 | S89: =D89 -> 85000000 | X89: =SUM(H89:W89) -> 85000000
B90: PRIME STAR MICE SERVICE | C90: WNS; 2025; SEPTEMBER 2025; 051-01-TEP3-SEP-2025; WNS - UN WOMEN INDONESIA - 25TH ANNIVERSARY OF UNSCR 1325 CELEBRATION JAKARTA TGL 17 - 18 SEP 25; BIAYA PRODUCTION UN WOMEN TGL 17-18 SEP 2025 ( 1 PCKG X Rp 126.030.000 ). TOTAL Rp 126.030.000 - PPH 23 Rp 2.520.600 = Rp 123.509.400. INV NO : PELUNASAN Rp 123.509.400 TGL 21 OKTOBER 2025 TRF REK BCA 6975808061 an PANCA INDERA KREATIF INDONESIA | D90: 30877350 | F90: 45960 | U90: =D90 -> 30877350 | X90: =SUM(H90:W90) -> 30877350
B91: MECA DIGITAL PRINTING | C91: WNS; 2025; OCTOBER 2025; 033-01-TEP2-JUL-2025; WNS - ITMF - ANNUAL CONFERENCE & IAF WORLD FASHION CONVENTION YOGYAKRATA TGL 24 - 25 OCT 25; BIAYA LANYARD FULL COLOR 360 PCS ( 1 PCKG X Rp 4.248.000 ) PVC B3 360 PCS ( 1 PCKG X Rp 6.264.000 ). TOTAL Rp 10.512.000. INV NO : MC1348 & MC1352 DP 30% Rp 3.153.600 TGL 16 OCT 2025 PELUNASAN Rp 7.358.400 TGL 30 OCT 2025 TRF REK BCA 8465612122 an KAISYA SAPUTRI | D91: 3153600 | F91: 45960 | U91: =D91 -> 3153600 | X91: =SUM(H91:W91) -> 3153600
B92: PT TEKUN LANCAR SEJAHTERA | C92: WNS - GA - BIAYA PEMB KERTAS FLIP CHART 10, BUKU GELATIK FOLIO 2, TINTA EPSON L15150 2. TTL 800.000 NO INV : 1174 PELUNASAN 14 OKT 2025 | D92: 800000 | F92: 45960 | U92: =D92 -> 800000 | X92: =SUM(H92:W92) -> 800000
B93: PT TEKUN LANCAR SEJAHTERA | C93: WNS; 2025; OCTOBER 2025; 034-01-TEP2-JUL-2025; WNS - DISPERINDAG DIY - JIBB YOGYAKARTA TGL 15 SEP - 5 OCT 25; BIAYA VIT 330 ML 12 BOX ( 1 PCKG X Rp 456.000 ). TOTAL Rp 456.000. INV NO : 1175 PELUNASAN Rp 456.000 TGL 14 OCT 2025 TRF REK MANDIRI 137 001 838 9292 an PT TEKUN LANCAR SEJAHTERA | D93: 456000 | F93: 45960 | U93: =D93 -> 456000 | X93: =SUM(H93:W93) -> 456000
B94: PT TEKUN LANCAR SEJAHTERA | C94: WNS - GA - BIAYA PEMB LAURIER 30 CM, LAURIER DAUN SIRIH DAN KANEBO, GAS 3 KG, MINYAK GORENG 2LT, PLASTIK WRAP, FLOOR CLEANER DAN KARBOL. TTL 419.500 NO INV : 1179, 1180 PELUNASAN 14 OKT 2025 | D94: 419500 | F94: 45960 | U94: =D94 -> 419500 | X94: =SUM(H94:W94) -> 419500
B95: PT TEKUN LANCAR SEJAHTERA | C95: WNS; 2025; OCTOBER 2025; 034-01-TEP2-JUL-2025; WNS - DISPERINDAG DIY - JIBB YOGYAKARTA TGL 15 SEP - 5 OCT 25; BIAYA VIT 330ML 15 BOX ( 15 BOX X Rp 38.000 ). TOTAL Rp 570.000. INV NO : 1176 PELUNASAN Rp 570.000 TGL 21 OCT 2025 TRF REK MANDIRI 137 001 838 9292 an PT TEKUN LANCAR SEJAHTERA | D95: 570000 | F95: 45960 | U95: =D95 -> 570000 | X95: =SUM(H95:W95) -> 570000
B96: PREMIERE TRANSPORT | C96: WNS BALI; 2025; OCTOBER 2025; 003-02-TEP1-BALI-AUG-2025; WNS BALI - BALI ES TOUR - 3D2N CULTURAL ESCAPE YOGYAKARTA TGL 27 - 29 SEP 25; BIAYA MEDIUM BUS 1 UNIT TGL 27-29 SEP 2025 ( 1 PCKG X Rp 6.400.000 ). TOTAL Rp 6.400.000 - PPH 23 Rp 128.000 = Rp 6.272.000. INV NO : PELUNASAN Rp 6.272.000 TGL 30 OCT 2025 TRF REK BCA 4451936829 an FELIX IVAN PRADIPTA NPWP : 94.274.291.7-524.000 an CV PREMIERE TRANSPORT INDONESIA | D96: 6272000 | F96: 45960 | U96: =D96 -> 6272000 | X96: =SUM(H96:W96) -> 6272000
B97: TAMAPICTURE PHOTO & VIDEO CREATOR | C97: WNW; 2025; OCTOBER 2025; 006-WNW-01-TEP3-SEP-2025; WNW - ADPMET - SOSIALISASI HASIL MUNAS V DAN RAPAT KERJA 2025 CEPU TGL 16 OCT 25; BIAYA DOKUMENTASI TGL 16 OKT 2025 ( 1 PCKG X Rp 4.625.000 ). TOTAL Rp 4.625.000 - PPH 21 Rp 115.625 = Rp 4.509.375. INV NO : DP 50% Rp 2.254.687 TGL 9 OCT 2025 PELUNASAN Rp 2.254.687 TGL 30 OCT 2025 TRF REK BCA 3850255651 an Deby Anggara Pratama NIK : 3573011310920001 DEBY ANGGARA PRATAMA | D97: 2254687 | F97: 45960 | U97: =D97 -> 2254687 | X97: =SUM(H97:W97) -> 2254687
B98: CV ARIANDRA MEDIA ARDHANA | C98: WNS; 2025; OCTOBER 2025; 034-01-TEP2-JUL-2025; WNS - DISPERINDAG DIY - JIBB YOGYAKARTA TGL 15 SEP - 5 OCT 25; BIAYA EVENT PRODUCTION DISPERINDAG JIBB TGL 2-5 OKT 2025 ( 1 PCKG X Rp 80.000.000 ). TOTAL Rp 80.000.000 + PPN 11% Rp 8.800.000 = Rp 88.800.000 - PPH 23 Rp 1.600.000 = Rp 87.200.000. INV NO : PELUNASAN Rp 87.200.000 TGL 6 NOV 2025 TRF REK MANDIRI 1370013972043 A.N CV ARIANDRA MEDIA ARDHANA | D98: 43600000 | F98: 45960 | U98: =D98 -> 43600000 | X98: =SUM(H98:W98) -> 43600000
B99: EVENT | C99: ELITERY | D99: 24750000 | F99: 45960 | U99: =D99 -> 24750000 | X99: =SUM(H99:W99) -> 24750000
B100: EVENT | C100: KROM | D100: 29000000 | F100: 45960 | U100: =D100 -> 29000000 | X100: =SUM(H100:W100) -> 29000000
B101: EVENT | C101: ADPMET | D101: 64500000 | F101: 45960 | U101: =D101 -> 64500000 | X101: =SUM(H101:W101) -> 64500000
B102: EVENT | C102: PRIMA TEE | D102: 51050000 | F102: 45960 | U102: =D102 -> 51050000 | X102: =SUM(H102:W102) -> 51050000
C103: TOTAL | D103: =SUM(D10:D102) -> 1763734063 | H103: =SUM(H10:H102) -> 0 | I103: =SUM(I10:I102) -> 0 | J103: =SUM(J10:J102) -> 0 | K103: =SUM(K10:K102) -> 18650000 | L103: =SUM(L10:L102) -> 1014560576 | M103: =SUM(M10:M102) -> 0 | N103: =SUM(N10:N102) -> 203483000 | O103: =SUM(O10:O102) -> 0 | ... X103: =SUM(X10:X102) -> 1763734063

Sheet OUT - HR - Pemberian Pinjaman
B1: Kategori : | C1: Cash Outflow (Pengeluaran Kas) | F1: Hari Kerja
B2: Pos Akun : | C2: Out-HR-Pemberian Pinjaman | F2: Jadwal Pembayaran (Selasa/ Jumat)
B3: Periode : | F3: Hari Libur
B4: Updated on : | C4: ='OUT - TEP - Cost Of Revenue'!E4 -> 0 | E4: Pengeluaran Biaya Operating Sales & Marketing | F4: Pengeluaran Biaya Operating Sales & Marketing
D5: JUMAT | E5: SABTU | F5: MINGGU | G5: SENIN | H5: SELASA | I5: RABU | J5: KAMIS | K5: JUMAT | L5: SABTU | M5: MINGGU | N5: SENIN | O5: SELASA | P5: RABU | Q5: KAMIS | R5: JUMAT | S5: SABTU
A6: DESKRIPSI | B6: NOMINAL | C6: TANGGAL | D6: 45947 | E6: 45948 | F6: 45949 | G6: 45950 | H6: 45951 | I6: 45952 | J6: 45953 | K6: 45954 | L6: 45955 | M6: 45956 | N6: 45957 | O6: 45958 | P6: 45959 | Q6: 45960 | R6: 45961 | S6: 45962 | T6: TOTAL
T7: =SUM(D7:S7) -> 0
T8: =SUM(D8:S8) -> 0
T9: =SUM(D9:S9) -> 0
T10: =SUM(D10:S10) -> 0
T11: =SUM(D11:S11) -> 0
B12: TOTAL | D12: =SUM(D7:D11) -> 0 | E12: =SUM(E7:E11) -> 0 | F12: =SUM(F7:F11) -> 0 | G12: =SUM(G7:G11) -> 0 | H12: =SUM(H7:H11) -> 0 | I12: =SUM(I7:I11) -> 0 | J12: =SUM(J7:J11) -> 0 | K12: =SUM(K7:K11) -> 0 | ... T12: =SUM(T7:T11) -> 0

Sheet OUT - TEP - Sales Call
B1: Kategori : | C1: Cash Outflow (Pengeluaran Kas) | F1: Hari Kerja
B2: Pos Akun : | C2: Out-TEP-Sales Call | F2: Jadwal Pembayaran (Selasa/ Jumat)
B3: Periode : | F3: Hari Libur
B4: Updated on : | C4: ='IN-CFC-Penerimaan PengemPinj'!C4 -> 45947 | D4: Pengeluaran Biaya Operating Sales & Marketing | E4: Pengeluaran Biaya Operating Sales & Marketing
D5: JUMAT | E5: SABTU | F5: MINGGU | G5: SENIN | H5: SELASA | I5: RABU | J5: KAMIS | K5: JUMAT | L5: SABTU | M5: MINGGU | N5: SENIN | O5: SELASA | P5: RABU | Q5: KAMIS | R5: JUMAT | S5: SABTU
A6: DESKRIPSI | B6: NOMINAL | C6: TANGGAL | D6: 45947 | E6: 45948 | F6: 45949 | G6: 45950 | H6: 45951 | I6: 45952 | J6: 45953 | K6: 45954 | L6: 45955 | M6: 45956 | N6: 45957 | O6: 45958 | P6: 45959 | Q6: 45960 | R6: 45961 | S6: 45962 | T6: TOTAL
T7: =SUM(D7:S7) -> 0
T8: =SUM(D8:S8) -> 0
T9: =SUM(D9:S9) -> 0
T10: =SUM(D10:S10) -> 0
T11: =SUM(D11:S11) -> 0
B12: TOTAL | D12: =SUM(D7:D11) -> 0 | E12: =SUM(E7:E11) -> 0 | F12: =SUM(F7:F11) -> 0 | G12: =SUM(G7:G11) -> 0 | H12: =SUM(H7:H11) -> 0 | I12: =SUM(I7:I11) -> 0 | J12: =SUM(J7:J11) -> 0 | K12: =SUM(K7:K11) -> 0 | ... T12: =SUM(T7:T11) -> 0

Sheet OUT-CFC -Pengem Sunti Modal Own
B1: Kategori : | C1: Cash Outflow (Pengeluaran Kas) | E1: Hari Kerja
B2: Pos Akun : | C2: Out-CFC-Pengembalian Suntikan Modal | E2: Jadwal Pembayaran (Selasa/ Jumat)
B3: Periode : | E3: Hari Libur
B4: Updated on : | C4: ='IN-Pengem Pinj Pokok'!C4 -> 45947 | E4: Pengeluaran Biaya Operating Sales & Marketing
D5: JUMAT | E5: SABTU | F5: MINGGU | G5: SENIN | H5: SELASA | I5: RABU | J5: KAMIS | K5: JUMAT | L5: SABTU | M5: MINGGU | N5: SENIN | O5: SELASA | P5: RABU | Q5: KAMIS | R5: JUMAT | S5: SABTU
A6: DESKRIPSI | B6: NOMINAL | C6: TANGGAL | D6: 45947 | E6: 45948 | F6: 45949 | G6: 45950 | H6: 45951 | I6: 45952 | J6: 45953 | K6: 45954 | L6: 45955 | M6: 45956 | N6: 45957 | O6: 45958 | P6: 45959 | Q6: 45960 | R6: 45961 | S6: 45962 | T6: TOTAL
T7: =SUM(D7:S7) -> 0
T8: =SUM(D8:S8) -> 0
T9: =SUM(D9:S9) -> 0
T10: =SUM(D10:S10) -> 0
T11: =SUM(D11:S11) -> 0
B12: TOTAL PENGEMBALIAN SUNTIKAN MODAL | D12: =SUM(D7:D11) -> 0 | E12: =SUM(E7:E11) -> 0 | F12: =SUM(F7:F11) -> 0 | G12: =SUM(G7:G11) -> 0 | H12: =SUM(H7:H11) -> 0 | I12: =SUM(I7:I11) -> 0 | J12: =SUM(J7:J11) -> 0 | K12: =SUM(K7:K11) -> 0 | ... T12: =SUM(T7:T11) -> 0

Sheet OUT - CF.12 Ops All Dept
B1: Kategori : | D1: Cash Outflow (Pengeluaran Kas) | F1: Hari Kerja
B2: Pos Akun : | D2: Pengeluaran Operasional Kantor | F2: Jadwal Pembayaran (Selasa/ Jumat)
B3: Periode : | F3: Hari Libur
C4: Kategori : | D4: Cash Outflow (Pengeluaran Kas) | G4: Hari Kerja
C5: Pos Akun : | D5: Operasional All Departemen | G5: Jadwal Pembayaran (Selasa/Kamis)
C6: Periode : | G6: Hari Libur
C7: Updated on : | D7: ='OUT - CFC - Bunga & Angsuran'!H4 -> 0 | E7: Pengeluaran Biaya Operating Sales & Marketing | F7: Pengeluaran Biaya Operating Sales & Marketing
E8: Minggu | F8: Senin | G8: Selasa | H8: Rabu | I8: Kamis | J8: Jumat | K8: Sabtu | L8: Minggu | M8: Senin | N8: Selasa | O8: Rabu | P8: Kamis | Q8: Jumat | R8: Sabtu | S8: Minggu | T8: Senin | U8: Selasa | V8: Rabu | W8: Kamis | X8: Jumat | Y8: Sabtu | Z8: Minggu | AA8: Senin | AB8: Selasa | AC8: Rabu | AD8: Kamis | AE8: Jumat | AF8: Sabtu | AG8: Minggu | AH8: Senin | AI8: Selasa | AJ8: Rabu | AK8: Kamis | AL8: Jumat | AM8: Sabtu | AN8: Minggu | AO8: Senin | AP8: Selasa | AQ8: Rabu | AR8: Kamis | AS8: Jumat | AT8: Sabtu | AU8: Minggu | AV8: Senin | AW8: Selasa | AX8: Rabu | AY8: Kamis | AZ8: Jumat | BA8: Sabtu | BB8: Minggu | BC8: Senin | BD8: Selasa | BE8: Rabu | BF8: Kamis | BG8: Jumat | BH8: Sabtu | BI8: Minggu | BJ8: Senin | BK8: Selasa | BL8: Rabu | BM8: Kamis | BN8: Jumat | BO8: Sabtu | BP8: Minggu | BQ8: Senin | BR8: Selasa | BS8: Rabu | BT8: Kamis | BU8: Jumat | BV8: Sabtu | BW8: Minggu | BX8: Senin | BY8: Selasa | BZ8: Rabu | CA8: Kamis | CB8: Jumat | CC8: Sabtu | CD8: Minggu | CE8: Senin | CF8: Selasa | CG8: Rabu | CH8: Kamis | CI8: Jumat | CJ8: Sabtu | CK8: Minggu | CL8: Senin | CM8: Selasa | CN8: Rabu | CO8: Kamis | CP8: Jumat | CQ8: Sabtu | CR8: Minggu | CS8: Senin | CT8: Selasa | CU8: Rabu | CV8: Kamis | CW8: Jumat | CX8: Sabtu | CY8: Minggu | CZ8: Senin | DA8: Selasa | DB8: Rabu | DC8: Kamis | DD8: Jumat | DE8: Sabtu | DF8: Minggu | DG8: Senin | DH8: Selasa | DI8: Rabu | DJ8: Kamis | DK8: Jumat | DL8: Sabtu | DM8: Minggu | DN8: Senin | DO8: Selasa | DP8: Rabu | DQ8: Kamis | DR8: Jumat | DS8: Sabtu | DT8: Minggu | DU8: Senin | DV8: Selasa | DW8: Rabu | DX8: Kamis | DY8: Jumat | DZ8: Sabtu | EA8: Minggu | EB8: Senin | EC8: Selasa | ED8: Rabu | EE8: Kamis | EF8: Jumat | EG8: Sabtu | EH8: Minggu | EI8: Senin | EJ8: Selasa | EK8: Rabu | EL8: Kamis | EM8: Jumat | EN8: Sabtu | EO8: Minggu | EP8: Senin | EQ8: Selasa | ER8: Rabu | ES8: Kamis | ET8: Jumat | EU8: Sabtu | EV8: Minggu | EW8: Senin | EX8: Selasa | EY8: Rabu | EZ8: Kamis | FA8: Jumat | FB8: Sabtu | FC8: Minggu | FD8: Senin | FE8: Selasa | FF8: Rabu | FG8: Kamis | FH8: Jumat | FI8: Sabtu | FJ8: Minggu | FK8: Senin | FL8: Selasa | FM8: Rabu | FN8: Kamis | FO8: Jumat
D9: TANGGAL | E9: 45704 | F9: 45705 | G9: 45706 | H9: 45707 | I9: 45708 | J9: 45709 | K9: 45710 | L9: 45711 | M9: 45712 | N9: 45713 | O9: 45714 | P9: 45715 | Q9: 45716 | R9: 45717 | S9: 45718 | T9: 45719 | U9: 45720 | V9: 45721 | W9: 45722 | X9: 45723 | Y9: 45724 | Z9: 45725 | AA9: 45726 | AB9: 45727 | AC9: 45728 | AD9: 45729 | AE9: 45730 | AF9: 45731 | AG9: 45732 | AH9: 45733 | AI9: 45734 | AJ9: 45735 | AK9: 45736 | AL9: 45737 | AM9: 45738 | AN9: 45739 | AO9: 45740 | AP9: 45741 | AQ9: 45742 | AR9: 45743 | AS9: 45744 | AT9: 45745 | AU9: 45746 | AV9: 45747 | AW9: 45748 | AX9: 45749 | AY9: 45750 | AZ9: 45751 | BA9: 45752 | BB9: 45753 | BC9: 45754 | BD9: 45755 | BE9: 45756 | BF9: 45757 | BG9: 45758 | BH9: 45759 | BI9: 45760 | BJ9: 45761 | BK9: 45762 | BL9: 45763 | BM9: 45764 | BN9: 45765 | BO9: 45766 | BP9: 45767 | BQ9: 45768 | BR9: 45769 | BS9: 45770 | BT9: 45771 | BU9: 45772 | BV9: 45773 | BW9: 45774 | BX9: 45775 | BY9: 45776 | BZ9: 45777 | CA9: 45778 | CB9: 45779 | CC9: 45780 | CD9: 45781 | CE9: 45782 | CF9: 45783 | CG9: 45784 | CH9: 45785 | CI9: 45786 | CJ9: 45787 | CK9: 45788 | CL9: 45789 | CM9: 45790 | CN9: 45791 | CO9: 45792 | CP9: 45793 | CQ9: 45794 | CR9: 45795 | CS9: 45796 | CT9: 45797 | CU9: 45798 | CV9: 45799 | CW9: 45800 | CX9: 45801 | CY9: 45802 | CZ9: 45803 | DA9: 45804 | DB9: 45805 | DC9: 45806 | DD9: 45807 | DE9: 45808 | DF9: 45809 | DG9: 45810 | DH9: 45811 | DI9: 45812 | DJ9: 45813 | DK9: 45814 | DL9: 45815 | DM9: 45816 | DN9: 45817 | DO9: 45818 | DP9: 45819 | DQ9: 45820 | DR9: 45821 | DS9: 45822 | DT9: 45823 | DU9: 45824 | DV9: 45825 | DW9: 45826 | DX9: 45827 | DY9: 45828 | DZ9: 45829 | EA9: 45830 | EB9: 45831 | EC9: 45832 | ED9: 45833 | EE9: 45834 | EF9: 45835 | EG9: 45836 | EH9: 45837 | EI9: 45838 | EJ9: 45839 | EK9: 45840 | EL9: 45841 | EM9: 45842 | EN9: 45843 | EO9: 45844 | EP9: 45845 | EQ9: 45846 | ER9: 45847 | ES9: 45848 | ET9: 45849 | EU9: 45850 | EV9: 45851 | EW9: 45852 | EX9: 45853 | EY9: 45854 | EZ9: 45855 | FA9: 45856 | FB9: 45857 | FC9: 45858 | FD9: 45859 | FE9: 45860 | FF9: 45861 | FG9: 45862 | FH9: 45863 | FI9: 45864 | FJ9: 45865 | FK9: 45866 | FL9: 45867 | FM9: 45868 | FN9: 45869 | FO9: 45870 | FP9: TOTAL
A11: KEBUTUHAN BIAYA YANG BELUM MENJADI OUTSTANDING HUTANG, TETAPI AKAN DIBIAYAKAN | B11: NOMINAL | C11: TGL JATUH TEMPO
A12: Pembelian Cairan Ozym @2 Pcs | B12: 500000 | C12: BID | CS12: Pembelian Cairan Ozym @2 Pcs | CT12: 500000 | CU12: BID | DD12: 500000 | FP12: =SUM(E12:FO12) -> 1000000
A13: Pembelian Seragam Capster @6 Pcs | B13: 390000 | C13: BID | CS13: Pembelian Seragam Capster @6 Pcs | CT13: 390000 | CU13: BID | FP13: =SUM(E13:FO13) -> 390000
A14: Pembelian Cape Gooper @10 Pcs | B14: 1150000 | C14: BID | CS14: Pembelian Cape Gooper @10 Pcs | CT14: 1150000 | CU14: BID | DD14: 1150000 | FP14: =SUM(E14:FO14) -> 2300000
A15: Pembelian Sepatu Cliper ukuran 0.5 @3 Set | B15: 48000 | C15: BID | CS15: Pembelian Sepatu Cliper ukuran 0.5 @3 Set | CT15: 48000 | CU15: BID | FP15: =SUM(E15:FO15) -> 48000
A16: Pembelian Produk Hairnutrition @100 Pcs | B16: 3500000 | C16: BID | CS16: Pembelian Produk Hairnutrition @100 Pcs | CT16: 3500000 | CU16: BID | FP16: =SUM(E16:FO16) -> 3500000
A17: Ads Conversi Gooper | B17: 2000000 | C17: BID | CS17: Ads Conversi Gooper | CT17: 2000000 | CU17: BID | FP17: =SUM(E17:FO17) -> 2000000
A18: Sampah Gooper | B18: 50000 | C18: BID | CS18: Sampah Gooper | CT18: 50000 | CU18: BID | FP18: =SUM(E18:FO18) -> 50000
A19: Sampah BID | B19: 70000 | C19: BID | CS19: Sampah BID | CT19: 70000 | CU19: BID | FP19: =SUM(E19:FO19) -> 70000
A20: Internet Gooper | B20: 405150 | C20: BID | CS20: Internet Gooper | CT20: 405150 | CU20: BID | FP20: =SUM(E20:FO20) -> 405150
A21: Internet BID | B21: 405150 | C21: BID | CS21: Internet BID | CT21: 405150 | CU21: BID | FP21: =SUM(E21:FO21) -> 405150
A22: Mess Gooper | B22: 550000 | C22: BID | CS22: Mess Gooper | CT22: 550000 | CU22: BID | FP22: =SUM(E22:FO22) -> 550000
A23: Keperluan Dapur BID | B23: 350000 | C23: BID | CS23: Keperluan Dapur BID | CT23: 350000 | CU23: BID | FP23: =SUM(E23:FO23) -> 350000
A24: Kebersihan BID | B24: 430000 | C24: BID | CS24: Kebersihan BID | CT24: 430000 | CU24: BID | FP24: =SUM(E24:FO24) -> 430000
A25: Kebersihan Gooper | B25: 150000 | C25: BID | CS25: Kebersihan Gooper | CT25: 150000 | CU25: BID | FP25: =SUM(E25:FO25) -> 150000
A26: Laundry Gooper | B26: 70000 | C26: BID | CS26: Laundry Gooper | CT26: 70000 | CU26: BID | CY26: 70008 | FP26: =SUM(E26:FO26) -> 140008
A27: Snack Gooper | B27: 390000 | C27: BID | CS27: Snack Gooper | CT27: 390000 | CU27: BID | DD27: 390000 | FP27: =SUM(E27:FO27) -> 780000
A28: Signature Drink Gooper | B28: 140000 | C28: BID | CS28: Signature Drink Gooper | CT28: 140000 | CU28: BID | FP28: =SUM(E28:FO28) -> 140000
A29: Shampoo Gooper @6 Pcs | B29: 1184750 | C29: BID | CS29: Shampoo Gooper @6 Pcs | CT29: 1184750 | CU29: BID | FP29: =SUM(E29:FO29) -> 1184750
A30: Grand Opening Gooper | B30: 5000000 | C30: BID | CS30: Grand Opening Gooper | CT30: 5000000 | CU30: BID | FP30: =SUM(E30:FO30) -> 5000000
A31: Biaya Riset | B31: 3000000 | C31: BID | CS31: Biaya Riset | CT31: 3000000 | CU31: BID | FP31: =SUM(E31:FO31) -> 3000000
A32: Kertas thermal Lite | B32: 30000 | C32: BID | CS32: Kertas thermal Lite | CT32: 30000 | CU32: BID | DD32: 30000 | FP32: =SUM(E32:FO32) -> 60000
A33: Disinfectan Bkleen 5 L @1 Pcs | B33: 88000 | C33: BID | CS33: Disinfectan Bkleen 5 L @1 Pcs | CT33: 88000 | CU33: BID | DD33: 88000 | FP33: =SUM(E33:FO33) -> 176000
A34: Roazor @2 Pcs | B34: 70000 | C34: BID | CS34: Roazor @2 Pcs | CT34: 70000 | CU34: BID | DD34: 70000 | FP34: =SUM(E34:FO34) -> 140000
A35: Box Silet | B35: 35000 | C35: BID | CS35: Box Silet | CT35: 35000 | CU35: BID | DD35: 35000 | FP35: =SUM(E35:FO35) -> 70000
A36: Sarung Tangan latex | B36: 40000 | C36: BID | CS36: Sarung Tangan latex | CT36: 40000 | CU36: BID | DD36: 40000 | FP36: =SUM(E36:FO36) -> 80000
A37: Pouch Sterilisasi 13,5 x 28 (Besar) | B37: 95000 | C37: BID | CS37: Pouch Sterilisasi 13,5 x 28 (Besar) | CT37: 95000 | CU37: BID | FP37: =SUM(E37:FO37) -> 95000
A38: Pouch Sterilisasi 9 x 26 (Kecil) | B38: 64000 | C38: BID | CS38: Pouch Sterilisasi 9 x 26 (Kecil) | CT38: 64000 | CU38: BID | FP38: =SUM(E38:FO38) -> 64000
A39: Penutup Kepala Cat Rambut | B39: 99000 | C39: BID | CS39: Penutup Kepala Cat Rambut | CT39: 99000 | CU39: BID | DD39: 20000 | FP39: =SUM(E39:FO39) -> 119000
A40: Sisir Over Comb | B40: 25000 | C40: BID | CS40: Sisir Over Comb | CT40: 25000 | CU40: BID | DD40: 25000 | FP40: =SUM(E40:FO40) -> 50000
A41: Papper Bag @100 Pcs | B41: 1600000 | C41: BID | CS41: Papper Bag @100 Pcs | CT41: 1600000 | CU41: BID | FP41: =SUM(E41:FO41) -> 1600000
A42: Printing Signage | B42: 130000 | C42: BID | CS42: Printing Signage | CT42: 130000 | CU42: BID | FP42: =SUM(E42:FO42) -> 130000
A43: KOL | B43: 3000000 | C43: BID | CS43: KOL | CT43: 3000000 | CU43: BID | FP43: =SUM(E43:FO43) -> 3000000
A44: Conditioner Gooper | B44: 120000 | C44: BID | CS44: Conditioner Gooper | CT44: 120000 | CU44: BID | FP44: =SUM(E44:FO44) -> 120000
A45: AC Daikin 1/2 PK untuk Meeting Room BID | B45: 3814000 | C45: BID | CS45: AC Daikin 1/2 PK untuk Meeting Room BID | CT45: 3814000 | CU45: BID | FP45: =SUM(E45:FO45) -> 3814000
A46: Satnding Briket TV | B46: 400000 | C46: BID | CS46: Satnding Briket TV | CT46: 400000 | CU46: BID | FP46: =SUM(E46:FO46) -> 400000
A47: TV 43 Inch | B47: 5000000 | C47: BID | CS47: TV 43 Inch | CT47: 5000000 | CU47: BID | FP47: =SUM(E47:FO47) -> 5000000
A48: Kebersihan Corp | B48: 2000000 | C48: WG001 | D48: WG001 | FP48: =SUM(E48:FO48) -> 0
A49: Pemeliharaan Corp | B49: =900000+400000 -> 1300000 | C49: WG001 | D49: WG001 | FP49: =SUM(E49:FO49) -> 0
A50: Rumdin - WG-001 | B50: 60000000 | C50: WG001 | D50: WG001 | DB50: 60000000 | FP50: =SUM(E50:FO50) -> 60000000
A51: Survey & Trial Team Building Baru | B51: 2500000 | C51: PD | D51: PD | FP51: =SUM(E51:FO51) -> 0
A52: Product Launching 1 | B52: 3000000 | C52: PD | D52: PD | FP52: =SUM(E52:FO52) -> 0
A53: Videographer Exxon Mobile | B53: 1800000 | C53: PD | D53: PD | FP53: =SUM(E53:FO53) -> 0
A54: Prototipe product dupe Peek Me with Sekar Jawi | B54: 1500000 | C54: PD | D54: PD | FP54: =SUM(E54:FO54) -> 0
A55: Survey Escape Room Lippo Plaza Jogja | B55: 1000000 | C55: PD | D55: PD | FP55: =SUM(E55:FO55) -> 0
A56: Survey Remen Jawi | B56: 1000000 | C56: PD | D56: PD | FP56: =SUM(E56:FO56) -> 0
A57: Survey Gajah Putih Resto Bali & Team Building & Party Planner Bali, Silent Disco, Wellness Center | B57: 15000000 | C57: PD | D57: PD | FP57: =SUM(E57:FO57) -> 0
A58: Survey Local Resto Yogyakarta | B58: 1500000 | C58: PD | D58: PD | FP58: =SUM(E58:FO58) -> 0
A59: Buy & Trial Unsolved Case Files | B59: 750000 | C59: PD | D59: PD | FP59: =SUM(E59:FO59) -> 0
A60: Brainstorming Case File & Escape Room with Games Master | B60: 750000 | C60: PD | D60: PD | FP60: =SUM(E60:FO60) -> 0
A61: IDUL ADHA - PEMBELIAN KAMBING 2 KAMBING @3.500.000 | D61: HR | DJ61: 7000000 | FP61: =SUM(E61:FO61) -> 7000000
A62: JUMPSTAR | D62: HR | DH62: 2500000 | EJ62: 2500000 | FO62: 2500000 | FP62: =SUM(E62:FO62) -> 7500000
A63: KARYAWAN SAKIT 2 ORANG RP250.000 | D63: HR | DO63: 500000 | FP63: =SUM(E63:FO63) -> 500000
A64: MID YEAR RECHARGE FEE TENAGA AHLI | D64: HR | FE64: 50000000 | FP64: =SUM(E64:FO64) -> 50000000
A65: JOB PORTAL | D65: HR | DQ65: 600000 | ES65: 600000 | FP65: =SUM(E65:FO65) -> 1200000
A66: KOS RAMA 2 BULAN (JUNI - JULI) | D66: HR | DQ66: 850000 | EQ66: 850000 | FP66: =SUM(E66:FO66) -> 1700000
A67: KOS VIANA 2 BULAN (JUNI - JULI) | D67: HR | DJ67: 3250000 | EQ67: 3250000 | FP67: =SUM(E67:FO67) -> 6500000
A68: BPJS KESEHATAN | D68: HR | EE68: 8170905 | FL68: 8170905 | FP68: =SUM(E68:FO68) -> 16341810
A69: BPJS KETENAGAKERJAAN | D69: HR | EE69: 21501882 | FL69: 21501882 | FP69: =SUM(E69:FO69) -> 43003764
A70: BIAYA PEMB JASA CLEANING SERVICE BULAN MARET 2025 | D70: HR | EE70: 7853000 | FL70: 7853000 | FP70: =SUM(E70:FO70) -> 15706000
A71: BIAYA PEMB JASA PERSONIL SECURITY BULAN MARET 2025 | D71: HR | EE71: 9389430 | FL71: 9389430 | FP71: =SUM(E71:FO71) -> 18778860
A72: BIAYA PEMB MANAJEMENT FEE JASA PERSONIL SECURITY BULAN MARET 2025 | D72: HR | EE72: 600000 | FL72: 600000 | FP72: =SUM(E72:FO72) -> 1200000
A73: BIAYA PEMB TAMBAHAN BELI PUTUS SEPATU UNTUK JASA CLEANING SERVICE | D73: HR | EE73: 948717 | FL73: 948717 | FP73: =SUM(E73:FO73) -> 1897434
A74: BIAYA PEMB FASILITASI AKTA PERUBAHAN PT WERKUDARA NIRWANA SAKTI | D74: HR | EE74: 7750000 | FL74: 7750000 | FP74: =SUM(E74:FO74) -> 15500000
A75: BIAYA PEMB FEE KONSULTAN BULAN JANUARI 2025 | D75: HR | EE75: 3076923 | FL75: 3076923 | FP75: =SUM(E75:FO75) -> 6153846
A76: BIAYA PEMB JASA INHOUSE LAWYER PT WERKUDARA NIRWANA SAKTI BULAN MARET 2025 | D76: HR | EE76: 4591837 | FL76: 4591837 | FP76: =SUM(E76:FO76) -> 9183674
A77: BIAYA PEMB JASA INHOUSE LAWYER PT WERKUDARA NIRWANA SAKTI BULAN MARET 2025 | D77: HR | EE77: 4591837 | FL77: 4591837 | FP77: =SUM(E77:FO77) -> 9183674
FP78: =SUM(E78:FO78) -> 0
FP79: =SUM(E79:FO79) -> 0
E80: =SUM(E12:E79) -> 0 | F80: =SUM(F12:F79) -> 0 | G80: =SUM(G12:G79) -> 0 | H80: =SUM(H12:H79) -> 0 | I80: =SUM(I12:I79) -> 0 | J80: =SUM(J12:J79) -> 0 | K80: =SUM(K12:K79) -> 0 | L80: =SUM(L12:L79) -> 0 | ... FP80: =SUM(FP12:FP79) -> 308160120

Sheet IN-Pengem Pinj Pokok
B1: Kategori : | C1: Cash Outflow (Pengeluaran Kas) | E1: Hari Kerja
B2: Pos Akun : | C2: Pengembalian Pinjaman Pokok | E2: Jadwal Pembayaran (Selasa/ Jumat)
B3: Periode : | E3: Hari Libur
B4: Updated on : | C4: ='OUT - TEP - Sales Call'!C4 -> 45947 | D4: Pengeluaran Biaya Operating Sales & Marketing | E4: Pengeluaran Biaya Operating Sales & Marketing
D5: Minggu | E5: Senin | F5: Selasa | G5: Rabu | H5: Kamis | I5: Jumat | J5: Sabtu | K5: Minggu | L5: Senin | M5: Selasa | N5: Rabu | O5: Kamis | P5: Jumat | Q5: Sabtu | R5: Minggu | S5: Senin | T5: Selasa | U5: Rabu | V5: Kamis | W5: Jumat | X5: Sabtu | Y5: Minggu | Z5: Senin | AA5: Selasa | AB5: Rabu | AC5: Kamis | AD5: Jumat | AE5: Sabtu | AF5: Minggu | AG5: Senin | AH5: Selasa | AI5: Rabu | AJ5: Kamis | AK5: Jumat | AL5: Sabtu | AM5: Minggu | AN5: Senin | AO5: Selasa | AP5: Rabu | AQ5: Kamis | AR5: Jumat | AS5: Sabtu | AT5: Minggu | AU5: Senin | AV5: Selasa | AW5: Rabu | AX5: Kamis | AY5: Jumat | AZ5: Sabtu | BA5: Minggu | BB5: Senin | BC5: Selasa | BD5: Rabu | BE5: Kamis | BF5: Jumat | BG5: Sabtu | BH5: Minggu | BI5: Senin | BJ5: Selasa | BK5: Rabu | BL5: Kamis | BM5: Jumat | BN5: Sabtu | BO5: Minggu | BP5: Senin | BQ5: Selasa | BR5: Rabu | BS5: Kamis | BT5: Jumat | BU5: Sabtu | BV5: Minggu | BW5: Senin | BX5: Selasa | BY5: Rabu | BZ5: Kamis | CA5: Jumat | CB5: Sabtu | CC5: Minggu | CD5: Senin | CE5: Selasa | CF5: Rabu | CG5: Kamis | CH5: Jumat | CI5: Sabtu | CJ5: Minggu | CK5: Senin | CL5: Selasa | CM5: Rabu | CN5: Kamis | CO5: Jumat | CP5: Sabtu | CQ5: Minggu | CR5: Senin | CS5: Selasa | CT5: Rabu | CU5: Kamis | CV5: Jumat | CW5: Sabtu | CX5: Minggu | CY5: Senin | CZ5: Selasa | DA5: Rabu | DB5: Kamis | DC5: Jumat | DD5: Sabtu | DE5: Minggu | DF5: Senin | DG5: Selasa | DH5: Rabu | DI5: Kamis | DJ5: Jumat | DK5: Sabtu | DL5: Minggu | DM5: Senin | DN5: Selasa | DO5: Rabu | DP5: Kamis | DQ5: Jumat | DR5: Sabtu | DS5: Minggu | DT5: Senin | DU5: Selasa | DV5: Rabu | DW5: Kamis | DX5: Jumat | DY5: Sabtu | DZ5: Minggu | EA5: Senin | EB5: Selasa | EC5: Rabu | ED5: Kamis | EE5: Jumat | EF5: Sabtu | EG5: Minggu | EH5: Senin | EI5: Selasa | EJ5: Rabu | EK5: Kamis | EL5: Jumat | EM5: Sabtu | EN5: Minggu | EO5: Senin | EP5: Selasa | EQ5: Rabu | ER5: Kamis | ES5: Jumat | ET5: Sabtu | EU5: Minggu | EV5: Senin | EW5: Selasa | EX5: Rabu | EY5: Kamis | EZ5: Jumat | FA5: Sabtu | FB5: Minggu | FC5: Senin | FD5: Selasa | FE5: Rabu | FF5: Kamis | FG5: Jumat | FH5: Sabtu | FI5: Minggu | FJ5: Senin | FK5: Selasa | FL5: Rabu | FM5: Kamis | FN5: Jumat
A6: KETERANGAN PENGEMBALIAN PINJAMAN POKOK | B6: NOMINAL | C6: TANGGAL | D6: 45704 | E6: 45705 | F6: 45706 | G6: 45707 | H6: 45708 | I6: 45709 | J6: 45710 | K6: 45711 | L6: 45712 | M6: 45713 | N6: 45714 | O6: 45715 | P6: 45716 | Q6: 45717 | R6: 45718 | S6: 45719 | T6: 45720 | U6: 45721 | V6: 45722 | W6: 45723 | X6: 45724 | Y6: 45725 | Z6: 45726 | AA6: 45727 | AB6: 45728 | AC6: 45729 | AD6: 45730 | AE6: 45731 | AF6: 45732 | AG6: 45733 | AH6: 45734 | AI6: 45735 | AJ6: 45736 | AK6: 45737 | AL6: 45738 | AM6: 45739 | AN6: 45740 | AO6: 45741 | AP6: 45742 | AQ6: 45743 | AR6: 45744 | AS6: 45745 | AT6: 45746 | AU6: 45747 | AV6: 45748 | AW6: 45749 | AX6: 45750 | AY6: 45751 | AZ6: 45752 | BA6: 45753 | BB6: 45754 | BC6: 45755 | BD6: 45756 | BE6: 45757 | BF6: 45758 | BG6: 45759 | BH6: 45760 | BI6: 45761 | BJ6: 45762 | BK6: 45763 | BL6: 45764 | BM6: 45765 | BN6: 45766 | BO6: 45767 | BP6: 45768 | BQ6: 45769 | BR6: 45770 | BS6: 45771 | BT6: 45772 | BU6: 45773 | BV6: 45774 | BW6: 45775 | BX6: 45776 | BY6: 45777 | BZ6: 45778 | CA6: 45779 | CB6: 45780 | CC6: 45781 | CD6: 45782 | CE6: 45783 | CF6: 45784 | CG6: 45785 | CH6: 45786 | CI6: 45787 | CJ6: 45788 | CK6: 45789 | CL6: 45790 | CM6: 45791 | CN6: 45792 | CO6: 45793 | CP6: 45794 | CQ6: 45795 | CR6: 45796 | CS6: 45797 | CT6: 45798 | CU6: 45799 | CV6: 45800 | CW6: 45801 | CX6: 45802 | CY6: 45803 | CZ6: 45804 | DA6: 45805 | DB6: 45806 | DC6: 45807 | DD6: 45808 | DE6: 45809 | DF6: 45810 | DG6: 45811 | DH6: 45812 | DI6: 45813 | DJ6: 45814 | DK6: 45815 | DL6: 45816 | DM6: 45817 | DN6: 45818 | DO6: 45819 | DP6: 45820 | DQ6: 45821 | DR6: 45822 | DS6: 45823 | DT6: 45824 | DU6: 45825 | DV6: 45826 | DW6: 45827 | DX6: 45828 | DY6: 45829 | DZ6: 45830 | EA6: 45831 | EB6: 45832 | EC6: 45833 | ED6: 45834 | EE6: 45835 | EF6: 45836 | EG6: 45837 | EH6: 45838 | EI6: 45839 | EJ6: 45840 | EK6: 45841 | EL6: 45842 | EM6: 45843 | EN6: 45844 | EO6: 45845 | EP6: 45846 | EQ6: 45847 | ER6: 45848 | ES6: 45849 | ET6: 45850 | EU6: 45851 | EV6: 45852 | EW6: 45853 | EX6: 45854 | EY6: 45855 | EZ6: 45856 | FA6: 45857 | FB6: 45858 | FC6: 45859 | FD6: 45860 | FE6: 45861 | FF6: 45862 | FG6: 45863 | FH6: 45864 | FI6: 45865 | FJ6: 45866 | FK6: 45867 | FL6: 45868 | FM6: 45869 | FN6: 45870 | FO6: ='OUT - TEP - Sales Call'!T7 -> 0
D7: 0 | E7: 0 | F7: 0 | G7: 0 | H7: 0 | I7: 0 | J7: 0 | K7: 0 | L7: 0 | M7: 0 | N7: 0 | O7: 0 | P7: 0 | Q7: 0 | R7: 0 | S7: 0 | T7: 0 | U7: 0 | V7: 0 | W7: 0 | X7: 0 | Y7: 0 | Z7: 0 | AA7: 0 | AB7: 0 | AC7: 0 | AD7: 0 | AE7: 0 | AF7: 0 | AG7: 0 | AH7: 0 | AI7: 0 | FO7: =SUM(D7:FN7) -> 0
D8: 0 | E8: 0 | F8: 0 | G8: 0 | H8: 0 | I8: 0 | J8: 0 | K8: 0 | L8: 0 | M8: 0 | N8: 0 | O8: 0 | P8: 0 | Q8: 0 | R8: 0 | S8: 0 | T8: 0 | U8: 0 | V8: 0 | W8: 0 | X8: 0 | Y8: 0 | Z8: 0 | AA8: 0 | AB8: 0 | AC8: 0 | AD8: 0 | AE8: 0 | AF8: 0 | AG8: 0 | AH8: 0 | AI8: 0 | FO8: =SUM(D8:FN8) -> 0
D9: 0 | E9: 0 | F9: 0 | G9: 0 | H9: 0 | I9: 0 | J9: 0 | K9: 0 | L9: 0 | M9: 0 | N9: 0 | O9: 0 | P9: 0 | Q9: 0 | R9: 0 | S9: 0 | T9: 0 | U9: 0 | V9: 0 | W9: 0 | X9: 0 | Y9: 0 | Z9: 0 | AA9: 0 | AB9: 0 | AC9: 0 | AD9: 0 | AE9: 0 | AF9: 0 | AG9: 0 | AH9: 0 | AI9: 0 | FO9: =SUM(D9:FN9) -> 0
D10: 0 | E10: 0 | F10: 0 | G10: 0 | H10: 0 | I10: 0 | J10: 0 | K10: 0 | L10: 0 | M10: 0 | N10: 0 | O10: 0 | P10: 0 | Q10: 0 | R10: 0 | S10: 0 | T10: 0 | U10: 0 | V10: 0 | W10: 0 | X10: 0 | Y10: 0 | Z10: 0 | AA10: 0 | AB10: 0 | AC10: 0 | AD10: 0 | AE10: 0 | AF10: 0 | AG10: 0 | AH10: 0 | AI10: 0 | FO10: =SUM(D10:FN10) -> 0
D11: 0 | E11: 0 | F11: 0 | G11: 0 | H11: 0 | I11: 0 | J11: 0 | K11: 0 | L11: 0 | M11: 0 | N11: 0 | O11: 0 | P11: 0 | Q11: 0 | R11: 0 | S11: 0 | T11: 0 | U11: 0 | V11: 0 | W11: 0 | X11: 0 | Y11: 0 | Z11: 0 | AA11: 0 | AB11: 0 | AC11: 0 | AD11: 0 | AE11: 0 | AF11: 0 | AG11: 0 | AH11: 0 | AI11: 0 | FO11: =SUM(D11:FN11) -> 0
B12: TOTAL PENGEMBALIAN PINJAMAN POKOK | D12: =SUM(D7:D11) -> 0 | E12: =SUM(E7:E11) -> 0 | F12: =SUM(F7:F11) -> 0 | G12: =SUM(G7:G11) -> 0 | H12: =SUM(H7:H11) -> 0 | I12: =SUM(I7:I11) -> 0 | J12: =SUM(J7:J11) -> 0 | K12: =SUM(K7:K11) -> 0 | ... FO12: =SUM(FO7:FO11) -> 0
D15: 44711 | E15: 44712

Sheet Saldo 2023
A1: Rekening | B1: Hold BRI - Bank Garansi | C1: 11 Nov 23
A2: BCA Fadli | C2: 593000000 | D2: 693765443 | E2: 650000000
A3: ocbc wisata | C3: 250000000
A4: maybank wisata
A5: BCA wisata | C5: 19000000 | D5: 16044456 | E5: 16000000
A6: ocbc nadi
A7: cimb nadi | C7: 37144153 | D7: 95483903 | E7: 94000000
A8: BRI nadi | C8: 19881203
A9: ocbc utama kalpana
A10: bri utama kalpana | C10: 143238223 | D10: 163188887 | E10: 162000000
A11: ocbc Sakti | C11: 254908753 | D11: 197831241 | E11: 196000000
A12: mandiri sakti | C12: 3000000 | D12: 362689733 | E12: 361000000
A13: bri sakti | B13: 124652925 | C13: =345426813-B13 -> 220773888 | D13: 463628643 | E13: =D13-B13-200000000 -> 138975718
A14: uob SAKTI
A15: cimb maharaja pratama | C15: 48028997 | D15: 231015428 | E15: 230000000
A16: bri maharaja pratama | C16: 2851067 | D16: 1,644,202 | E16: 0
A17: bri yukti | C17: 13809796 | D17: 13,790,562 | E17: 12000000
A18: mandiri yukti | C18: 136429446
C19: =SUM(C2:C18) -> 1742065526 | E19: =SUM(E2:E18) -> 1859975718
B33: keep utk Gaji juli'21
B34: sisa dana :
B36: Expenses Juli yang belum dibayar :
A37: 1 | B37: CC HSBC lama - 4439 (Min Payment)
A38: 2 | B38: CC HSBC baru - 6604
A39: 3 | B39: CC bri platinum 9007 (Min Payment)
A40: 4 | B40: Tag Grab Juli 21 (tunggu info dr bas)
B43: Kekurangan dana :

Sheet Saldo 2021
A1: No | B1: Rekening | C1: Hold BRI - Bank Garansi (IESR+HCML) | D1: Hold BRI - Bank Garansi - HCML | E1: Hold BRI - Bank Garansi | F1: Saldo - 14 Juli 21 | G1: Saldo Bank - 18 Juli 21 | H1: Saldo Bank - 23 Juli 22 | I1: Saldo Bank - 27 Juli 23 Pagi | J1: Saldo Bank - 27 Juli 23 siang | K1: Saldo Bank - 30 Juli pagi | L1: Saldo Bank - 2 Agt | M1: Saldo Bank - 3 Agt | N1: Saldo Bank - 4 Agt | O1: Saldo Bank - 9 Agt | P1: Saldo Bank 12 Agt | T1: Minimum Saldo | U1: OB | X1: minim saldo | Y1: 5000000 | AD1: Saldo Bank 17Agt | AE1: Saldo Bank 23 Agt | AF1: Saldo Bank 08 Okt | AG1: Saldo Bank 23 Okt 2021 | AH1: Saldo Bank 05 NOV 2021 | AJ1: Saldo Bank 09 NOV 2021 | AL1: Saldo Bank 11 NOV 2021 | AN1: Saldo Bank 15 NOV 2021 | AP1: Saldo Bank 23 NOV 2021 | AR1: Saldo Bank 25 NOV 2021 | AT1: Saldo Bank 25 NOV 2021 | AV1: Saldo Bank 01 DES 2021 | AX1: Saldo Bank 06 DES 2021 PAGI | AZ1: Saldo Bank 06 DES 2021 SORE | BB1: Saldo Bank 14 DES 2021 | BD1: Saldo Bank 21 DES 2021 | BF1: Saldo Bank 24 DES 2021 | BH1: Saldo Bank 24 DES 2021
A2: 1 | B2: ocbc wisata | F2: 13606839 | G2: 7172838 | H2: 2494209 | I2: 408516 | J2: =I2 -> 408516 | K2: 408516 | L2: 115516 | M2: 32088345 | N2: 2310439 | O2: =N2 -> 2310439 | P2: 803939 | X2: gaji | Y2: 68427226 | AD2: 2156479 | AE2: 5606979 | AF2: 20063551 | AG2: 47371167 | AH2: 61423690 | AI2: 60000000 | AJ2: 61423690 | AK2: 60000000 | AL2: 32275190 | AM2: 31000000 | AN2: 28339249 | AO2: 27100000 | AP2: 138060148 | AQ2: 135000000 | AR2: 20767648 | AS2: 19000000 | AT2: 49299478 | AU2: 48000000 | AV2: 13818424 | AW2: 12000000 | AX2: 8450234 | AY2: 8000000 | AZ2: 8450234 | BA2: 8000000 | BB2: 1656464 | BC2: 1000000 | BD2: 28024464 | BE2: 27000000 | BF2: 8924743 | BG2: 7000000 | BH2: 8924743 | BI2: 7000000
A3: 2 | B3: ocbc nadi | F3: 7328295 | G3: 1715926 | H3: 1715926 | I3: 1717186 | J3: 1084176 | K3: 1114176 | L3: 1084176 | M3: 1084176 | N3: 1084176 | O3: =N3 -> 1084176 | P3: 77676 | Q3: 1 | R3: =B3 -> ocbc nadi | S3: OCBC UK - ob ke bca | U3: 1000000 | V3: Rival | W3: done | X3: saldo | Y3: =J10 -> -109922450 | AD3: 77958 | AE3: 77958 | AF3: 577999 | AG3: 578202 | AH3: 578202 | AJ3: 578202 | AN3: 578202 | AP3: 10578202 | AQ3: 9000000 | AR3: 10578202 | AS3: 9000000 | AT3: 10581570 | AV3: 10581570 | AW3: 9000000 | AX3: 565070 | AZ3: 565070 | BD3: 595070 | BF3: 595070 | BH3: 595070
A4: 3 | B4: ocbc utama kalpana | F4: 1715926 | G4: 7328295 | H4: 7328295 | I4: 7332816 | J4: 326316 | K4: 326316 | L4: 296316 | M4: 296316 | N4: 296316 | O4: =N4 -> 296316 | P4: 296316 | X4: kek bunga pinjaman | Y4: 2500000 | AD4: 266652 | AE4: 266652 | AF4: 486825 | AG4: 457076 | AH4: 457076 | AJ4: 457076 | AN4: 457076 | AP4: 457076 | AX4: 427370 | AZ4: 427370 | BD4: 427,370.00 | BF4: 427370 | BH4: 427370
A5: 4 | B5: cimb nadi | F5: 45885627 | G5: 45885627 | H5: 100429527 | I5: 100429527 | J5: 100429527 | K5: 3280527 | L5: 1018584 | M5: 1018584 | N5: 2668584 | O5: =N5 -> 2668584 | P5: 1012084 | Q5: 2 | R5: =B5 -> cimb nadi | S5: ob ke bca | T5: 1000000 | U5: 1650000 | V5: Jay | W5: done | Y5: =SUM(Y1:Y4) -> -33995224 | Z5: (80 jt ob ke bri 306) | AD5: 971884 | AE5: 941884 | AF5: 1271884 | AG5: 1241884 | AH5: 1241884 | AJ5: 1241884 | AN5: 1241884 | AP5: 1211884 | AX5: 35086343 | AY5: 34000000 | AZ5: 1597984 | BA5: 1000000 | BD5: 1567984 | BF5: 1567984 | BH5: 1567984
A6: 5 | B6: cimb MRP | F6: 1324344 | G6: 1324344 | H6: 1294344 | I6: 1294344 | J6: 1294344 | K6: 1294344 | L6: 1294344 | M6: 1294344 | N6: 1294344 | O6: =N6 -> 1294344 | P6: 1012844 | Q6: 3 | R6: =B6 -> cimb MRP | S6: ob ke bca | T6: 1000000 | U6: 275000 | V6: Rival | W6: done | AD6: 982844 | AE6: 952844 | AF6: 902844 | AG6: 872844 | AH6: 872844 | AJ6: 822844 | AN6: 822844 | AP6: 792844 | AT6: 135099343 | AU6: 130000000 | AV6: 35086343 | AW6: 34000000 | AX6: 1597984 | AY6: 1000000 | AZ6: 35086343 | BA6: 34000000 | BD6: 178020203 | BE6: 175000000 | BF6: 28000703 | BG6: 27000000 | BH6: 28000703 | BI6: 27000000
A7: 6 | B7: bri yukti | F7: 618775 | G7: 618775 | H7: 39789237 | I7: 39789237 | J7: 39789237 | K7: 39789237 | L7: 39789237 | M7: 782737 | N7: 782737 | O7: =N7 -> 782737 | P7: 76237 | Q7: 4 | R7: =B7 -> bri yukti | S7: ob ke bca | T7: 50000 | U7: 700000 | V7: Jay | W7: done | AD7: 12820527 | AE7: 7986110 | AF7: 979610 | AG7: 65609961 | AH7: 603461 | AJ7: 603461 | AN7: 603461 | AP7: 616547 | AX7: 616547 | AZ7: 616547 | BD7: 566.547 | BF7: 566.547 | BH7: 566.547
A8: 7 | B8: bri utama kalpana | F8: 3052820 | G8: 3052820 | H8: 3057682 | I8: 3057682 | J8: 3057682 | K8: 3057682 | L8: 3057682 | M8: 3057682 | N8: 3057682 | O8: =N8 -> 3057682 | P8: 51182 | Q8: 5 | R8: =B8 -> bri utama kalpana | S8: ob ke bca | U8: 3000000 | V8: Jay | W8: done | X8: =57500*3 -> 172500 | AD8: 2376 | AE8: 0 | AF8: 500000 | AG8: 34771904 | AH8: 758904 | AJ8: 450000 | AN8: 450000 | AP8: 762646 | AX8: 762646 | AZ8: 762646 | BB8: 3.032.474 | BC8: 2000000 | BD8: 970.484 | BF8: 970.484 | BH8: 970.484
A9: 8 | B9: bri MRP | F9: 562208 | G9: 562208 | H9: 568297 | I9: 568297 | J9: 568297 | K9: 568297 | L9: 568297 | M9: 568297 | N9: 568297 | O9: =N9 -> 568297 | P9: 61797 | Q9: 6 | R9: =B9 -> bri MRP | S9: ob ke bca | T9: 50000 | U9: 500000 | V9: Jay | W9: done | AD9: 5519 | AF9: 500000 | AG9: 450000 | AH9: 450000 | AJ9: 758904 | AN9: 758904 | AP9: 400000 | AX9: 400000 | AZ9: 400000 | BD9: 350000 | BF9: 350000 | BH9: 350000
A10: 9 | B10: bri sakti | C10: 234575375 | D10: 124652925 | E10: 234575375 | F10: =D10-E10 -> -109922450 | G10: =F10 -> -109922450 | H10: =G10 -> -109922450 | I10: =H10 -> -109922450 | J10: =I10 -> -109922450 | K10: =202201212-D10 -> 77548287 | L10: 5079483 | M10: 10157033 | N10: 154133 | O10: =N10 -> 154133 | P10: 154133 | AD10: =672748584-234575375 -> 438173209 | AE10: =444213426-E10 -> 209638051 | AF10: =291613421-234575375 -> 57038046 | AG10: =303724025-D10 -> 179071100 | AH10: =129658225-D10 -> 5005300 | AJ10: =171620725-D10 -> 46967800 | AK10: 45000000 | AL10: 138742374 | AM10: 12000000 | AN10: 170521374 | AO10: 45000000 | AP10: 253584874 | AQ10: =AP10-D10 -> 128931949 | AR10: 263235914 | AS10: =AR10-D10-85000000 -> 53582989 | AT10: 517490249 | AU10: =AT10-D10-100000000 -> 292837324 | AV10: 331123626 | AW10: =AV10-D10 -> 206470701 | AX10: 136439626 | AY10: =AX10-D10-1000000 -> 10786701 | AZ10: 197265776 | BA10: =AZ10-D10-1000000 -> 71612851 | BB10: 127052876 | BC10: =BB10-D10 -> 2399951 | BD10: 167976696 | BE10: =165000000-D10 -> 40347075 | BH10: 228802846 | BI10: =BH10-D10-1000000 -> 103149921
A11: 10 | B11: mandiri sakti | F11: 69402 | G11: =F11 -> 69402 | H11: =G11 -> 69402 | I11: 59402 | J11: 59402 | K11: 59402 | L11: 22035 | M11: 22035 | N11: 1776672 | O11: =N11 -> 1776672 | P11: 60172 | Q11: 7 | R11: =B11 -> mandiri sakti | S11: ob ke bca | T11: 50000 | U11: 1700000 | V11: Rival | W11: done | AD11: 12963 | AE11: 12963 | AF11: 490000 | AG11: 452500 | AH11: 452500 | AJ11: 442500 | AN11: 442500 | AP11: 442500 | AX11: 405000 | AZ11: 405000 | BD11: 95000 | BF11: 85000 | BH11: 85000
A12: 11 | B12: mandiri yukti | F12: 1812400 | G12: =F12 -> 1812400 | H12: =G12 -> 1812400 | I12: 1812400 | J12: 1812400 | K12: 1812400 | L12: 1776672 | M12: 1776672 | N12: 22035 | O12: =N12 -> 22035 | P12: 22035 | AD12: 6799880 | AE12: 6799880 | AF12: 747669 | AG12: 700169 | AH12: 700169 | AJ12: 700169 | AN12: 700169 | AP12: 700169 | AX12: 652669 | AZ12: 652669 | BD12: 44288502 | BE12: 40000000 | BF12: 44278502 | BG12: 43000000 | BH12: 44278502 | BI12: 43000000
A13: 12 | B13: maybank - Wisata | F13: 3038511 | G13: =F13 -> 3038511 | H13: =G13 -> 3038511 | I13: 3038511 | J13: 3038511 | K13: 3038511 | L13: 3038511 | M13: 923511 | N13: 937511 | O13: =N13 -> 937511 | P13: 85011 | Q13: 8 | R13: =B13 -> maybank - Wisata | S13: ob ke ocbc wisata | U13: 850000 | V13: Rival | W13: done | AD13: 11375324 | AE13: 11426324 | AF13: 6822377 | AG13: 10598461 | AH13: 20867150 | AI13: 19000000 | AJ13: 22217150 | AK13: 21000000 | AL13: 1217150 | AN13: 3108088 | AO13: 2000000 | AP13: 1177648 | AR13: 45177648 | AS13: 42000000 | AT13: 19425148 | AV13: 35882821 | AW13: 34000000 | AX13: 45835321 | AY13: 835321 | AZ13: 38547821 | BA13: 37000000 | BB13: 30896685 | BC13: 30000000 | BD13: 53654355 | BE13: 50000000 | BF13: 121835155 | BG13: 120000000 | BH13: 121835155 | BI13: 120000000
A14: 13 | B14: BCA - Wisata | F14: 1712427 | G14: 993597 | H14: 993597 | I14: 993597 | J14: =I14 -> 993597 | K14: 987097 | L14: 957097 | M14: 2597097 | N14: 700203 | O14: =N14 -> 700203 | P14: 1076985 | U14: =U13+U11+U9+U8+U6+U5+U7+U3 -> 9675000 | AB14: =K16 -> 133284792 | AD14: 978000 | AE14: 8253100 | AF14: 11000000 | AG14: 50000521 | AH14: 13466791 | AI14: 12000000 | AJ14: 38831791 | AK14: 37000000 | AL14: 23229391 | AM14: 22000000 | AN14: 23229391 | AO14: =22200000+19000000 -> 41200000 | AP14: 28293829 | AQ14: 27000000 | AR14: 67832048 | AS14: 66000000 | AT14: 29417155 | AV14: 21598564 | AW14: 20000000 | AX14: 28592952 | AY14: 28000000 | AZ14: 23,757,914. | BA14: 22000000 | BB14: 88269082 | BC14: 87000000 | BD14: 11341382 | BE14: 10000000 | BF14: 16,030,819 | BG14: 15000000 | BH14: 16,030,819 | BI14: 15000000
A15: 14 | B15: UOB- SAKTI | AE15: 15000000 | AF15: 81248986 | AH15: 1940421 | AJ15: 1940421 | AN15: 1940421 | AP15: 1990421 | AX15: 500000 | AZ15: 500000 | BD15: 1943136
A16: Total Saldo Bank | F16: =SUM(F2:F14) -> -29194876 | G16: =SUM(G2:G14) -> -36347707 | H16: =SUM(H2:H14) -> 52668977 | I16: =SUM(I2:I14) -> 50579065 | J16: =SUM(J2:J14) -> 42939555 | K16: =SUM(K2:K14) -> 133284792 | L16: =SUM(L2:L14) -> 58097950 | M16: =SUM(M2:M14) -> 55666829 | ... P16: =SUM(P2:P14) -> 4790411 | U16: =10801818 -> 10801818 | V16: 5 Agt | X16: selisih = | AD16: =SUM(AD2:AD15) -> 474623615 | AE16: =SUM(AE2:AE15) -> 266962745 | AF16: =SUM(AF2:AF15) -> 182629791 | AG16: =SUM(AG2:AG15) -> 392175789 | AH16: =SUM(AH2:AH15) -> 108818392 | AI16: =SUM(AI2:AI15) -> 91000000 | AK16: =SUM(AK2:AK15) -> 163000000 | AM16: =SUM(AM2:AM15) -> 65000000 | AO16: =SUM(AO2:AO15) -> 115300000 | AQ16: =SUM(AQ2:AQ15) -> 299931949 | AS16: =SUM(AS2:AS15) -> 189582989 | AU16: =SUM(AU2:AU15) -> 470837324 | AW16: =SUM(AW2:AW15) -> 315470701 | AY16: =SUM(AY2:AY15) -> 82622022 | BA16: =SUM(BA2:BA15) -> 173612851 | BC16: =SUM(BC2:BC15) -> 122399951 | BE16: =SUM(BE2:BE15) -> 342347075 | BG16: =SUM(BG2:BG15) -> 212000000 | BI16: =SUM(BI2:BI15) -> 315149921
J17: - | N17: BU 10 Agt 2021 | O17: 10801818 | U17: =U16-U14 -> 1126818 | V17: 33768838 | X17: CC Mandiri Fadli | Y17: 2000000 | AB17: 128445642
AN18: keb 16 Nov 21 | AO18: 113117500
D20: 88932100 | AW20: =AW16-250000000 -> 65470701
D21: 165179000
B38: CAPITAL | J38: - | N38: sisa | O38: =O16-O17 -> 4851311 | V38: =L16-V17 -> 24329112 | X38: fee driver trisno | Y38: 75000
A39: 1 | B39: DEPOSITO HSBC | H39: =[1]Tabungan!D30+[1]Tabungan!D36+[1]Tabungan!D37 -> 360000000 | J39: - | N39: Corp | O39: ='[2]Biaya Corporate-update Agt'!$H$5 -> 0 | S39: =O39-O2 -> -2310439 | U39: 9525203 | X39: admin | Y39: 13000
A40: 2 | B40: DEPOSITO DBS | H40: =[1]Tabungan!D20 -> 100000000 | J40: - | N40: sisa | O40: =O38-O39 -> 4851311 | U40: =U16-U39 -> 1276615 | X40: lysit | Y40: 2500000 | AG40: Fadli240977bagus
A41: 3 | B41: DEPOSITO OCBC | H41: =[1]Tabungan!D24 -> 25000000 | J41: - | X41: andre BKN | Y41: 12885000 | AB41: =O17-6200000 -> 4601818
A42: 4 | B42: DEPOSITO BRI | H42: =[1]Tabungan!D33 -> 50000000 | J42: - | X42: PCR Add kasbon Citibank | Y42: ?
A43: 5 | B43: HOLD BRI - HCML 21 des'20 - 20 mar'22 | H43: =E10 -> 234575375
A44: 6 | B44: HOLD BRI - IESR 24 agt-24 okt | H44: 120000000
A45: TOTAL CAPITAL | H45: =SUM(H39:H44) -> 889575375
A46: GRAND TOTAL | H46: =H16+H45 -> 942244352
C51: keep utk Gaji juli'21 | E51: keep utk Gaji juli'21 | F51: 73000000 | G51: =F51 -> 73000000
C52: sisa dana : | E52: sisa dana : | F52: =F16-F51 -> -102194876 | G52: =G16-G51 -> -109347707
C54: Expenses Juli yang belum dibayar : | E54: Expenses Juli yang belum dibayar :
B55: 1 | C55: CC HSBC lama - 4439 (Min Payment) | D55: Corp | E55: CC HSBC lama - 4439 (Min Payment) | G55: ='[3]tag cc hsbc lama 4439'!F48 -> 2551810.5
B56: 2 | C56: CC HSBC baru - 6604 | D56: Corp | E56: CC HSBC baru - 6604 | G56: ='[3]tag cc hsbc baru 6604'!F60 -> 807643
B57: 3 | C57: CC bri platinum 9007 (Min Payment) | D57: BU | E57: CC bri platinum 9007 (Min Payment) | G57: ='[3]tag cc bri platinum 9007'!G27 -> 3635376
B58: 4 | C58: Tag Grab Juli 21 (tunggu info dr bas) | D58: BU | E58: Tag Grab Juli 21 (tunggu info dr bas) | G58: 3756855
G59: =SUM(G55:G58) -> 10751684
C61: Kekurangan dana : | E61: Kekurangan dana : | G61: =G52-G59 -> -1.2009939e+08

Sheet 20mar-BALI
D1: 1 | E1: 2 | F1: 3 | G1: 4 | H1: 5 | I1: 6 | K1: 7 | L1: 8 | M1: 9 | N1: 10 | O1: 11 | P1: 12 | Q1: 13 | R1: 14 | S1: 15 | T1: 16 | U1: 17 | V1: 18 | W1: 19 | X1: 20 | Y1: 21 | Z1: 22 | AA1: 23 | AB1: 24 | AC1: 25 | AD1: 26 | AE1: 27 | AF1: 28 | AG1: 29 | AH1: 30
D2: MRP | F2: SAKTI | R2: UK | T2: NADI/WNN | X2: YUKTI | Z2: WISATA | AD2: BCA | AE2: WNS CABANG BALI
A3: Tgl | B3: Ket | C3: Total | D3: CIMB | E3: BRI | F3: BRI | G3: MANDIRI | H3: OCBC -IDR | I3: OCBC - USD | J3: OCBC - EUR | K3: UOB | L3: BCA SYARIAH 995 | M3: BCA SYARIAH 998 | N3: BNI 791 | O3: BNI 793 | P3: BNI 943 | Q3: BNI 316 | R3: BRI | S3: OCBC | T3: OCBC - IDR | U3: OCBC - USD | V3: CIMB | W3: BRI | X3: MANDIRI | Y3: BRI | Z3: MAYBANK | AA3: BCA | AB3: OCBC | AC3: BCA SYARIAH | AD3: FADLI FAHMI ALI | AE3: MAYBANK | AF3: DANAMON | AG3: BNI 595 | AH3: BNI 950
A4: 45736 | B4: Saldo Riil | C4: =SUM(D4:AH4) -> 5064796 | AF4: 5064796
B5: Saldo Dipake | C5: =SUM(D5:AH5) -> 5064796 | AF5: =AF4 -> 5064796
